<SceneObjectGroup><SceneObjectPart xmlns:xsi="http://www.w3.org/2001/XMLSchema-instance" xmlns:xsd="http://www.w3.org/2001/XMLSchema"><AllowedDrop>false</AllowedDrop><CreatorID><UUID>02230640-aa67-463c-a786-b62705f895d6</UUID></CreatorID><CreatorData>http://sacrarium24.ru:8002/;Sanctual Heart</CreatorData><FolderID><UUID>a40aad41-2f07-4ed8-a1ec-ef816f56e106</UUID></FolderID><InventorySerial>6</InventorySerial><TaskInventory><TaskInventoryItem><AssetID><UUID>a50d92fb-99db-48db-9cd8-1938484242e5</UUID></AssetID><BasePermissions>581632</BasePermissions><CreationDate>1547509416</CreationDate><CreatorID><UUID>02230640-aa67-463c-a786-b62705f895d6</UUID></CreatorID><Description>2019-01-15 00:43:41 lsl2 script</Description><EveryonePermissions>0</EveryonePermissions><Flags>0</Flags><GroupID><UUID>f8d438d7-257a-4111-b2d5-fe602171e0e5</UUID></GroupID><GroupPermissions>0</GroupPermissions><InvType>10</InvType><ItemID><UUID>4aff936e-1a58-4d2b-9aab-a3df9a1778ce</UUID></ItemID><OldItemID><UUID>00000000-0000-0000-0000-000000000000</UUID></OldItemID><LastOwnerID><UUID>02230640-aa67-463c-a786-b62705f895d6</UUID></LastOwnerID><Name>Extras</Name><NextPermissions>581632</NextPermissions><OwnerID><UUID>9e38a2fd-e368-4268-9b6d-6d37fbfb9884</UUID></OwnerID><CurrentPermissions>581632</CurrentPermissions><ParentID><UUID>a40aad41-2f07-4ed8-a1ec-ef816f56e106</UUID></ParentID><ParentPartID><UUID>a40aad41-2f07-4ed8-a1ec-ef816f56e106</UUID></ParentPartID><PermsGranter><UUID>00000000-0000-0000-0000-000000000000</UUID></PermsGranter><PermsMask>0</PermsMask><Type>10</Type><OwnerChanged>false</OwnerChanged></TaskInventoryItem><TaskInventoryItem><AssetID><UUID>b77cfdec-f2d6-4ff5-82cb-98d2ae554165</UUID></AssetID><BasePermissions>581632</BasePermissions><CreationDate>1547509821</CreationDate><CreatorID><UUID>02230640-aa67-463c-a786-b62705f895d6</UUID></CreatorID><Description>(No Description)</Description><EveryonePermissions>0</EveryonePermissions><Flags>0</Flags><GroupID><UUID>f8d438d7-257a-4111-b2d5-fe602171e0e5</UUID></GroupID><GroupPermissions>0</GroupPermissions><InvType>6</InvType><ItemID><UUID>a06f372f-9352-4f54-80da-ecf196f73a9a</UUID></ItemID><OldItemID><UUID>00000000-0000-0000-0000-000000000000</UUID></OldItemID><LastOwnerID><UUID>02230640-aa67-463c-a786-b62705f895d6</UUID></LastOwnerID><Name>Female magazine</Name><NextPermissions>581632</NextPermissions><OwnerID><UUID>9e38a2fd-e368-4268-9b6d-6d37fbfb9884</UUID></OwnerID><CurrentPermissions>581632</CurrentPermissions><ParentID><UUID>a40aad41-2f07-4ed8-a1ec-ef816f56e106</UUID></ParentID><ParentPartID><UUID>a40aad41-2f07-4ed8-a1ec-ef816f56e106</UUID></ParentPartID><PermsGranter><UUID>00000000-0000-0000-0000-000000000000</UUID></PermsGranter><PermsMask>0</PermsMask><Type>6</Type><OwnerChanged>false</OwnerChanged></TaskInventoryItem><TaskInventoryItem><AssetID><UUID>90f26f3c-f9eb-4a21-ba86-cc4d2c41a068</UUID></AssetID><BasePermissions>581632</BasePermissions><CreationDate>1547509821</CreationDate><CreatorID><UUID>02230640-aa67-463c-a786-b62705f895d6</UUID></CreatorID><Description>(No Description)</Description><EveryonePermissions>0</EveryonePermissions><Flags>0</Flags><GroupID><UUID>f8d438d7-257a-4111-b2d5-fe602171e0e5</UUID></GroupID><GroupPermissions>0</GroupPermissions><InvType>6</InvType><ItemID><UUID>279ff6d4-60d7-4f0c-a8fd-03aad6ce4bc3</UUID></ItemID><OldItemID><UUID>00000000-0000-0000-0000-000000000000</UUID></OldItemID><LastOwnerID><UUID>02230640-aa67-463c-a786-b62705f895d6</UUID></LastOwnerID><Name>Male magazine</Name><NextPermissions>581632</NextPermissions><OwnerID><UUID>9e38a2fd-e368-4268-9b6d-6d37fbfb9884</UUID></OwnerID><CurrentPermissions>581632</CurrentPermissions><ParentID><UUID>a40aad41-2f07-4ed8-a1ec-ef816f56e106</UUID></ParentID><ParentPartID><UUID>a40aad41-2f07-4ed8-a1ec-ef816f56e106</UUID></ParentPartID><PermsGranter><UUID>00000000-0000-0000-0000-000000000000</UUID></PermsGranter><PermsMask>0</PermsMask><Type>6</Type><OwnerChanged>false</OwnerChanged></TaskInventoryItem><TaskInventoryItem><AssetID><UUID>6e04debc-18eb-42eb-9955-a638d2c6e7e7</UUID></AssetID><BasePermissions>581632</BasePermissions><CreationDate>1547509646</CreationDate><CreatorID><UUID>02230640-aa67-463c-a786-b62705f895d6</UUID></CreatorID><Description>toilet_male__vomit</Description><EveryonePermissions>0</EveryonePermissions><Flags>0</Flags><GroupID><UUID>f8d438d7-257a-4111-b2d5-fe602171e0e5</UUID></GroupID><GroupPermissions>0</GroupPermissions><InvType>19</InvType><ItemID><UUID>b3c7c983-b411-4c33-aa4e-158b95b51065</UUID></ItemID><OldItemID><UUID>00000000-0000-0000-0000-000000000000</UUID></OldItemID><LastOwnerID><UUID>02230640-aa67-463c-a786-b62705f895d6</UUID></LastOwnerID><Name>toilet_male__vomit</Name><NextPermissions>581632</NextPermissions><OwnerID><UUID>9e38a2fd-e368-4268-9b6d-6d37fbfb9884</UUID></OwnerID><CurrentPermissions>581632</CurrentPermissions><ParentID><UUID>a40aad41-2f07-4ed8-a1ec-ef816f56e106</UUID></ParentID><ParentPartID><UUID>a40aad41-2f07-4ed8-a1ec-ef816f56e106</UUID></ParentPartID><PermsGranter><UUID>00000000-0000-0000-0000-000000000000</UUID></PermsGranter><PermsMask>0</PermsMask><Type>20</Type><OwnerChanged>false</OwnerChanged></TaskInventoryItem><TaskInventoryItem><AssetID><UUID>0f07e91b-2bad-4d4f-a829-6bd9b11a1147</UUID></AssetID><BasePermissions>581632</BasePermissions><CreationDate>1547509639</CreationDate><CreatorID><UUID>02230640-aa67-463c-a786-b62705f895d6</UUID></CreatorID><Description>Male_toilet</Description><EveryonePermissions>0</EveryonePermissions><Flags>0</Flags><GroupID><UUID>f8d438d7-257a-4111-b2d5-fe602171e0e5</UUID></GroupID><GroupPermissions>0</GroupPermissions><InvType>19</InvType><ItemID><UUID>a39f5d79-7d7b-4889-84b8-a9d0feeceeb1</UUID></ItemID><OldItemID><UUID>00000000-0000-0000-0000-000000000000</UUID></OldItemID><LastOwnerID><UUID>02230640-aa67-463c-a786-b62705f895d6</UUID></LastOwnerID><Name>Male_toilet</Name><NextPermissions>581632</NextPermissions><OwnerID><UUID>9e38a2fd-e368-4268-9b6d-6d37fbfb9884</UUID></OwnerID><CurrentPermissions>581632</CurrentPermissions><ParentID><UUID>a40aad41-2f07-4ed8-a1ec-ef816f56e106</UUID></ParentID><ParentPartID><UUID>a40aad41-2f07-4ed8-a1ec-ef816f56e106</UUID></ParentPartID><PermsGranter><UUID>00000000-0000-0000-0000-000000000000</UUID></PermsGranter><PermsMask>0</PermsMask><Type>20</Type><OwnerChanged>false</OwnerChanged></TaskInventoryItem><TaskInventoryItem><AssetID><UUID>d21a70f7-4da0-495b-8f64-b1373bc523d8</UUID></AssetID><BasePermissions>581632</BasePermissions><CreationDate>1547509644</CreationDate><CreatorID><UUID>02230640-aa67-463c-a786-b62705f895d6</UUID></CreatorID><Description>toilet_female_vomit</Description><EveryonePermissions>0</EveryonePermissions><Flags>0</Flags><GroupID><UUID>f8d438d7-257a-4111-b2d5-fe602171e0e5</UUID></GroupID><GroupPermissions>0</GroupPermissions><InvType>19</InvType><ItemID><UUID>fb63dd89-0a25-4530-8265-08aa014e94b1</UUID></ItemID><OldItemID><UUID>00000000-0000-0000-0000-000000000000</UUID></OldItemID><LastOwnerID><UUID>02230640-aa67-463c-a786-b62705f895d6</UUID></LastOwnerID><Name>toilet_female_vomit</Name><NextPermissions>581632</NextPermissions><OwnerID><UUID>9e38a2fd-e368-4268-9b6d-6d37fbfb9884</UUID></OwnerID><CurrentPermissions>581632</CurrentPermissions><ParentID><UUID>a40aad41-2f07-4ed8-a1ec-ef816f56e106</UUID></ParentID><ParentPartID><UUID>a40aad41-2f07-4ed8-a1ec-ef816f56e106</UUID></ParentPartID><PermsGranter><UUID>00000000-0000-0000-0000-000000000000</UUID></PermsGranter><PermsMask>0</PermsMask><Type>20</Type><OwnerChanged>false</OwnerChanged></TaskInventoryItem><TaskInventoryItem><AssetID><UUID>5bfad441-6acc-46f5-95b7-5e9d6bcfc8b3</UUID></AssetID><BasePermissions>581632</BasePermissions><CreationDate>1547509643</CreationDate><CreatorID><UUID>02230640-aa67-463c-a786-b62705f895d6</UUID></CreatorID><Description>peemale</Description><EveryonePermissions>0</EveryonePermissions><Flags>0</Flags><GroupID><UUID>f8d438d7-257a-4111-b2d5-fe602171e0e5</UUID></GroupID><GroupPermissions>0</GroupPermissions><InvType>19</InvType><ItemID><UUID>d9e0e9ad-eb0f-4d70-9307-9396d61f1d4a</UUID></ItemID><OldItemID><UUID>00000000-0000-0000-0000-000000000000</UUID></OldItemID><LastOwnerID><UUID>02230640-aa67-463c-a786-b62705f895d6</UUID></LastOwnerID><Name>peemale</Name><NextPermissions>581632</NextPermissions><OwnerID><UUID>9e38a2fd-e368-4268-9b6d-6d37fbfb9884</UUID></OwnerID><CurrentPermissions>581632</CurrentPermissions><ParentID><UUID>a40aad41-2f07-4ed8-a1ec-ef816f56e106</UUID></ParentID><ParentPartID><UUID>a40aad41-2f07-4ed8-a1ec-ef816f56e106</UUID></ParentPartID><PermsGranter><UUID>00000000-0000-0000-0000-000000000000</UUID></PermsGranter><PermsMask>0</PermsMask><Type>20</Type><OwnerChanged>false</OwnerChanged></TaskInventoryItem><TaskInventoryItem><AssetID><UUID>9c7fe6ff-9482-423b-adcb-95dc3e575bbb</UUID></AssetID><BasePermissions>581632</BasePermissions><CreationDate>1547509638</CreationDate><CreatorID><UUID>02230640-aa67-463c-a786-b62705f895d6</UUID></CreatorID><Description>Female_toilet</Description><EveryonePermissions>0</EveryonePermissions><Flags>0</Flags><GroupID><UUID>f8d438d7-257a-4111-b2d5-fe602171e0e5</UUID></GroupID><GroupPermissions>0</GroupPermissions><InvType>19</InvType><ItemID><UUID>8c978295-ed29-4468-9b44-1065cad2baed</UUID></ItemID><OldItemID><UUID>00000000-0000-0000-0000-000000000000</UUID></OldItemID><LastOwnerID><UUID>02230640-aa67-463c-a786-b62705f895d6</UUID></LastOwnerID><Name>Female_toilet</Name><NextPermissions>581632</NextPermissions><OwnerID><UUID>9e38a2fd-e368-4268-9b6d-6d37fbfb9884</UUID></OwnerID><CurrentPermissions>581632</CurrentPermissions><ParentID><UUID>a40aad41-2f07-4ed8-a1ec-ef816f56e106</UUID></ParentID><ParentPartID><UUID>a40aad41-2f07-4ed8-a1ec-ef816f56e106</UUID></ParentPartID><PermsGranter><UUID>00000000-0000-0000-0000-000000000000</UUID></PermsGranter><PermsMask>0</PermsMask><Type>20</Type><OwnerChanged>false</OwnerChanged></TaskInventoryItem><TaskInventoryItem><AssetID><UUID>0d9c2b2a-978f-4657-a7c6-3497f2ed230f</UUID></AssetID><BasePermissions>581632</BasePermissions><CreationDate>1547509641</CreationDate><CreatorID><UUID>02230640-aa67-463c-a786-b62705f895d6</UUID></CreatorID><Description>peeing_looped</Description><EveryonePermissions>0</EveryonePermissions><Flags>0</Flags><GroupID><UUID>f8d438d7-257a-4111-b2d5-fe602171e0e5</UUID></GroupID><GroupPermissions>0</GroupPermissions><InvType>1</InvType><ItemID><UUID>96039b04-8111-48b9-9dcd-600306a21e50</UUID></ItemID><OldItemID><UUID>00000000-0000-0000-0000-000000000000</UUID></OldItemID><LastOwnerID><UUID>02230640-aa67-463c-a786-b62705f895d6</UUID></LastOwnerID><Name>peeing_looped</Name><NextPermissions>581632</NextPermissions><OwnerID><UUID>9e38a2fd-e368-4268-9b6d-6d37fbfb9884</UUID></OwnerID><CurrentPermissions>581632</CurrentPermissions><ParentID><UUID>a40aad41-2f07-4ed8-a1ec-ef816f56e106</UUID></ParentID><ParentPartID><UUID>a40aad41-2f07-4ed8-a1ec-ef816f56e106</UUID></ParentPartID><PermsGranter><UUID>00000000-0000-0000-0000-000000000000</UUID></PermsGranter><PermsMask>0</PermsMask><Type>1</Type><OwnerChanged>false</OwnerChanged></TaskInventoryItem><TaskInventoryItem><AssetID><UUID>4cef5c11-c8eb-0b90-fb37-21f85fe07077</UUID></AssetID><BasePermissions>581632</BasePermissions><CreationDate>1547509663</CreationDate><CreatorID><UUID>02230640-aa67-463c-a786-b62705f895d6</UUID></CreatorID><Description>2019-01-15 00:47:43 note card</Description><EveryonePermissions>0</EveryonePermissions><Flags>0</Flags><GroupID><UUID>f8d438d7-257a-4111-b2d5-fe602171e0e5</UUID></GroupID><GroupPermissions>0</GroupPermissions><InvType>7</InvType><ItemID><UUID>a8e1832c-1941-489d-b01f-93fa297519d6</UUID></ItemID><OldItemID><UUID>00000000-0000-0000-0000-000000000000</UUID></OldItemID><LastOwnerID><UUID>02230640-aa67-463c-a786-b62705f895d6</UUID></LastOwnerID><Name>AVpos</Name><NextPermissions>581632</NextPermissions><OwnerID><UUID>9e38a2fd-e368-4268-9b6d-6d37fbfb9884</UUID></OwnerID><CurrentPermissions>581632</CurrentPermissions><ParentID><UUID>a40aad41-2f07-4ed8-a1ec-ef816f56e106</UUID></ParentID><ParentPartID><UUID>a40aad41-2f07-4ed8-a1ec-ef816f56e106</UUID></ParentPartID><PermsGranter><UUID>00000000-0000-0000-0000-000000000000</UUID></PermsGranter><PermsMask>0</PermsMask><Type>7</Type><OwnerChanged>false</OwnerChanged></TaskInventoryItem><TaskInventoryItem><AssetID><UUID>b7b379db-c22d-4bea-b27f-a15ba1836283</UUID></AssetID><BasePermissions>581632</BasePermissions><CreationDate>1547509637</CreationDate><CreatorID><UUID>02230640-aa67-463c-a786-b62705f895d6</UUID></CreatorID><Description>F_pee</Description><EveryonePermissions>0</EveryonePermissions><Flags>0</Flags><GroupID><UUID>f8d438d7-257a-4111-b2d5-fe602171e0e5</UUID></GroupID><GroupPermissions>0</GroupPermissions><InvType>19</InvType><ItemID><UUID>40f02642-390f-4f93-846b-f72e38f2a105</UUID></ItemID><OldItemID><UUID>00000000-0000-0000-0000-000000000000</UUID></OldItemID><LastOwnerID><UUID>02230640-aa67-463c-a786-b62705f895d6</UUID></LastOwnerID><Name>F_pee</Name><NextPermissions>581632</NextPermissions><OwnerID><UUID>9e38a2fd-e368-4268-9b6d-6d37fbfb9884</UUID></OwnerID><CurrentPermissions>581632</CurrentPermissions><ParentID><UUID>a40aad41-2f07-4ed8-a1ec-ef816f56e106</UUID></ParentID><ParentPartID><UUID>a40aad41-2f07-4ed8-a1ec-ef816f56e106</UUID></ParentPartID><PermsGranter><UUID>00000000-0000-0000-0000-000000000000</UUID></PermsGranter><PermsMask>0</PermsMask><Type>20</Type><OwnerChanged>false</OwnerChanged></TaskInventoryItem><TaskInventoryItem><AssetID><UUID>b281a805-a2e3-46ee-bc92-bb6628f5ed44</UUID></AssetID><BasePermissions>581632</BasePermissions><CreationDate>1520531502</CreationDate><CreatorID><UUID>02230640-aa67-463c-a786-b62705f895d6</UUID></CreatorID><Description>2018-03-08 18:51:43 lsl2 script</Description><EveryonePermissions>0</EveryonePermissions><Flags>0</Flags><GroupID><UUID>f8d438d7-257a-4111-b2d5-fe602171e0e5</UUID></GroupID><GroupPermissions>0</GroupPermissions><InvType>10</InvType><ItemID><UUID>7a0a3c9f-1f44-4834-9a99-5b3a681cbe46</UUID></ItemID><OldItemID><UUID>00000000-0000-0000-0000-000000000000</UUID></OldItemID><LastOwnerID><UUID>02230640-aa67-463c-a786-b62705f895d6</UUID></LastOwnerID><Name>[AV]prop</Name><NextPermissions>581632</NextPermissions><OwnerID><UUID>9e38a2fd-e368-4268-9b6d-6d37fbfb9884</UUID></OwnerID><CurrentPermissions>581632</CurrentPermissions><ParentID><UUID>a40aad41-2f07-4ed8-a1ec-ef816f56e106</UUID></ParentID><ParentPartID><UUID>a40aad41-2f07-4ed8-a1ec-ef816f56e106</UUID></ParentPartID><PermsGranter><UUID>00000000-0000-0000-0000-000000000000</UUID></PermsGranter><PermsMask>0</PermsMask><Type>10</Type><OwnerChanged>false</OwnerChanged></TaskInventoryItem><TaskInventoryItem><AssetID><UUID>85c86a5c-112e-4a16-bf84-2b62ddbf80c0</UUID></AssetID><BasePermissions>581632</BasePermissions><CreationDate>1520531413</CreationDate><CreatorID><UUID>02230640-aa67-463c-a786-b62705f895d6</UUID></CreatorID><Description>2018-03-08 18:50:14 lsl2 script</Description><EveryonePermissions>0</EveryonePermissions><Flags>0</Flags><GroupID><UUID>f8d438d7-257a-4111-b2d5-fe602171e0e5</UUID></GroupID><GroupPermissions>0</GroupPermissions><InvType>10</InvType><ItemID><UUID>2db2c871-b76c-4608-b652-bb9bcd4d50e3</UUID></ItemID><OldItemID><UUID>00000000-0000-0000-0000-000000000000</UUID></OldItemID><LastOwnerID><UUID>02230640-aa67-463c-a786-b62705f895d6</UUID></LastOwnerID><Name>[AV]sitB</Name><NextPermissions>581632</NextPermissions><OwnerID><UUID>9e38a2fd-e368-4268-9b6d-6d37fbfb9884</UUID></OwnerID><CurrentPermissions>581632</CurrentPermissions><ParentID><UUID>a40aad41-2f07-4ed8-a1ec-ef816f56e106</UUID></ParentID><ParentPartID><UUID>a40aad41-2f07-4ed8-a1ec-ef816f56e106</UUID></ParentPartID><PermsGranter><UUID>00000000-0000-0000-0000-000000000000</UUID></PermsGranter><PermsMask>0</PermsMask><Type>10</Type><OwnerChanged>false</OwnerChanged></TaskInventoryItem><TaskInventoryItem><AssetID><UUID>058da35f-cece-41e1-be37-5451416b32ca</UUID></AssetID><BasePermissions>581632</BasePermissions><CreationDate>1520531582</CreationDate><CreatorID><UUID>02230640-aa67-463c-a786-b62705f895d6</UUID></CreatorID><Description /><EveryonePermissions>524288</EveryonePermissions><Flags>0</Flags><GroupID><UUID>f8d438d7-257a-4111-b2d5-fe602171e0e5</UUID></GroupID><GroupPermissions>0</GroupPermissions><InvType>6</InvType><ItemID><UUID>5e399420-931e-4a06-8290-164b86ba16c3</UUID></ItemID><OldItemID><UUID>00000000-0000-0000-0000-000000000000</UUID></OldItemID><LastOwnerID><UUID>02230640-aa67-463c-a786-b62705f895d6</UUID></LastOwnerID><Name>[AV]helper</Name><NextPermissions>581632</NextPermissions><OwnerID><UUID>9e38a2fd-e368-4268-9b6d-6d37fbfb9884</UUID></OwnerID><CurrentPermissions>581632</CurrentPermissions><ParentID><UUID>a40aad41-2f07-4ed8-a1ec-ef816f56e106</UUID></ParentID><ParentPartID><UUID>a40aad41-2f07-4ed8-a1ec-ef816f56e106</UUID></ParentPartID><PermsGranter><UUID>00000000-0000-0000-0000-000000000000</UUID></PermsGranter><PermsMask>0</PermsMask><Type>6</Type><OwnerChanged>false</OwnerChanged></TaskInventoryItem><TaskInventoryItem><AssetID><UUID>36932d60-7cbd-457c-bb51-c087b59cc380</UUID></AssetID><BasePermissions>581632</BasePermissions><CreationDate>1520531393</CreationDate><CreatorID><UUID>02230640-aa67-463c-a786-b62705f895d6</UUID></CreatorID><Description>2018-03-08 18:49:54 lsl2 script</Description><EveryonePermissions>0</EveryonePermissions><Flags>0</Flags><GroupID><UUID>f8d438d7-257a-4111-b2d5-fe602171e0e5</UUID></GroupID><GroupPermissions>0</GroupPermissions><InvType>10</InvType><ItemID><UUID>26f4a5b1-effc-4cf4-906b-1bf225a9ca06</UUID></ItemID><OldItemID><UUID>00000000-0000-0000-0000-000000000000</UUID></OldItemID><LastOwnerID><UUID>02230640-aa67-463c-a786-b62705f895d6</UUID></LastOwnerID><Name>[AV]sitA</Name><NextPermissions>581632</NextPermissions><OwnerID><UUID>9e38a2fd-e368-4268-9b6d-6d37fbfb9884</UUID></OwnerID><CurrentPermissions>581632</CurrentPermissions><ParentID><UUID>a40aad41-2f07-4ed8-a1ec-ef816f56e106</UUID></ParentID><ParentPartID><UUID>a40aad41-2f07-4ed8-a1ec-ef816f56e106</UUID></ParentPartID><PermsGranter><UUID>9e38a2fd-e368-4268-9b6d-6d37fbfb9884</UUID></PermsGranter><PermsMask>16</PermsMask><Type>10</Type><OwnerChanged>false</OwnerChanged></TaskInventoryItem><TaskInventoryItem><AssetID><UUID>648ec53e-13ff-46ed-aaed-bdd80a976f92</UUID></AssetID><BasePermissions>581632</BasePermissions><CreationDate>1520531252</CreationDate><CreatorID><UUID>02230640-aa67-463c-a786-b62705f895d6</UUID></CreatorID><Description>2018-03-08 18:47:33 lsl2 script</Description><EveryonePermissions>0</EveryonePermissions><Flags>0</Flags><GroupID><UUID>f8d438d7-257a-4111-b2d5-fe602171e0e5</UUID></GroupID><GroupPermissions>0</GroupPermissions><InvType>10</InvType><ItemID><UUID>ee8b7066-1646-4b47-91ee-4e0e294f88c2</UUID></ItemID><OldItemID><UUID>00000000-0000-0000-0000-000000000000</UUID></OldItemID><LastOwnerID><UUID>02230640-aa67-463c-a786-b62705f895d6</UUID></LastOwnerID><Name>[AV]adjuster</Name><NextPermissions>581632</NextPermissions><OwnerID><UUID>9e38a2fd-e368-4268-9b6d-6d37fbfb9884</UUID></OwnerID><CurrentPermissions>581632</CurrentPermissions><ParentID><UUID>a40aad41-2f07-4ed8-a1ec-ef816f56e106</UUID></ParentID><ParentPartID><UUID>a40aad41-2f07-4ed8-a1ec-ef816f56e106</UUID></ParentPartID><PermsGranter><UUID>00000000-0000-0000-0000-000000000000</UUID></PermsGranter><PermsMask>0</PermsMask><Type>10</Type><OwnerChanged>false</OwnerChanged></TaskInventoryItem></TaskInventory><UUID><UUID>a40aad41-2f07-4ed8-a1ec-ef816f56e106</UUID></UUID><LocalId>1031035992</LocalId><Name>Modern Bathroom - Toilet</Name><Material>3</Material><PassTouches>false</PassTouches><PassCollisions>false</PassCollisions><RegionHandle>6734508721696000</RegionHandle><ScriptAccessPin>0</ScriptAccessPin><GroupPosition><X>190.2939</X><Y>164.1271</Y><Z>26.93738</Z></GroupPosition><OffsetPosition><X>0</X><Y>0</Y><Z>0</Z></OffsetPosition><RotationOffset><X>0</X><Y>0</Y><Z>-0.7071068</Z><W>0.7071067</W></RotationOffset><Velocity><X>0</X><Y>0</Y><Z>0</Z></Velocity><AngularVelocity><X>0</X><Y>0</Y><Z>0</Z></AngularVelocity><Acceleration><X>0</X><Y>0</Y><Z>0</Z></Acceleration><Description /><Color><R>255</R><G>255</G><B>255</B><A>255</A></Color><Text /><SitName /><TouchName /><LinkNum>1</LinkNum><ClickAction>1</ClickAction><Shape><ProfileCurve>1</ProfileCurve><TextureEntry>3zkzmH1hQqCPtqm9O6t//RAX5Efn11NOwoRAyXY24d5UCPdp1kPCFEJduwu6wEZMbe8EmlyO8eV3SymMEd5bDYEfsgLudxvAi4hDd4dGLuQUNtWvAXx1vxVSzEestJ92iMZMODIAAAAAAAAAAIA/AAAAgD8AAAAAAAAAAAAAAAAAAAAAAAAAAAAAAAAAAAAAAAAAAAA=</TextureEntry><ExtraParams>ATAAEQAAAGaTqBvc60imgoxGDSPGRGQF</ExtraParams><PathBegin>0</PathBegin><PathCurve>16</PathCurve><PathEnd>0</PathEnd><PathRadiusOffset>0</PathRadiusOffset><PathRevolutions>0</PathRevolutions><PathScaleX>100</PathScaleX><PathScaleY>100</PathScaleY><PathShearX>0</PathShearX><PathShearY>0</PathShearY><PathSkew>0</PathSkew><PathTaperX>0</PathTaperX><PathTaperY>0</PathTaperY><PathTwist>0</PathTwist><PathTwistBegin>0</PathTwistBegin><PCode>9</PCode><ProfileBegin>12500</ProfileBegin><ProfileEnd>0</ProfileEnd><ProfileHollow>27500</ProfileHollow><State>0</State><LastAttachPoint>0</LastAttachPoint><ProfileShape>Square</ProfileShape><HollowShape>Same</HollowShape><SculptTexture><UUID>6693a81b-dceb-48a6-828c-460d23c64464</UUID></SculptTexture><SculptType>5</SculptType><FlexiSoftness>0</FlexiSoftness><FlexiTension>0</FlexiTension><FlexiDrag>0</FlexiDrag><FlexiGravity>0</FlexiGravity><FlexiWind>0</FlexiWind><FlexiForceX>0</FlexiForceX><FlexiForceY>0</FlexiForceY><FlexiForceZ>0</FlexiForceZ><LightColorR>0</LightColorR><LightColorG>0</LightColorG><LightColorB>0</LightColorB><LightColorA>1</LightColorA><LightRadius>0</LightRadius><LightCutoff>0</LightCutoff><LightFalloff>0</LightFalloff><LightIntensity>1</LightIntensity><FlexiEntry>false</FlexiEntry><LightEntry>false</LightEntry><SculptEntry>true</SculptEntry></Shape><Scale><X>0.666007</X><Y>1.00835</Y><Z>1.08805</Z></Scale><SitTargetOrientation><X>0</X><Y>0</Y><Z>-0.7071068</Z><W>0.7071068</W></SitTargetOrientation><SitTargetPosition><X>-0.00549</X><Y>-0.1</Y><Z>0.41371</Z></SitTargetPosition><SitTargetPositionLL><X>-0.00549</X><Y>-0.1</Y><Z>0.41371</Z></SitTargetPositionLL><SitTargetOrientationLL><X>0</X><Y>0</Y><Z>-0.7071068</Z><W>0.7071068</W></SitTargetOrientationLL><ParentID>0</ParentID><CreationDate>1547509318</CreationDate><Category>0</Category><SalePrice>10</SalePrice><ObjectSaleType>0</ObjectSaleType><OwnershipCost>0</OwnershipCost><GroupID><UUID>f8d438d7-257a-4111-b2d5-fe602171e0e5</UUID></GroupID><OwnerID><UUID>9e38a2fd-e368-4268-9b6d-6d37fbfb9884</UUID></OwnerID><LastOwnerID><UUID>9e38a2fd-e368-4268-9b6d-6d37fbfb9884</UUID></LastOwnerID><RezzerID><UUID>9e38a2fd-e368-4268-9b6d-6d37fbfb9884</UUID></RezzerID><BaseMask>647168</BaseMask><OwnerMask>581632</OwnerMask><GroupMask>0</GroupMask><EveryoneMask>0</EveryoneMask><NextOwnerMask>581632</NextOwnerMask><Flags>Scripted</Flags><CollisionSound><UUID>00000000-0000-0000-0000-000000000000</UUID></CollisionSound><CollisionSoundVolume>0</CollisionSoundVolume><AttachedPos><X>0</X><Y>0</Y><Z>0</Z></AttachedPos><TextureAnimation></TextureAnimation><ParticleSystem></ParticleSystem><PayPrice0>-2</PayPrice0><PayPrice1>-2</PayPrice1><PayPrice2>-2</PayPrice2><PayPrice3>-2</PayPrice3><PayPrice4>-2</PayPrice4><Buoyancy>0</Buoyancy><Force><X>0</X><Y>0</Y><Z>0</Z></Force><Torque><X>0</X><Y>0</Y><Z>0</Z></Torque><VolumeDetectActive>false</VolumeDetectActive><PhysicsShapeType>0</PhysicsShapeType><CameraEyeOffset><X>0</X><Y>0</Y><Z>0</Z></CameraEyeOffset><CameraAtOffset><X>0</X><Y>0</Y><Z>0</Z></CameraAtOffset><SoundID><UUID>00000000-0000-0000-0000-000000000000</UUID></SoundID><SoundGain>0</SoundGain><SoundFlags>0</SoundFlags><SoundRadius>0</SoundRadius><SoundQueueing>false</SoundQueueing></SceneObjectPart><OtherParts><SceneObjectPart xmlns:xsi="http://www.w3.org/2001/XMLSchema-instance" xmlns:xsd="http://www.w3.org/2001/XMLSchema"><AllowedDrop>false</AllowedDrop><CreatorID><UUID>02230640-aa67-463c-a786-b62705f895d6</UUID></CreatorID><CreatorData>http://sacrarium24.ru:8002/;Sanctual Heart</CreatorData><FolderID><UUID>b9dc977a-aeb4-4436-ab10-469ee2a6fcae</UUID></FolderID><InventorySerial>1</InventorySerial><UUID><UUID>b9dc977a-aeb4-4436-ab10-469ee2a6fcae</UUID></UUID><LocalId>1031035993</LocalId><Name>Toilet</Name><Material>3</Material><PassTouches>false</PassTouches><PassCollisions>false</PassCollisions><RegionHandle>6734508721696000</RegionHandle><ScriptAccessPin>0</ScriptAccessPin><GroupPosition><X>190.2939</X><Y>164.1271</Y><Z>26.93738</Z></GroupPosition><OffsetPosition><X>-0.246048</X><Y>0.2139893</Y><Z>0.4464111</Z></OffsetPosition><RotationOffset><X>0.5</X><Y>-0.5</Y><Z>0.5</Z><W>0.5</W></RotationOffset><Velocity><X>0</X><Y>0</Y><Z>0</Z></Velocity><AngularVelocity><X>0</X><Y>0</Y><Z>0</Z></AngularVelocity><Acceleration><X>0</X><Y>0</Y><Z>0</Z></Acceleration><Description>(No Description)</Description><Color><R>0</R><G>0</G><B>0</B><A>255</A></Color><Text /><SitName /><TouchName /><LinkNum>2</LinkNum><ClickAction>1</ClickAction><Shape><ProfileCurve>1</ProfileCurve><TextureEntry>V0jezPYpRhyaNqNaIh/iHwQFCkBTxZZAya904Nmrz5xVAVd6zIGQvE2Ri82vbA8tMboAAAAAAAAAAIA/AAAAgD8AAAAAAAAAAAAAAAAAAAAAAAAAAAAAAAAAAAAAAAAAAAA=</TextureEntry><ExtraParams>ATAAEQAAAH/ZfnRcLkMtpdR0R8u8OKcF</ExtraParams><PathBegin>0</PathBegin><PathCurve>16</PathCurve><PathEnd>0</PathEnd><PathRadiusOffset>0</PathRadiusOffset><PathRevolutions>0</PathRevolutions><PathScaleX>100</PathScaleX><PathScaleY>100</PathScaleY><PathShearX>0</PathShearX><PathShearY>0</PathShearY><PathSkew>0</PathSkew><PathTaperX>0</PathTaperX><PathTaperY>0</PathTaperY><PathTwist>0</PathTwist><PathTwistBegin>0</PathTwistBegin><PCode>9</PCode><ProfileBegin>12500</ProfileBegin><ProfileEnd>0</ProfileEnd><ProfileHollow>27500</ProfileHollow><State>0</State><LastAttachPoint>0</LastAttachPoint><ProfileShape>Square</ProfileShape><HollowShape>Same</HollowShape><SculptTexture><UUID>7fd97e74-5c2e-432d-a5d4-7447cbbc38a7</UUID></SculptTexture><SculptType>5</SculptType><FlexiSoftness>0</FlexiSoftness><FlexiTension>0</FlexiTension><FlexiDrag>0</FlexiDrag><FlexiGravity>0</FlexiGravity><FlexiWind>0</FlexiWind><FlexiForceX>0</FlexiForceX><FlexiForceY>0</FlexiForceY><FlexiForceZ>0</FlexiForceZ><LightColorR>0</LightColorR><LightColorG>0</LightColorG><LightColorB>0</LightColorB><LightColorA>1</LightColorA><LightRadius>0</LightRadius><LightCutoff>0</LightCutoff><LightFalloff>0</LightFalloff><LightIntensity>1</LightIntensity><FlexiEntry>false</FlexiEntry><LightEntry>false</LightEntry><SculptEntry>true</SculptEntry></Shape><Scale><X>0.127567</X><Y>0.169731</Y><Z>0.156368</Z></Scale><SitTargetOrientation><X>0</X><Y>0</Y><Z>0</Z><W>1</W></SitTargetOrientation><SitTargetPosition><X>0</X><Y>0</Y><Z>0</Z></SitTargetPosition><SitTargetPositionLL><X>0</X><Y>0</Y><Z>0</Z></SitTargetPositionLL><SitTargetOrientationLL><X>0</X><Y>0</Y><Z>0</Z><W>1</W></SitTargetOrientationLL><ParentID>1031035992</ParentID><CreationDate>1547509318</CreationDate><Category>0</Category><SalePrice>10</SalePrice><ObjectSaleType>0</ObjectSaleType><OwnershipCost>0</OwnershipCost><GroupID><UUID>f8d438d7-257a-4111-b2d5-fe602171e0e5</UUID></GroupID><OwnerID><UUID>9e38a2fd-e368-4268-9b6d-6d37fbfb9884</UUID></OwnerID><LastOwnerID><UUID>9e38a2fd-e368-4268-9b6d-6d37fbfb9884</UUID></LastOwnerID><RezzerID><UUID>9e38a2fd-e368-4268-9b6d-6d37fbfb9884</UUID></RezzerID><BaseMask>647168</BaseMask><OwnerMask>581632</OwnerMask><GroupMask>0</GroupMask><EveryoneMask>0</EveryoneMask><NextOwnerMask>581632</NextOwnerMask><Flags>Scripted</Flags><CollisionSound><UUID>00000000-0000-0000-0000-000000000000</UUID></CollisionSound><CollisionSoundVolume>0</CollisionSoundVolume><AttachedPos><X>0</X><Y>0</Y><Z>0</Z></AttachedPos><TextureAnimation></TextureAnimation><ParticleSystem></ParticleSystem><PayPrice0>-2</PayPrice0><PayPrice1>-2</PayPrice1><PayPrice2>-2</PayPrice2><PayPrice3>-2</PayPrice3><PayPrice4>-2</PayPrice4><Buoyancy>0</Buoyancy><Force><X>0</X><Y>0</Y><Z>0</Z></Force><Torque><X>0</X><Y>0</Y><Z>0</Z></Torque><VolumeDetectActive>false</VolumeDetectActive><PhysicsShapeType>0</PhysicsShapeType><CameraEyeOffset><X>0</X><Y>0</Y><Z>0</Z></CameraEyeOffset><CameraAtOffset><X>0</X><Y>0</Y><Z>0</Z></CameraAtOffset><SoundID><UUID>00000000-0000-0000-0000-000000000000</UUID></SoundID><SoundGain>0</SoundGain><SoundFlags>0</SoundFlags><SoundRadius>0</SoundRadius><SoundQueueing>false</SoundQueueing></SceneObjectPart><SceneObjectPart xmlns:xsi="http://www.w3.org/2001/XMLSchema-instance" xmlns:xsd="http://www.w3.org/2001/XMLSchema"><AllowedDrop>false</AllowedDrop><CreatorID><UUID>02230640-aa67-463c-a786-b62705f895d6</UUID></CreatorID><CreatorData>http://sacrarium24.ru:8002/;Sanctual Heart</CreatorData><FolderID><UUID>f8ff0702-0133-4e1d-81cb-6f2dd7a3dc7d</UUID></FolderID><InventorySerial>1</InventorySerial><UUID><UUID>f8ff0702-0133-4e1d-81cb-6f2dd7a3dc7d</UUID></UUID><LocalId>1031035994</LocalId><Name>flap</Name><Material>3</Material><PassTouches>false</PassTouches><PassCollisions>false</PassCollisions><RegionHandle>6734508721696000</RegionHandle><ScriptAccessPin>0</ScriptAccessPin><GroupPosition><X>190.2939</X><Y>164.1271</Y><Z>26.93738</Z></GroupPosition><OffsetPosition><X>-0.0002670288</X><Y>0.2088623</Y><Z>0.0357666</Z></OffsetPosition><RotationOffset><X>0</X><Y>0</Y><Z>0</Z><W>1</W></RotationOffset><Velocity><X>0</X><Y>0</Y><Z>0</Z></Velocity><AngularVelocity><X>0</X><Y>0</Y><Z>0</Z></AngularVelocity><Acceleration><X>0</X><Y>0</Y><Z>0</Z></Acceleration><Description /><Color><R>0</R><G>0</G><B>0</B><A>255</A></Color><Text /><SitName /><TouchName /><LinkNum>3</LinkNum><ClickAction>1</ClickAction><Shape><ProfileCurve>1</ProfileCurve><TextureEntry>bgyCFSfCSXC9ov/Yy7II5wRq7Jw0QK9IBomNLOr5SrUmAqqEvldrq0hWiBZeBefnpjEBV3rMgZC8TZGLza9sDy0xugAAAAAAAAAAgD8AAACAPwAAAAAAAAAAAAAAAAAAAAAAAAAAAAAAAAAAAAAAAAAAAA==</TextureEntry><ExtraParams>ATAAEQAAAP7l37EstEx/s9xrckwQ2/8F</ExtraParams><PathBegin>0</PathBegin><PathCurve>16</PathCurve><PathEnd>0</PathEnd><PathRadiusOffset>0</PathRadiusOffset><PathRevolutions>0</PathRevolutions><PathScaleX>100</PathScaleX><PathScaleY>100</PathScaleY><PathShearX>0</PathShearX><PathShearY>0</PathShearY><PathSkew>0</PathSkew><PathTaperX>0</PathTaperX><PathTaperY>0</PathTaperY><PathTwist>0</PathTwist><PathTwistBegin>0</PathTwistBegin><PCode>9</PCode><ProfileBegin>12500</ProfileBegin><ProfileEnd>0</ProfileEnd><ProfileHollow>27500</ProfileHollow><State>0</State><LastAttachPoint>0</LastAttachPoint><ProfileShape>Square</ProfileShape><HollowShape>Same</HollowShape><SculptTexture><UUID>fee5dfb1-2cb4-4c7f-b3dc-6b724c10dbff</UUID></SculptTexture><SculptType>5</SculptType><FlexiSoftness>0</FlexiSoftness><FlexiTension>0</FlexiTension><FlexiDrag>0</FlexiDrag><FlexiGravity>0</FlexiGravity><FlexiWind>0</FlexiWind><FlexiForceX>0</FlexiForceX><FlexiForceY>0</FlexiForceY><FlexiForceZ>0</FlexiForceZ><LightColorR>0</LightColorR><LightColorG>0</LightColorG><LightColorB>0</LightColorB><LightColorA>1</LightColorA><LightRadius>0</LightRadius><LightCutoff>0</LightCutoff><LightFalloff>0</LightFalloff><LightIntensity>1</LightIntensity><FlexiEntry>false</FlexiEntry><LightEntry>false</LightEntry><SculptEntry>true</SculptEntry></Shape><Scale><X>0.512548</X><Y>1.41362</Y><Z>0.0479891</Z></Scale><SitTargetOrientation><X>0</X><Y>0</Y><Z>0</Z><W>1</W></SitTargetOrientation><SitTargetPosition><X>0</X><Y>0</Y><Z>0</Z></SitTargetPosition><SitTargetPositionLL><X>0</X><Y>0</Y><Z>0</Z></SitTargetPositionLL><SitTargetOrientationLL><X>0</X><Y>0</Y><Z>0</Z><W>1</W></SitTargetOrientationLL><ParentID>1031035992</ParentID><CreationDate>1547509318</CreationDate><Category>0</Category><SalePrice>0</SalePrice><ObjectSaleType>0</ObjectSaleType><OwnershipCost>0</OwnershipCost><GroupID><UUID>f8d438d7-257a-4111-b2d5-fe602171e0e5</UUID></GroupID><OwnerID><UUID>9e38a2fd-e368-4268-9b6d-6d37fbfb9884</UUID></OwnerID><LastOwnerID><UUID>9e38a2fd-e368-4268-9b6d-6d37fbfb9884</UUID></LastOwnerID><RezzerID><UUID>9e38a2fd-e368-4268-9b6d-6d37fbfb9884</UUID></RezzerID><BaseMask>647168</BaseMask><OwnerMask>581632</OwnerMask><GroupMask>0</GroupMask><EveryoneMask>0</EveryoneMask><NextOwnerMask>581632</NextOwnerMask><Flags>Scripted</Flags><CollisionSound><UUID>00000000-0000-0000-0000-000000000000</UUID></CollisionSound><CollisionSoundVolume>0</CollisionSoundVolume><AttachedPos><X>0</X><Y>0</Y><Z>0</Z></AttachedPos><TextureAnimation></TextureAnimation><ParticleSystem></ParticleSystem><PayPrice0>-2</PayPrice0><PayPrice1>-2</PayPrice1><PayPrice2>-2</PayPrice2><PayPrice3>-2</PayPrice3><PayPrice4>-2</PayPrice4><Buoyancy>0</Buoyancy><Force><X>0</X><Y>0</Y><Z>0</Z></Force><Torque><X>0</X><Y>0</Y><Z>0</Z></Torque><VolumeDetectActive>false</VolumeDetectActive><PhysicsShapeType>0</PhysicsShapeType><CameraEyeOffset><X>0</X><Y>0</Y><Z>0</Z></CameraEyeOffset><CameraAtOffset><X>0</X><Y>0</Y><Z>0</Z></CameraAtOffset><SoundID><UUID>00000000-0000-0000-0000-000000000000</UUID></SoundID><SoundGain>0</SoundGain><SoundFlags>0</SoundFlags><SoundRadius>0</SoundRadius><SoundQueueing>false</SoundQueueing></SceneObjectPart><SceneObjectPart xmlns:xsi="http://www.w3.org/2001/XMLSchema-instance" xmlns:xsd="http://www.w3.org/2001/XMLSchema"><AllowedDrop>false</AllowedDrop><CreatorID><UUID>02230640-aa67-463c-a786-b62705f895d6</UUID></CreatorID><CreatorData>http://sacrarium24.ru:8002/;Sanctual Heart</CreatorData><FolderID><UUID>97803e7d-c8cf-400e-ab8c-4bf4c1748e8d</UUID></FolderID><InventorySerial>1</InventorySerial><UUID><UUID>97803e7d-c8cf-400e-ab8c-4bf4c1748e8d</UUID></UUID><LocalId>1031035995</LocalId><Name>Toilet</Name><Material>3</Material><PassTouches>false</PassTouches><PassCollisions>false</PassCollisions><RegionHandle>6734508721696000</RegionHandle><ScriptAccessPin>0</ScriptAccessPin><GroupPosition><X>190.2939</X><Y>164.1271</Y><Z>26.93738</Z></GroupPosition><OffsetPosition><X>-0.003494263</X><Y>-0.04432678</Y><Z>0.05456543</Z></OffsetPosition><RotationOffset><X>0</X><Y>0</Y><Z>0</Z><W>1</W></RotationOffset><Velocity><X>0</X><Y>0</Y><Z>0</Z></Velocity><AngularVelocity><X>0</X><Y>0</Y><Z>0</Z></AngularVelocity><Acceleration><X>0</X><Y>0</Y><Z>0</Z></Acceleration><Description /><Color><R>0</R><G>0</G><B>0</B><A>255</A></Color><Text /><SitName /><TouchName /><LinkNum>4</LinkNum><ClickAction>1</ClickAction><Shape><ProfileCurve>1</ProfileCurve><TextureEntry>V0jezPYpRhyaNqNaIh/iHwHHy1UmSstPSLSC/5FnHvRGAAAAAAAAAACAPwAAAIA/AAAAAAAAAAAAAAAAAAAAAAAAAAAAAAAAAAAAAAAAAAAA</TextureEntry><ExtraParams>ATAAEQAAAMDoytxcAEkKhDbcGCwdzvsF</ExtraParams><PathBegin>0</PathBegin><PathCurve>16</PathCurve><PathEnd>0</PathEnd><PathRadiusOffset>0</PathRadiusOffset><PathRevolutions>0</PathRevolutions><PathScaleX>100</PathScaleX><PathScaleY>100</PathScaleY><PathShearX>0</PathShearX><PathShearY>0</PathShearY><PathSkew>0</PathSkew><PathTaperX>0</PathTaperX><PathTaperY>0</PathTaperY><PathTwist>0</PathTwist><PathTwistBegin>0</PathTwistBegin><PCode>9</PCode><ProfileBegin>12500</ProfileBegin><ProfileEnd>0</ProfileEnd><ProfileHollow>27500</ProfileHollow><State>0</State><LastAttachPoint>0</LastAttachPoint><ProfileShape>Square</ProfileShape><HollowShape>Same</HollowShape><SculptTexture><UUID>c0e8cadc-5c00-490a-8436-dc182c1dcefb</UUID></SculptTexture><SculptType>5</SculptType><FlexiSoftness>0</FlexiSoftness><FlexiTension>0</FlexiTension><FlexiDrag>0</FlexiDrag><FlexiGravity>0</FlexiGravity><FlexiWind>0</FlexiWind><FlexiForceX>0</FlexiForceX><FlexiForceY>0</FlexiForceY><FlexiForceZ>0</FlexiForceZ><LightColorR>0</LightColorR><LightColorG>0</LightColorG><LightColorB>0</LightColorB><LightColorA>1</LightColorA><LightRadius>0</LightRadius><LightCutoff>0</LightCutoff><LightFalloff>0</LightFalloff><LightIntensity>1</LightIntensity><FlexiEntry>false</FlexiEntry><LightEntry>false</LightEntry><SculptEntry>true</SculptEntry></Shape><Scale><X>0.809924</X><Y>1.1121</Y><Z>1.18828</Z></Scale><SitTargetOrientation><X>0</X><Y>0</Y><Z>0</Z><W>1</W></SitTargetOrientation><SitTargetPosition><X>0</X><Y>0</Y><Z>0</Z></SitTargetPosition><SitTargetPositionLL><X>0</X><Y>0</Y><Z>0</Z></SitTargetPositionLL><SitTargetOrientationLL><X>0</X><Y>0</Y><Z>0</Z><W>1</W></SitTargetOrientationLL><ParentID>1031035992</ParentID><CreationDate>1547509318</CreationDate><Category>0</Category><SalePrice>0</SalePrice><ObjectSaleType>0</ObjectSaleType><OwnershipCost>0</OwnershipCost><GroupID><UUID>f8d438d7-257a-4111-b2d5-fe602171e0e5</UUID></GroupID><OwnerID><UUID>9e38a2fd-e368-4268-9b6d-6d37fbfb9884</UUID></OwnerID><LastOwnerID><UUID>9e38a2fd-e368-4268-9b6d-6d37fbfb9884</UUID></LastOwnerID><RezzerID><UUID>9e38a2fd-e368-4268-9b6d-6d37fbfb9884</UUID></RezzerID><BaseMask>647168</BaseMask><OwnerMask>581632</OwnerMask><GroupMask>0</GroupMask><EveryoneMask>0</EveryoneMask><NextOwnerMask>581632</NextOwnerMask><Flags>Scripted</Flags><CollisionSound><UUID>00000000-0000-0000-0000-000000000000</UUID></CollisionSound><CollisionSoundVolume>0</CollisionSoundVolume><AttachedPos><X>0</X><Y>0</Y><Z>0</Z></AttachedPos><TextureAnimation></TextureAnimation><ParticleSystem></ParticleSystem><PayPrice0>-2</PayPrice0><PayPrice1>-2</PayPrice1><PayPrice2>-2</PayPrice2><PayPrice3>-2</PayPrice3><PayPrice4>-2</PayPrice4><Buoyancy>0</Buoyancy><Force><X>0</X><Y>0</Y><Z>0</Z></Force><Torque><X>0</X><Y>0</Y><Z>0</Z></Torque><VolumeDetectActive>false</VolumeDetectActive><PhysicsShapeType>0</PhysicsShapeType><CameraEyeOffset><X>0</X><Y>0</Y><Z>0</Z></CameraEyeOffset><CameraAtOffset><X>0</X><Y>0</Y><Z>0</Z></CameraAtOffset><SoundID><UUID>00000000-0000-0000-0000-000000000000</UUID></SoundID><SoundGain>0</SoundGain><SoundFlags>0</SoundFlags><SoundRadius>0</SoundRadius><SoundQueueing>false</SoundQueueing></SceneObjectPart></OtherParts></SceneObjectGroup>