<SceneObjectGroup><SceneObjectPart xmlns:xsi="http://www.w3.org/2001/XMLSchema-instance" xmlns:xsd="http://www.w3.org/2001/XMLSchema"><AllowedDrop>false</AllowedDrop><CreatorID><UUID>6684463c-2bde-4cf6-8859-509ef5b6baf2</UUID></CreatorID><CreatorData>http://login.greatcanadiangrid.ca:8002/;Nine Zero</CreatorData><FolderID><UUID>68a51ca4-be72-41af-be60-2cb59efc7e13</UUID></FolderID><InventorySerial>1</InventorySerial><TaskInventory><TaskInventoryItem><AssetID><UUID>e12bc097-609b-4912-8ba0-3569b9a8d5a9</UUID></AssetID><BasePermissions>581632</BasePermissions><CreationDate>1524701850</CreationDate><CreatorID><UUID>d37a3f5b-562a-4bfd-b780-68c0b9b940be</UUID></CreatorID><Description>(No Description)</Description><EveryonePermissions>32768</EveryonePermissions><Flags>786432</Flags><GroupID><UUID>f8d438d7-257a-4111-b2d5-fe602171e0e5</UUID></GroupID><GroupPermissions>573440</GroupPermissions><InvType>1</InvType><ItemID><UUID>64a029ce-8cda-4809-b8cf-0552dc4416f4</UUID></ItemID><OldItemID><UUID>00000000-0000-0000-0000-000000000000</UUID></OldItemID><LastOwnerID><UUID>d37a3f5b-562a-4bfd-b780-68c0b9b940be</UUID></LastOwnerID><Name>pour_rice</Name><NextPermissions>581632</NextPermissions><OwnerID><UUID>9e38a2fd-e368-4268-9b6d-6d37fbfb9884</UUID></OwnerID><CurrentPermissions>581632</CurrentPermissions><ParentID><UUID>68a51ca4-be72-41af-be60-2cb59efc7e13</UUID></ParentID><ParentPartID><UUID>68a51ca4-be72-41af-be60-2cb59efc7e13</UUID></ParentPartID><PermsGranter><UUID>00000000-0000-0000-0000-000000000000</UUID></PermsGranter><PermsMask>0</PermsMask><Type>1</Type><OwnerChanged>false</OwnerChanged></TaskInventoryItem><TaskInventoryItem><AssetID><UUID>93073e62-aded-436e-89f5-9f29f93709bc</UUID></AssetID><BasePermissions>581632</BasePermissions><CreationDate>1524701687</CreationDate><CreatorID><UUID>6357562e-93aa-4142-9e60-4f84658b0cd1</UUID></CreatorID><Description>2018-04-25 20:14:48 lsl2 script</Description><EveryonePermissions>32768</EveryonePermissions><Flags>786432</Flags><GroupID><UUID>f8d438d7-257a-4111-b2d5-fe602171e0e5</UUID></GroupID><GroupPermissions>573440</GroupPermissions><InvType>10</InvType><ItemID><UUID>94ff88c7-eb59-40a7-ba42-095d858574b3</UUID></ItemID><OldItemID><UUID>00000000-0000-0000-0000-000000000000</UUID></OldItemID><LastOwnerID><UUID>d37a3f5b-562a-4bfd-b780-68c0b9b940be</UUID></LastOwnerID><Name>plate</Name><NextPermissions>581632</NextPermissions><OwnerID><UUID>9e38a2fd-e368-4268-9b6d-6d37fbfb9884</UUID></OwnerID><CurrentPermissions>581632</CurrentPermissions><ParentID><UUID>68a51ca4-be72-41af-be60-2cb59efc7e13</UUID></ParentID><ParentPartID><UUID>68a51ca4-be72-41af-be60-2cb59efc7e13</UUID></ParentPartID><PermsGranter><UUID>00000000-0000-0000-0000-000000000000</UUID></PermsGranter><PermsMask>0</PermsMask><Type>10</Type><OwnerChanged>false</OwnerChanged></TaskInventoryItem><TaskInventoryItem><AssetID><UUID>89759095-0fd1-47e8-a03f-cd14e3555c0c</UUID></AssetID><BasePermissions>581632</BasePermissions><CreationDate>1448152279</CreationDate><CreatorID><UUID>df39e2f0-2495-d3ea-25a6-6aeedc72e111</UUID></CreatorID><Description>faint</Description><EveryonePermissions>32768</EveryonePermissions><Flags>1835008</Flags><GroupID><UUID>f8d438d7-257a-4111-b2d5-fe602171e0e5</UUID></GroupID><GroupPermissions>573440</GroupPermissions><InvType>19</InvType><ItemID><UUID>244c664c-6c67-41a7-bc10-ceea1532456f</UUID></ItemID><OldItemID><UUID>00000000-0000-0000-0000-000000000000</UUID></OldItemID><LastOwnerID><UUID>d37a3f5b-562a-4bfd-b780-68c0b9b940be</UUID></LastOwnerID><Name>faint</Name><NextPermissions>581632</NextPermissions><OwnerID><UUID>9e38a2fd-e368-4268-9b6d-6d37fbfb9884</UUID></OwnerID><CurrentPermissions>581632</CurrentPermissions><ParentID><UUID>68a51ca4-be72-41af-be60-2cb59efc7e13</UUID></ParentID><ParentPartID><UUID>68a51ca4-be72-41af-be60-2cb59efc7e13</UUID></ParentPartID><PermsGranter><UUID>00000000-0000-0000-0000-000000000000</UUID></PermsGranter><PermsMask>0</PermsMask><Type>20</Type><OwnerChanged>false</OwnerChanged></TaskInventoryItem></TaskInventory><UUID><UUID>68a51ca4-be72-41af-be60-2cb59efc7e13</UUID></UUID><LocalId>1031036223</LocalId><Name>SF Plate (wear)</Name><Material>3</Material><PassTouches>false</PassTouches><PassCollisions>false</PassCollisions><RegionHandle>6734508721696000</RegionHandle><ScriptAccessPin>0</ScriptAccessPin><GroupPosition><X>122.5675</X><Y>226.0603</Y><Z>23.68086</Z></GroupPosition><OffsetPosition><X>0</X><Y>0</Y><Z>0</Z></OffsetPosition><RotationOffset><X>-0.6343366</X><Y>0.008132981</Y><Z>-0.7729461</Z><W>0.01026319</W></RotationOffset><Velocity><X>0</X><Y>0</Y><Z>0</Z></Velocity><AngularVelocity><X>0</X><Y>0</Y><Z>0</Z></AngularVelocity><Acceleration><X>0</X><Y>0</Y><Z>0</Z></Acceleration><Description>(No Description)</Description><Color><R>0</R><G>0</G><B>0</B><A>255</A></Color><Text /><SitName /><TouchName /><LinkNum>1</LinkNum><ClickAction>0</ClickAction><Shape><ProfileCurve>1</ProfileCurve><TextureEntry>pcsa1BG9S4Kj2OopBuXOrQAAAAAAAAAAgD8AAACAPwAAAAAAAAAAAAAAAAAAAAAAAAAAAAAAAAAAAAAAAAAAAA==</TextureEntry><ExtraParams>ATAAEQAAAJK0vbRz7E0Gn5xzwj3EC+wF</ExtraParams><PathBegin>0</PathBegin><PathCurve>16</PathCurve><PathEnd>0</PathEnd><PathRadiusOffset>0</PathRadiusOffset><PathRevolutions>0</PathRevolutions><PathScaleX>100</PathScaleX><PathScaleY>100</PathScaleY><PathShearX>0</PathShearX><PathShearY>0</PathShearY><PathSkew>0</PathSkew><PathTaperX>0</PathTaperX><PathTaperY>0</PathTaperY><PathTwist>0</PathTwist><PathTwistBegin>0</PathTwistBegin><PCode>9</PCode><ProfileBegin>12500</ProfileBegin><ProfileEnd>0</ProfileEnd><ProfileHollow>27500</ProfileHollow><State>0</State><LastAttachPoint>6</LastAttachPoint><ProfileShape>Square</ProfileShape><HollowShape>Same</HollowShape><SculptTexture><UUID>92b4bdb4-73ec-4d06-9f9c-73c23dc40bec</UUID></SculptTexture><SculptType>5</SculptType><FlexiSoftness>0</FlexiSoftness><FlexiTension>0</FlexiTension><FlexiDrag>0</FlexiDrag><FlexiGravity>0</FlexiGravity><FlexiWind>0</FlexiWind><FlexiForceX>0</FlexiForceX><FlexiForceY>0</FlexiForceY><FlexiForceZ>0</FlexiForceZ><LightColorR>0</LightColorR><LightColorG>0</LightColorG><LightColorB>0</LightColorB><LightColorA>1</LightColorA><LightRadius>0</LightRadius><LightCutoff>0</LightCutoff><LightFalloff>0</LightFalloff><LightIntensity>1</LightIntensity><FlexiEntry>false</FlexiEntry><LightEntry>false</LightEntry><SculptEntry>true</SculptEntry></Shape><Scale><X>0.4150288</X><Y>0.4150288</Y><Z>0.03025308</Z></Scale><SitTargetOrientation><X>0</X><Y>0</Y><Z>0</Z><W>1</W></SitTargetOrientation><SitTargetPosition><X>0</X><Y>0</Y><Z>0</Z></SitTargetPosition><SitTargetPositionLL><X>0</X><Y>0</Y><Z>0</Z></SitTargetPositionLL><SitTargetOrientationLL><X>0</X><Y>0</Y><Z>0</Z><W>1</W></SitTargetOrientationLL><ParentID>0</ParentID><CreationDate>1433662548</CreationDate><Category>0</Category><SalePrice>10</SalePrice><ObjectSaleType>0</ObjectSaleType><OwnershipCost>0</OwnershipCost><GroupID><UUID>f8d438d7-257a-4111-b2d5-fe602171e0e5</UUID></GroupID><OwnerID><UUID>9e38a2fd-e368-4268-9b6d-6d37fbfb9884</UUID></OwnerID><LastOwnerID><UUID>9e38a2fd-e368-4268-9b6d-6d37fbfb9884</UUID></LastOwnerID><RezzerID><UUID>9e38a2fd-e368-4268-9b6d-6d37fbfb9884</UUID></RezzerID><BaseMask>647168</BaseMask><OwnerMask>581632</OwnerMask><GroupMask>573440</GroupMask><EveryoneMask>32768</EveryoneMask><NextOwnerMask>581632</NextOwnerMask><Flags>Scripted Phantom</Flags><CollisionSound><UUID>00000000-0000-0000-0000-000000000000</UUID></CollisionSound><CollisionSoundVolume>0</CollisionSoundVolume><AttachedPos><X>0.0659318</X><Y>-0.01754497</Y><Z>-0.01844325</Z></AttachedPos><TextureAnimation></TextureAnimation><ParticleSystem></ParticleSystem><PayPrice0>-2</PayPrice0><PayPrice1>-2</PayPrice1><PayPrice2>-2</PayPrice2><PayPrice3>-2</PayPrice3><PayPrice4>-2</PayPrice4><Buoyancy>0</Buoyancy><Force><X>0</X><Y>0</Y><Z>0</Z></Force><Torque><X>0</X><Y>0</Y><Z>0</Z></Torque><VolumeDetectActive>false</VolumeDetectActive><PhysicsShapeType>0</PhysicsShapeType><CameraEyeOffset><X>0</X><Y>0</Y><Z>0</Z></CameraEyeOffset><CameraAtOffset><X>0</X><Y>0</Y><Z>0</Z></CameraAtOffset><SoundID><UUID>00000000-0000-0000-0000-000000000000</UUID></SoundID><SoundGain>0</SoundGain><SoundFlags>0</SoundFlags><SoundRadius>0</SoundRadius><SoundQueueing>false</SoundQueueing></SceneObjectPart><OtherParts><SceneObjectPart xmlns:xsi="http://www.w3.org/2001/XMLSchema-instance" xmlns:xsd="http://www.w3.org/2001/XMLSchema"><AllowedDrop>false</AllowedDrop><CreatorID><UUID>d37a3f5b-562a-4bfd-b780-68c0b9b940be</UUID></CreatorID><CreatorData>http://hypergrid.org:8002/;Satyr Aeon</CreatorData><FolderID><UUID>9fbac1e2-2479-43b4-abda-ba16094d4975</UUID></FolderID><InventorySerial>1</InventorySerial><UUID><UUID>9fbac1e2-2479-43b4-abda-ba16094d4975</UUID></UUID><LocalId>1031036224</LocalId><Name>drink</Name><Material>3</Material><PassTouches>false</PassTouches><PassCollisions>false</PassCollisions><RegionHandle>6734508721696000</RegionHandle><ScriptAccessPin>0</ScriptAccessPin><GroupPosition><X>122.5675</X><Y>226.0603</Y><Z>23.68086</Z></GroupPosition><OffsetPosition><X>0.003820059</X><Y>0.004663235</Y><Z>0.004053242</Z></OffsetPosition><RotationOffset><X>0.009835187</X><Y>0.0001000736</Y><Z>0.9998659</Z><W>0.01310251</W></RotationOffset><Velocity><X>0</X><Y>0</Y><Z>0</Z></Velocity><AngularVelocity><X>0</X><Y>0</Y><Z>0</Z></AngularVelocity><Acceleration><X>0</X><Y>0</Y><Z>0</Z></Acceleration><Description /><Color><R>0</R><G>0</G><B>0</B><A>255</A></Color><Text /><SitName /><TouchName /><LinkNum>2</LinkNum><ClickAction>0</ClickAction><Shape><ProfileCurve>5</ProfileCurve><TextureEntry>fEg9TZRkTnylECnbxr5jnQAAAAD/AGZmZj8CAACAPwBmZuY/AAAAAABAAAAAAAAAAAAAAAAAAAAAAAAAAAAAAAAAAAAA</TextureEntry><ExtraParams>AA==</ExtraParams><PathBegin>0</PathBegin><PathCurve>32</PathCurve><PathEnd>25000</PathEnd><PathRadiusOffset>0</PathRadiusOffset><PathRevolutions>0</PathRevolutions><PathScaleX>100</PathScaleX><PathScaleY>100</PathScaleY><PathShearX>0</PathShearX><PathShearY>0</PathShearY><PathSkew>0</PathSkew><PathTaperX>0</PathTaperX><PathTaperY>0</PathTaperY><PathTwist>0</PathTwist><PathTwistBegin>0</PathTwistBegin><PCode>9</PCode><ProfileBegin>0</ProfileBegin><ProfileEnd>0</ProfileEnd><ProfileHollow>0</ProfileHollow><State>0</State><LastAttachPoint>0</LastAttachPoint><ProfileShape>HalfCircle</ProfileShape><HollowShape>Same</HollowShape><SculptTexture><UUID>00000000-0000-0000-0000-000000000000</UUID></SculptTexture><SculptType>0</SculptType><FlexiSoftness>0</FlexiSoftness><FlexiTension>0</FlexiTension><FlexiDrag>0</FlexiDrag><FlexiGravity>0</FlexiGravity><FlexiWind>0</FlexiWind><FlexiForceX>0</FlexiForceX><FlexiForceY>0</FlexiForceY><FlexiForceZ>0</FlexiForceZ><LightColorR>0</LightColorR><LightColorG>0</LightColorG><LightColorB>0</LightColorB><LightColorA>1</LightColorA><LightRadius>0</LightRadius><LightCutoff>0</LightCutoff><LightFalloff>0</LightFalloff><LightIntensity>1</LightIntensity><FlexiEntry>false</FlexiEntry><LightEntry>false</LightEntry><SculptEntry>false</SculptEntry></Shape><Scale><X>0.2740248</X><Y>0.2740248</Y><Z>0.1559728</Z></Scale><SitTargetOrientation><X>0</X><Y>0</Y><Z>0</Z><W>1</W></SitTargetOrientation><SitTargetPosition><X>0</X><Y>0</Y><Z>0</Z></SitTargetPosition><SitTargetPositionLL><X>0</X><Y>0</Y><Z>0</Z></SitTargetPositionLL><SitTargetOrientationLL><X>0</X><Y>0</Y><Z>0</Z><W>1</W></SitTargetOrientationLL><ParentID>1031036223</ParentID><CreationDate>1505507458</CreationDate><Category>0</Category><SalePrice>10</SalePrice><ObjectSaleType>0</ObjectSaleType><OwnershipCost>0</OwnershipCost><GroupID><UUID>f8d438d7-257a-4111-b2d5-fe602171e0e5</UUID></GroupID><OwnerID><UUID>9e38a2fd-e368-4268-9b6d-6d37fbfb9884</UUID></OwnerID><LastOwnerID><UUID>9e38a2fd-e368-4268-9b6d-6d37fbfb9884</UUID></LastOwnerID><RezzerID><UUID>9e38a2fd-e368-4268-9b6d-6d37fbfb9884</UUID></RezzerID><BaseMask>647168</BaseMask><OwnerMask>581632</OwnerMask><GroupMask>573440</GroupMask><EveryoneMask>32768</EveryoneMask><NextOwnerMask>581632</NextOwnerMask><Flags>Scripted Phantom</Flags><CollisionSound><UUID>00000000-0000-0000-0000-000000000000</UUID></CollisionSound><CollisionSoundVolume>0</CollisionSoundVolume><AttachedPos><X>0</X><Y>0</Y><Z>0</Z></AttachedPos><TextureAnimation></TextureAnimation><ParticleSystem></ParticleSystem><PayPrice0>-2</PayPrice0><PayPrice1>-2</PayPrice1><PayPrice2>-2</PayPrice2><PayPrice3>-2</PayPrice3><PayPrice4>-2</PayPrice4><Buoyancy>0</Buoyancy><Force><X>0</X><Y>0</Y><Z>0</Z></Force><Torque><X>0</X><Y>0</Y><Z>0</Z></Torque><VolumeDetectActive>false</VolumeDetectActive><PhysicsShapeType>0</PhysicsShapeType><CameraEyeOffset><X>0</X><Y>0</Y><Z>0</Z></CameraEyeOffset><CameraAtOffset><X>0</X><Y>0</Y><Z>0</Z></CameraAtOffset><SoundID><UUID>00000000-0000-0000-0000-000000000000</UUID></SoundID><SoundGain>0</SoundGain><SoundFlags>0</SoundFlags><SoundRadius>0</SoundRadius><SoundQueueing>false</SoundQueueing></SceneObjectPart></OtherParts></SceneObjectGroup>