<SceneObjectGroup><RootPart><SceneObjectPart xmlns:xsi="http://www.w3.org/2001/XMLSchema-instance" xmlns:xsd="http://www.w3.org/2001/XMLSchema"><AllowedDrop>false</AllowedDrop><CreatorID><UUID>86f15958-8a66-407d-8d06-6f4a6ec94bab</UUID></CreatorID><FolderID><UUID>5baf43e7-c526-424c-ba64-57bc69fdbf61</UUID></FolderID><InventorySerial>0</InventorySerial><UUID><UUID>5baf43e7-c526-424c-ba64-57bc69fdbf61</UUID></UUID><LocalId>1472706706</LocalId><Name>Rogue - Brown Boot  lower R - The Painted Lilly</Name><Material>3</Material><PassTouches>false</PassTouches><PassCollisions>false</PassCollisions><RegionHandle>10985220675669248</RegionHandle><ScriptAccessPin>0</ScriptAccessPin><GroupPosition><X>-0.146437</X><Y>0.003887</Y><Z>0.010049</Z></GroupPosition><OffsetPosition><X>0</X><Y>0</Y><Z>0</Z></OffsetPosition><RotationOffset><X>0.001783423</X><Y>0.01743334</Y><Z>-0.01740062</Z><W>0.999695</W></RotationOffset><Velocity><X>0</X><Y>0</Y><Z>0</Z></Velocity><AngularVelocity><X>0</X><Y>0</Y><Z>0</Z></AngularVelocity><Acceleration><X>0</X><Y>0</Y><Z>0</Z></Acceleration><Description>(No Description)</Description><Color><R>0</R><G>0</G><B>0</B><A>255</A></Color><Text /><SitName /><TouchName /><LinkNum>1</LinkNum><ClickAction>0</ClickAction><Shape><ProfileCurve>0</ProfileCurve><TextureEntry>YxLLqER/RhKD70PJzWqWAAAAAAAAAAAAgD8AAACAPwAAAAAAAAAAAABAAAAAAAAAAAAAAAAAAAAAAAAAAAAA</TextureEntry><ExtraParams>ATAAEQAAAH/Yiy4Zf0Q8mtPbICHs3WoB</ExtraParams><PathBegin>0</PathBegin><PathCurve>32</PathCurve><PathEnd>0</PathEnd><PathRadiusOffset>0</PathRadiusOffset><PathRevolutions>0</PathRevolutions><PathScaleX>100</PathScaleX><PathScaleY>150</PathScaleY><PathShearX>0</PathShearX><PathShearY>0</PathShearY><PathSkew>0</PathSkew><PathTaperX>0</PathTaperX><PathTaperY>0</PathTaperY><PathTwist>0</PathTwist><PathTwistBegin>0</PathTwistBegin><PCode>9</PCode><ProfileBegin>0</ProfileBegin><ProfileEnd>0</ProfileEnd><ProfileHollow>0</ProfileHollow><State>8</State><LastAttachPoint>8</LastAttachPoint><ProfileShape>Circle</ProfileShape><HollowShape>Same</HollowShape><SculptTexture><UUID>7fd88b2e-197f-443c-9ad3-db2021ecdd6a</UUID></SculptTexture><SculptType>1</SculptType><FlexiSoftness>0</FlexiSoftness><FlexiTension>0</FlexiTension><FlexiDrag>0</FlexiDrag><FlexiGravity>0</FlexiGravity><FlexiWind>0</FlexiWind><FlexiForceX>0</FlexiForceX><FlexiForceY>0</FlexiForceY><FlexiForceZ>0</FlexiForceZ><LightColorR>0</LightColorR><LightColorG>0</LightColorG><LightColorB>0</LightColorB><LightColorA>1</LightColorA><LightRadius>0</LightRadius><LightCutoff>0</LightCutoff><LightFalloff>0</LightFalloff><LightIntensity>1</LightIntensity><FlexiEntry>false</FlexiEntry><LightEntry>false</LightEntry><SculptEntry>true</SculptEntry></Shape><Scale><X>0.1042427</X><Y>0.0840987</Y><Z>0.08642346</Z></Scale><SitTargetOrientation><X>0</X><Y>0</Y><Z>0</Z><W>1</W></SitTargetOrientation><SitTargetPosition><X>0</X><Y>0</Y><Z>0</Z></SitTargetPosition><SitTargetPositionLL><X>0</X><Y>0</Y><Z>0</Z></SitTargetPositionLL><SitTargetOrientationLL><X>0</X><Y>0</Y><Z>0</Z><W>1</W></SitTargetOrientationLL><ParentID>0</ParentID><CreationDate>1471709062</CreationDate><Category>0</Category><SalePrice>0</SalePrice><ObjectSaleType>0</ObjectSaleType><OwnershipCost>0</OwnershipCost><GroupID><UUID>00000000-0000-0000-0000-000000000000</UUID></GroupID><OwnerID><UUID>86f15958-8a66-407d-8d06-6f4a6ec94bab</UUID></OwnerID><LastOwnerID><UUID>86f15958-8a66-407d-8d06-6f4a6ec94bab</UUID></LastOwnerID><RezzerID><UUID>00000000-0000-0000-0000-000000000000</UUID></RezzerID><BaseMask>647168</BaseMask><OwnerMask>647168</OwnerMask><GroupMask>0</GroupMask><EveryoneMask>0</EveryoneMask><NextOwnerMask>532480</NextOwnerMask><Flags>None</Flags><CollisionSound><UUID>00000000-0000-0000-0000-000000000000</UUID></CollisionSound><CollisionSoundVolume>0</CollisionSoundVolume><AttachedPos><X>-0.146437</X><Y>0.003887</Y><Z>0.010049</Z></AttachedPos><TextureAnimation /><ParticleSystem /><PayPrice0>-2</PayPrice0><PayPrice1>-2</PayPrice1><PayPrice2>-2</PayPrice2><PayPrice3>-2</PayPrice3><PayPrice4>-2</PayPrice4><Buoyancy>0</Buoyancy><Force><X>0</X><Y>0</Y><Z>0</Z></Force><Torque><X>0</X><Y>0</Y><Z>0</Z></Torque><VolumeDetectActive>false</VolumeDetectActive><PhysicsShapeType>0</PhysicsShapeType><CameraEyeOffset><X>0</X><Y>0</Y><Z>0</Z></CameraEyeOffset><CameraAtOffset><X>0</X><Y>0</Y><Z>0</Z></CameraAtOffset><SoundID><UUID>00000000-0000-0000-0000-000000000000</UUID></SoundID><SoundGain>0</SoundGain><SoundFlags>0</SoundFlags><SoundRadius>0</SoundRadius><SoundQueueing>false</SoundQueueing><CreatorData>http://grid.vibel.eu:8002;Roland Francis</CreatorData></SceneObjectPart></RootPart><OtherParts><Part><SceneObjectPart xmlns:xsi="http://www.w3.org/2001/XMLSchema-instance" xmlns:xsd="http://www.w3.org/2001/XMLSchema"><AllowedDrop>false</AllowedDrop><CreatorID><UUID>86f15958-8a66-407d-8d06-6f4a6ec94bab</UUID></CreatorID><FolderID><UUID>da36d82e-34be-4d7f-8925-08a7d02b291a</UUID></FolderID><InventorySerial>0</InventorySerial><UUID><UUID>da36d82e-34be-4d7f-8925-08a7d02b291a</UUID></UUID><LocalId>1472706707</LocalId><Name>Object</Name><Material>3</Material><PassTouches>false</PassTouches><PassCollisions>false</PassCollisions><RegionHandle>10985220675669248</RegionHandle><ScriptAccessPin>0</ScriptAccessPin><GroupPosition><X>-0.146437</X><Y>0.003887</Y><Z>0.010049</Z></GroupPosition><OffsetPosition><X>0.1137941</X><Y>-0.004204381</Y><Z>0.03159321</Z></OffsetPosition><RotationOffset><X>-0.04015965</X><Y>-0.1152873</Y><Z>0.06224056</Z><W>0.9905666</W></RotationOffset><Velocity><X>0</X><Y>0</Y><Z>0</Z></Velocity><AngularVelocity><X>0</X><Y>0</Y><Z>0</Z></AngularVelocity><Acceleration><X>0</X><Y>0</Y><Z>0</Z></Acceleration><Description>(No Description)</Description><Color><R>0</R><G>0</G><B>0</B><A>255</A></Color><Text /><SitName /><TouchName /><LinkNum>2</LinkNum><ClickAction>0</ClickAction><Shape><ProfileCurve>0</ProfileCurve><TextureEntry>6Xz0EI5hcAXsBmKeukzR+wDJ4vAAAAAAAAAAAAAAAADnOwAAAAAF4AABAAAAAAAAAAAAAAAAAAAAAAAAAAAA</TextureEntry><ExtraParams>ATAAEQAAAPFHDzqzEE86m/TaVLe5awcB</ExtraParams><PathBegin>0</PathBegin><PathCurve>32</PathCurve><PathEnd>0</PathEnd><PathRadiusOffset>0</PathRadiusOffset><PathRevolutions>0</PathRevolutions><PathScaleX>100</PathScaleX><PathScaleY>150</PathScaleY><PathShearX>0</PathShearX><PathShearY>0</PathShearY><PathSkew>0</PathSkew><PathTaperX>0</PathTaperX><PathTaperY>0</PathTaperY><PathTwist>0</PathTwist><PathTwistBegin>0</PathTwistBegin><PCode>9</PCode><ProfileBegin>0</ProfileBegin><ProfileEnd>0</ProfileEnd><ProfileHollow>0</ProfileHollow><State>0</State><LastAttachPoint>0</LastAttachPoint><ProfileShape>Circle</ProfileShape><HollowShape>Same</HollowShape><SculptTexture><UUID>f1470f3a-b310-4f3a-9bf4-da54b7b96b07</UUID></SculptTexture><SculptType>1</SculptType><FlexiSoftness>0</FlexiSoftness><FlexiTension>0</FlexiTension><FlexiDrag>0</FlexiDrag><FlexiGravity>0</FlexiGravity><FlexiWind>0</FlexiWind><FlexiForceX>0</FlexiForceX><FlexiForceY>0</FlexiForceY><FlexiForceZ>0</FlexiForceZ><LightColorR>0</LightColorR><LightColorG>0</LightColorG><LightColorB>0</LightColorB><LightColorA>1</LightColorA><LightRadius>0</LightRadius><LightCutoff>0</LightCutoff><LightFalloff>0</LightFalloff><LightIntensity>1</LightIntensity><FlexiEntry>false</FlexiEntry><LightEntry>false</LightEntry><SculptEntry>true</SculptEntry></Shape><Scale><X>0.3047328</X><Y>0.1619735</Y><Z>0.2270382</Z></Scale><SitTargetOrientation><X>0</X><Y>0</Y><Z>0</Z><W>1</W></SitTargetOrientation><SitTargetPosition><X>0</X><Y>0</Y><Z>0</Z></SitTargetPosition><SitTargetPositionLL><X>0</X><Y>0</Y><Z>0</Z></SitTargetPositionLL><SitTargetOrientationLL><X>0</X><Y>0</Y><Z>0</Z><W>1</W></SitTargetOrientationLL><ParentID>1472706706</ParentID><CreationDate>1471709081</CreationDate><Category>0</Category><SalePrice>10</SalePrice><ObjectSaleType>0</ObjectSaleType><OwnershipCost>0</OwnershipCost><GroupID><UUID>00000000-0000-0000-0000-000000000000</UUID></GroupID><OwnerID><UUID>86f15958-8a66-407d-8d06-6f4a6ec94bab</UUID></OwnerID><LastOwnerID><UUID>86f15958-8a66-407d-8d06-6f4a6ec94bab</UUID></LastOwnerID><RezzerID><UUID>00000000-0000-0000-0000-000000000000</UUID></RezzerID><BaseMask>647168</BaseMask><OwnerMask>647168</OwnerMask><GroupMask>0</GroupMask><EveryoneMask>0</EveryoneMask><NextOwnerMask>532480</NextOwnerMask><Flags>None</Flags><CollisionSound><UUID>00000000-0000-0000-0000-000000000000</UUID></CollisionSound><CollisionSoundVolume>0</CollisionSoundVolume><AttachedPos><X>0</X><Y>0</Y><Z>0</Z></AttachedPos><TextureAnimation /><ParticleSystem /><PayPrice0>-2</PayPrice0><PayPrice1>-2</PayPrice1><PayPrice2>-2</PayPrice2><PayPrice3>-2</PayPrice3><PayPrice4>-2</PayPrice4><Buoyancy>0</Buoyancy><Force><X>0</X><Y>0</Y><Z>0</Z></Force><Torque><X>0</X><Y>0</Y><Z>0</Z></Torque><VolumeDetectActive>false</VolumeDetectActive><PhysicsShapeType>0</PhysicsShapeType><CameraEyeOffset><X>0</X><Y>0</Y><Z>0</Z></CameraEyeOffset><CameraAtOffset><X>0</X><Y>0</Y><Z>0</Z></CameraAtOffset><SoundID><UUID>00000000-0000-0000-0000-000000000000</UUID></SoundID><SoundGain>0</SoundGain><SoundFlags>0</SoundFlags><SoundRadius>0</SoundRadius><SoundQueueing>false</SoundQueueing><CreatorData>http://grid.vibel.eu:8002;Roland Francis</CreatorData></SceneObjectPart></Part><Part><SceneObjectPart xmlns:xsi="http://www.w3.org/2001/XMLSchema-instance" xmlns:xsd="http://www.w3.org/2001/XMLSchema"><AllowedDrop>false</AllowedDrop><CreatorID><UUID>86f15958-8a66-407d-8d06-6f4a6ec94bab</UUID></CreatorID><FolderID><UUID>a2bec587-c405-4f8a-9f6f-d4945c9e75a2</UUID></FolderID><InventorySerial>0</InventorySerial><UUID><UUID>a2bec587-c405-4f8a-9f6f-d4945c9e75a2</UUID></UUID><LocalId>1472706708</LocalId><Name>BootSole</Name><Material>3</Material><PassTouches>false</PassTouches><PassCollisions>false</PassCollisions><RegionHandle>10985220675669248</RegionHandle><ScriptAccessPin>0</ScriptAccessPin><GroupPosition><X>-0.146437</X><Y>0.003887</Y><Z>0.010049</Z></GroupPosition><OffsetPosition><X>0.1122967</X><Y>0.0009292585</Y><Z>0.001021804</Z></OffsetPosition><RotationOffset><X>-0.0348516</X><Y>1.141219E-06</Y><Z>0.9993924</Z><W>1.735985E-06</W></RotationOffset><Velocity><X>0</X><Y>0</Y><Z>0</Z></Velocity><AngularVelocity><X>0</X><Y>0</Y><Z>0</Z></AngularVelocity><Acceleration><X>0</X><Y>0</Y><Z>0</Z></Acceleration><Description>(No Description)</Description><Color><R>0</R><G>0</G><B>0</B><A>255</A></Color><Text /><SitName /><TouchName /><LinkNum>3</LinkNum><ClickAction>0</ClickAction><Shape><ProfileCurve>0</ProfileCurve><TextureEntry>YxLLqER/RhKD70PJzWqWAAAAAAAAAM3MjD8AzczMPwAAAAAAAAAAAABAAAAAAAAAAAAAAAAAAAAAAAAAAAAA</TextureEntry><ExtraParams>ATAAEQAAAIOxK+SFDU/Rr0u/cU8+RkCB</ExtraParams><PathBegin>0</PathBegin><PathCurve>32</PathCurve><PathEnd>0</PathEnd><PathRadiusOffset>0</PathRadiusOffset><PathRevolutions>0</PathRevolutions><PathScaleX>100</PathScaleX><PathScaleY>150</PathScaleY><PathShearX>0</PathShearX><PathShearY>0</PathShearY><PathSkew>0</PathSkew><PathTaperX>0</PathTaperX><PathTaperY>0</PathTaperY><PathTwist>0</PathTwist><PathTwistBegin>0</PathTwistBegin><PCode>9</PCode><ProfileBegin>0</ProfileBegin><ProfileEnd>0</ProfileEnd><ProfileHollow>0</ProfileHollow><State>0</State><LastAttachPoint>0</LastAttachPoint><ProfileShape>Circle</ProfileShape><HollowShape>Same</HollowShape><SculptTexture><UUID>83b12be4-850d-4fd1-af4b-bf714f3e4640</UUID></SculptTexture><SculptType>129</SculptType><FlexiSoftness>0</FlexiSoftness><FlexiTension>0</FlexiTension><FlexiDrag>0</FlexiDrag><FlexiGravity>0</FlexiGravity><FlexiWind>0</FlexiWind><FlexiForceX>0</FlexiForceX><FlexiForceY>0</FlexiForceY><FlexiForceZ>0</FlexiForceZ><LightColorR>0</LightColorR><LightColorG>0</LightColorG><LightColorB>0</LightColorB><LightColorA>1</LightColorA><LightRadius>0</LightRadius><LightCutoff>0</LightCutoff><LightFalloff>0</LightFalloff><LightIntensity>1</LightIntensity><FlexiEntry>false</FlexiEntry><LightEntry>false</LightEntry><SculptEntry>true</SculptEntry></Shape><Scale><X>0.3459908</X><Y>0.1240062</Y><Z>0.07413238</Z></Scale><SitTargetOrientation><X>0</X><Y>0</Y><Z>0</Z><W>1</W></SitTargetOrientation><SitTargetPosition><X>0</X><Y>0</Y><Z>0</Z></SitTargetPosition><SitTargetPositionLL><X>0</X><Y>0</Y><Z>0</Z></SitTargetPositionLL><SitTargetOrientationLL><X>0</X><Y>0</Y><Z>0</Z><W>1</W></SitTargetOrientationLL><ParentID>1472706706</ParentID><CreationDate>1471709081</CreationDate><Category>0</Category><SalePrice>10</SalePrice><ObjectSaleType>0</ObjectSaleType><OwnershipCost>0</OwnershipCost><GroupID><UUID>00000000-0000-0000-0000-000000000000</UUID></GroupID><OwnerID><UUID>86f15958-8a66-407d-8d06-6f4a6ec94bab</UUID></OwnerID><LastOwnerID><UUID>86f15958-8a66-407d-8d06-6f4a6ec94bab</UUID></LastOwnerID><RezzerID><UUID>00000000-0000-0000-0000-000000000000</UUID></RezzerID><BaseMask>647168</BaseMask><OwnerMask>647168</OwnerMask><GroupMask>0</GroupMask><EveryoneMask>0</EveryoneMask><NextOwnerMask>532480</NextOwnerMask><Flags>None</Flags><CollisionSound><UUID>00000000-0000-0000-0000-000000000000</UUID></CollisionSound><CollisionSoundVolume>0</CollisionSoundVolume><AttachedPos><X>0</X><Y>0</Y><Z>0</Z></AttachedPos><TextureAnimation /><ParticleSystem /><PayPrice0>-2</PayPrice0><PayPrice1>-2</PayPrice1><PayPrice2>-2</PayPrice2><PayPrice3>-2</PayPrice3><PayPrice4>-2</PayPrice4><Buoyancy>0</Buoyancy><Force><X>0</X><Y>0</Y><Z>0</Z></Force><Torque><X>0</X><Y>0</Y><Z>0</Z></Torque><VolumeDetectActive>false</VolumeDetectActive><PhysicsShapeType>0</PhysicsShapeType><CameraEyeOffset><X>0</X><Y>0</Y><Z>0</Z></CameraEyeOffset><CameraAtOffset><X>0</X><Y>0</Y><Z>0</Z></CameraAtOffset><SoundID><UUID>00000000-0000-0000-0000-000000000000</UUID></SoundID><SoundGain>0</SoundGain><SoundFlags>0</SoundFlags><SoundRadius>0</SoundRadius><SoundQueueing>false</SoundQueueing><CreatorData>http://grid.vibel.eu:8002;Roland Francis</CreatorData></SceneObjectPart></Part><Part><SceneObjectPart xmlns:xsi="http://www.w3.org/2001/XMLSchema-instance" xmlns:xsd="http://www.w3.org/2001/XMLSchema"><AllowedDrop>false</AllowedDrop><CreatorID><UUID>86f15958-8a66-407d-8d06-6f4a6ec94bab</UUID></CreatorID><FolderID><UUID>abd362ed-3325-43ed-8d63-decdd8b06539</UUID></FolderID><InventorySerial>0</InventorySerial><UUID><UUID>abd362ed-3325-43ed-8d63-decdd8b06539</UUID></UUID><LocalId>1472706709</LocalId><Name>BootRight</Name><Material>3</Material><PassTouches>false</PassTouches><PassCollisions>false</PassCollisions><RegionHandle>10985220675669248</RegionHandle><ScriptAccessPin>0</ScriptAccessPin><GroupPosition><X>-0.146437</X><Y>0.003887</Y><Z>0.010049</Z></GroupPosition><OffsetPosition><X>0.1109457</X><Y>-0.0009864027</Y><Z>0.05443937</Z></OffsetPosition><RotationOffset><X>-0.008683149</X><Y>2.21387E-06</Y><Z>0.9999623</Z><W>-0.0002438743</W></RotationOffset><Velocity><X>0</X><Y>0</Y><Z>0</Z></Velocity><AngularVelocity><X>0</X><Y>0</Y><Z>0</Z></AngularVelocity><Acceleration><X>0</X><Y>0</Y><Z>0</Z></Acceleration><Description>(No Description)</Description><Color><R>0</R><G>0</G><B>0</B><A>255</A></Color><Text /><SitName /><TouchName /><LinkNum>4</LinkNum><ClickAction>0</ClickAction><Shape><ProfileCurve>0</ProfileCurve><TextureEntry>Q3b8VQxxQeWE1d4UFKTXHwAAAAAAAAAAgD8AAACAPwCZWQAAAAAAAAAAAAAAAAAAAAAAAAAAAAAAAAAAAAAA</TextureEntry><ExtraParams>ATAAEQAAAPFHDzqzEE86m/TaVLe5aweB</ExtraParams><PathBegin>0</PathBegin><PathCurve>32</PathCurve><PathEnd>0</PathEnd><PathRadiusOffset>0</PathRadiusOffset><PathRevolutions>0</PathRevolutions><PathScaleX>100</PathScaleX><PathScaleY>150</PathScaleY><PathShearX>0</PathShearX><PathShearY>0</PathShearY><PathSkew>0</PathSkew><PathTaperX>0</PathTaperX><PathTaperY>0</PathTaperY><PathTwist>0</PathTwist><PathTwistBegin>0</PathTwistBegin><PCode>9</PCode><ProfileBegin>0</ProfileBegin><ProfileEnd>0</ProfileEnd><ProfileHollow>0</ProfileHollow><State>0</State><LastAttachPoint>0</LastAttachPoint><ProfileShape>Circle</ProfileShape><HollowShape>Same</HollowShape><SculptTexture><UUID>f1470f3a-b310-4f3a-9bf4-da54b7b96b07</UUID></SculptTexture><SculptType>129</SculptType><FlexiSoftness>0</FlexiSoftness><FlexiTension>0</FlexiTension><FlexiDrag>0</FlexiDrag><FlexiGravity>0</FlexiGravity><FlexiWind>0</FlexiWind><FlexiForceX>0</FlexiForceX><FlexiForceY>0</FlexiForceY><FlexiForceZ>0</FlexiForceZ><LightColorR>0</LightColorR><LightColorG>0</LightColorG><LightColorB>0</LightColorB><LightColorA>1</LightColorA><LightRadius>0</LightRadius><LightCutoff>0</LightCutoff><LightFalloff>0</LightFalloff><LightIntensity>1</LightIntensity><FlexiEntry>false</FlexiEntry><LightEntry>false</LightEntry><SculptEntry>true</SculptEntry></Shape><Scale><X>0.3353029</X><Y>0.1271823</Y><Z>0.1628788</Z></Scale><SitTargetOrientation><X>0</X><Y>0</Y><Z>0</Z><W>1</W></SitTargetOrientation><SitTargetPosition><X>0</X><Y>0</Y><Z>0</Z></SitTargetPosition><SitTargetPositionLL><X>0</X><Y>0</Y><Z>0</Z></SitTargetPositionLL><SitTargetOrientationLL><X>0</X><Y>0</Y><Z>0</Z><W>1</W></SitTargetOrientationLL><ParentID>1472706706</ParentID><CreationDate>1471709081</CreationDate><Category>0</Category><SalePrice>10</SalePrice><ObjectSaleType>0</ObjectSaleType><OwnershipCost>0</OwnershipCost><GroupID><UUID>00000000-0000-0000-0000-000000000000</UUID></GroupID><OwnerID><UUID>86f15958-8a66-407d-8d06-6f4a6ec94bab</UUID></OwnerID><LastOwnerID><UUID>86f15958-8a66-407d-8d06-6f4a6ec94bab</UUID></LastOwnerID><RezzerID><UUID>00000000-0000-0000-0000-000000000000</UUID></RezzerID><BaseMask>647168</BaseMask><OwnerMask>647168</OwnerMask><GroupMask>0</GroupMask><EveryoneMask>0</EveryoneMask><NextOwnerMask>532480</NextOwnerMask><Flags>None</Flags><CollisionSound><UUID>00000000-0000-0000-0000-000000000000</UUID></CollisionSound><CollisionSoundVolume>0</CollisionSoundVolume><AttachedPos><X>0</X><Y>0</Y><Z>0</Z></AttachedPos><TextureAnimation /><ParticleSystem /><PayPrice0>-2</PayPrice0><PayPrice1>-2</PayPrice1><PayPrice2>-2</PayPrice2><PayPrice3>-2</PayPrice3><PayPrice4>-2</PayPrice4><Buoyancy>0</Buoyancy><Force><X>0</X><Y>0</Y><Z>0</Z></Force><Torque><X>0</X><Y>0</Y><Z>0</Z></Torque><VolumeDetectActive>false</VolumeDetectActive><PhysicsShapeType>0</PhysicsShapeType><CameraEyeOffset><X>0</X><Y>0</Y><Z>0</Z></CameraEyeOffset><CameraAtOffset><X>0</X><Y>0</Y><Z>0</Z></CameraAtOffset><SoundID><UUID>00000000-0000-0000-0000-000000000000</UUID></SoundID><SoundGain>0</SoundGain><SoundFlags>0</SoundFlags><SoundRadius>0</SoundRadius><SoundQueueing>false</SoundQueueing><CreatorData>http://grid.vibel.eu:8002;Roland Francis</CreatorData></SceneObjectPart></Part><Part><SceneObjectPart xmlns:xsi="http://www.w3.org/2001/XMLSchema-instance" xmlns:xsd="http://www.w3.org/2001/XMLSchema"><AllowedDrop>false</AllowedDrop><CreatorID><UUID>86f15958-8a66-407d-8d06-6f4a6ec94bab</UUID></CreatorID><FolderID><UUID>b072812b-0ed2-4fd7-9095-9f44d1f052e8</UUID></FolderID><InventorySerial>0</InventorySerial><UUID><UUID>b072812b-0ed2-4fd7-9095-9f44d1f052e8</UUID></UUID><LocalId>1472706710</LocalId><Name>Object</Name><Material>3</Material><PassTouches>false</PassTouches><PassCollisions>false</PassCollisions><RegionHandle>10985220675669248</RegionHandle><ScriptAccessPin>0</ScriptAccessPin><GroupPosition><X>-0.146437</X><Y>0.003887</Y><Z>0.010049</Z></GroupPosition><OffsetPosition><X>0.06182957</X><Y>-0.05806348</Y><Z>0.1037066</Z></OffsetPosition><RotationOffset><X>0.0387205</X><Y>-0.745377</Y><Z>-0.597078</Z><W>0.2939586</W></RotationOffset><Velocity><X>0</X><Y>0</Y><Z>0</Z></Velocity><AngularVelocity><X>0</X><Y>0</Y><Z>0</Z></AngularVelocity><Acceleration><X>0</X><Y>0</Y><Z>0</Z></Acceleration><Description>(No Description)</Description><Color><R>0</R><G>0</G><B>0</B><A>255</A></Color><Text /><SitName /><TouchName /><LinkNum>5</LinkNum><ClickAction>0</ClickAction><Shape><ProfileCurve>0</ProfileCurve><TextureEntry>R0TvbCNrQAWKBDSbgqQvQQAAAAAAAAAAgD8AAACAPwAAAAAAAAAAAADAAAAAAAAAAAAAAAAAAAAAAAAAAAAA</TextureEntry><ExtraParams>ATAAEQAAAFf2i/mkAEH8obaG6MXWP+aC</ExtraParams><PathBegin>0</PathBegin><PathCurve>32</PathCurve><PathEnd>0</PathEnd><PathRadiusOffset>0</PathRadiusOffset><PathRevolutions>0</PathRevolutions><PathScaleX>100</PathScaleX><PathScaleY>150</PathScaleY><PathShearX>0</PathShearX><PathShearY>0</PathShearY><PathSkew>0</PathSkew><PathTaperX>0</PathTaperX><PathTaperY>0</PathTaperY><PathTwist>0</PathTwist><PathTwistBegin>0</PathTwistBegin><PCode>9</PCode><ProfileBegin>0</ProfileBegin><ProfileEnd>0</ProfileEnd><ProfileHollow>0</ProfileHollow><State>0</State><LastAttachPoint>0</LastAttachPoint><ProfileShape>Circle</ProfileShape><HollowShape>Same</HollowShape><SculptTexture><UUID>57f68bf9-a400-41fc-a1b6-86e8c5d63fe6</UUID></SculptTexture><SculptType>130</SculptType><FlexiSoftness>0</FlexiSoftness><FlexiTension>0</FlexiTension><FlexiDrag>0</FlexiDrag><FlexiGravity>0</FlexiGravity><FlexiWind>0</FlexiWind><FlexiForceX>0</FlexiForceX><FlexiForceY>0</FlexiForceY><FlexiForceZ>0</FlexiForceZ><LightColorR>0</LightColorR><LightColorG>0</LightColorG><LightColorB>0</LightColorB><LightColorA>1</LightColorA><LightRadius>0</LightRadius><LightCutoff>0</LightCutoff><LightFalloff>0</LightFalloff><LightIntensity>1</LightIntensity><FlexiEntry>false</FlexiEntry><LightEntry>false</LightEntry><SculptEntry>true</SculptEntry></Shape><Scale><X>0.03331431</X><Y>0.03331431</Y><Z>0.01499665</Z></Scale><SitTargetOrientation><X>0</X><Y>0</Y><Z>0</Z><W>1</W></SitTargetOrientation><SitTargetPosition><X>0</X><Y>0</Y><Z>0</Z></SitTargetPosition><SitTargetPositionLL><X>0</X><Y>0</Y><Z>0</Z></SitTargetPositionLL><SitTargetOrientationLL><X>0</X><Y>0</Y><Z>0</Z><W>1</W></SitTargetOrientationLL><ParentID>1472706706</ParentID><CreationDate>1471709081</CreationDate><Category>0</Category><SalePrice>10</SalePrice><ObjectSaleType>0</ObjectSaleType><OwnershipCost>0</OwnershipCost><GroupID><UUID>00000000-0000-0000-0000-000000000000</UUID></GroupID><OwnerID><UUID>86f15958-8a66-407d-8d06-6f4a6ec94bab</UUID></OwnerID><LastOwnerID><UUID>86f15958-8a66-407d-8d06-6f4a6ec94bab</UUID></LastOwnerID><RezzerID><UUID>00000000-0000-0000-0000-000000000000</UUID></RezzerID><BaseMask>647168</BaseMask><OwnerMask>647168</OwnerMask><GroupMask>0</GroupMask><EveryoneMask>0</EveryoneMask><NextOwnerMask>532480</NextOwnerMask><Flags>None</Flags><CollisionSound><UUID>00000000-0000-0000-0000-000000000000</UUID></CollisionSound><CollisionSoundVolume>0</CollisionSoundVolume><AttachedPos><X>0</X><Y>0</Y><Z>0</Z></AttachedPos><TextureAnimation /><ParticleSystem /><PayPrice0>-2</PayPrice0><PayPrice1>-2</PayPrice1><PayPrice2>-2</PayPrice2><PayPrice3>-2</PayPrice3><PayPrice4>-2</PayPrice4><Buoyancy>0</Buoyancy><Force><X>0</X><Y>0</Y><Z>0</Z></Force><Torque><X>0</X><Y>0</Y><Z>0</Z></Torque><VolumeDetectActive>false</VolumeDetectActive><PhysicsShapeType>0</PhysicsShapeType><CameraEyeOffset><X>0</X><Y>0</Y><Z>0</Z></CameraEyeOffset><CameraAtOffset><X>0</X><Y>0</Y><Z>0</Z></CameraAtOffset><SoundID><UUID>00000000-0000-0000-0000-000000000000</UUID></SoundID><SoundGain>0</SoundGain><SoundFlags>0</SoundFlags><SoundRadius>0</SoundRadius><SoundQueueing>false</SoundQueueing><CreatorData>http://grid.vibel.eu:8002;Roland Francis</CreatorData></SceneObjectPart></Part><Part><SceneObjectPart xmlns:xsi="http://www.w3.org/2001/XMLSchema-instance" xmlns:xsd="http://www.w3.org/2001/XMLSchema"><AllowedDrop>false</AllowedDrop><CreatorID><UUID>86f15958-8a66-407d-8d06-6f4a6ec94bab</UUID></CreatorID><FolderID><UUID>240f5efc-da38-48cb-be6d-e5fecb30a95b</UUID></FolderID><InventorySerial>0</InventorySerial><UUID><UUID>240f5efc-da38-48cb-be6d-e5fecb30a95b</UUID></UUID><LocalId>1472706711</LocalId><Name>Object</Name><Material>3</Material><PassTouches>false</PassTouches><PassCollisions>false</PassCollisions><RegionHandle>10985220675669248</RegionHandle><ScriptAccessPin>0</ScriptAccessPin><GroupPosition><X>-0.146437</X><Y>0.003887</Y><Z>0.010049</Z></GroupPosition><OffsetPosition><X>0.07563442</X><Y>-0.05667397</Y><Z>0.08757214</Z></OffsetPosition><RotationOffset><X>-0.03122617</X><Y>-0.8172535</Y><Z>-0.5508951</Z><W>0.1662413</W></RotationOffset><Velocity><X>0</X><Y>0</Y><Z>0</Z></Velocity><AngularVelocity><X>0</X><Y>0</Y><Z>0</Z></AngularVelocity><Acceleration><X>0</X><Y>0</Y><Z>0</Z></Acceleration><Description>(No Description)</Description><Color><R>0</R><G>0</G><B>0</B><A>255</A></Color><Text /><SitName /><TouchName /><LinkNum>6</LinkNum><ClickAction>0</ClickAction><Shape><ProfileCurve>0</ProfileCurve><TextureEntry>R0TvbCNrQAWKBDSbgqQvQQAAAAAAAAAAgD8AAACAPwAAAAAAAAAAAADAAAAAAAAAAAAAAAAAAAAAAAAAAAAA</TextureEntry><ExtraParams>ATAAEQAAAFf2i/mkAEH8obaG6MXWP+aC</ExtraParams><PathBegin>0</PathBegin><PathCurve>32</PathCurve><PathEnd>0</PathEnd><PathRadiusOffset>0</PathRadiusOffset><PathRevolutions>0</PathRevolutions><PathScaleX>100</PathScaleX><PathScaleY>150</PathScaleY><PathShearX>0</PathShearX><PathShearY>0</PathShearY><PathSkew>0</PathSkew><PathTaperX>0</PathTaperX><PathTaperY>0</PathTaperY><PathTwist>0</PathTwist><PathTwistBegin>0</PathTwistBegin><PCode>9</PCode><ProfileBegin>0</ProfileBegin><ProfileEnd>0</ProfileEnd><ProfileHollow>0</ProfileHollow><State>0</State><LastAttachPoint>0</LastAttachPoint><ProfileShape>Circle</ProfileShape><HollowShape>Same</HollowShape><SculptTexture><UUID>57f68bf9-a400-41fc-a1b6-86e8c5d63fe6</UUID></SculptTexture><SculptType>130</SculptType><FlexiSoftness>0</FlexiSoftness><FlexiTension>0</FlexiTension><FlexiDrag>0</FlexiDrag><FlexiGravity>0</FlexiGravity><FlexiWind>0</FlexiWind><FlexiForceX>0</FlexiForceX><FlexiForceY>0</FlexiForceY><FlexiForceZ>0</FlexiForceZ><LightColorR>0</LightColorR><LightColorG>0</LightColorG><LightColorB>0</LightColorB><LightColorA>1</LightColorA><LightRadius>0</LightRadius><LightCutoff>0</LightCutoff><LightFalloff>0</LightFalloff><LightIntensity>1</LightIntensity><FlexiEntry>false</FlexiEntry><LightEntry>false</LightEntry><SculptEntry>true</SculptEntry></Shape><Scale><X>0.03424565</X><Y>0.03424565</Y><Z>0.0154159</Z></Scale><SitTargetOrientation><X>0</X><Y>0</Y><Z>0</Z><W>1</W></SitTargetOrientation><SitTargetPosition><X>0</X><Y>0</Y><Z>0</Z></SitTargetPosition><SitTargetPositionLL><X>0</X><Y>0</Y><Z>0</Z></SitTargetPositionLL><SitTargetOrientationLL><X>0</X><Y>0</Y><Z>0</Z><W>1</W></SitTargetOrientationLL><ParentID>1472706706</ParentID><CreationDate>1471709081</CreationDate><Category>0</Category><SalePrice>10</SalePrice><ObjectSaleType>0</ObjectSaleType><OwnershipCost>0</OwnershipCost><GroupID><UUID>00000000-0000-0000-0000-000000000000</UUID></GroupID><OwnerID><UUID>86f15958-8a66-407d-8d06-6f4a6ec94bab</UUID></OwnerID><LastOwnerID><UUID>86f15958-8a66-407d-8d06-6f4a6ec94bab</UUID></LastOwnerID><RezzerID><UUID>00000000-0000-0000-0000-000000000000</UUID></RezzerID><BaseMask>647168</BaseMask><OwnerMask>647168</OwnerMask><GroupMask>0</GroupMask><EveryoneMask>0</EveryoneMask><NextOwnerMask>532480</NextOwnerMask><Flags>None</Flags><CollisionSound><UUID>00000000-0000-0000-0000-000000000000</UUID></CollisionSound><CollisionSoundVolume>0</CollisionSoundVolume><AttachedPos><X>0</X><Y>0</Y><Z>0</Z></AttachedPos><TextureAnimation /><ParticleSystem /><PayPrice0>-2</PayPrice0><PayPrice1>-2</PayPrice1><PayPrice2>-2</PayPrice2><PayPrice3>-2</PayPrice3><PayPrice4>-2</PayPrice4><Buoyancy>0</Buoyancy><Force><X>0</X><Y>0</Y><Z>0</Z></Force><Torque><X>0</X><Y>0</Y><Z>0</Z></Torque><VolumeDetectActive>false</VolumeDetectActive><PhysicsShapeType>0</PhysicsShapeType><CameraEyeOffset><X>0</X><Y>0</Y><Z>0</Z></CameraEyeOffset><CameraAtOffset><X>0</X><Y>0</Y><Z>0</Z></CameraAtOffset><SoundID><UUID>00000000-0000-0000-0000-000000000000</UUID></SoundID><SoundGain>0</SoundGain><SoundFlags>0</SoundFlags><SoundRadius>0</SoundRadius><SoundQueueing>false</SoundQueueing><CreatorData>http://grid.vibel.eu:8002;Roland Francis</CreatorData></SceneObjectPart></Part><Part><SceneObjectPart xmlns:xsi="http://www.w3.org/2001/XMLSchema-instance" xmlns:xsd="http://www.w3.org/2001/XMLSchema"><AllowedDrop>false</AllowedDrop><CreatorID><UUID>86f15958-8a66-407d-8d06-6f4a6ec94bab</UUID></CreatorID><FolderID><UUID>916132df-1ea8-4cc9-8160-d5bdc2e825a1</UUID></FolderID><InventorySerial>0</InventorySerial><UUID><UUID>916132df-1ea8-4cc9-8160-d5bdc2e825a1</UUID></UUID><LocalId>1472706712</LocalId><Name>Object</Name><Material>3</Material><PassTouches>false</PassTouches><PassCollisions>false</PassCollisions><RegionHandle>10985220675669248</RegionHandle><ScriptAccessPin>0</ScriptAccessPin><GroupPosition><X>-0.146437</X><Y>0.003887</Y><Z>0.010049</Z></GroupPosition><OffsetPosition><X>0.07957916</X><Y>-0.06136194</Y><Z>0.0948078</Z></OffsetPosition><RotationOffset><X>0.6282969</X><Y>-0.1368171</Y><Z>0.4224502</Z><W>0.6387958</W></RotationOffset><Velocity><X>0</X><Y>0</Y><Z>0</Z></Velocity><AngularVelocity><X>0</X><Y>0</Y><Z>0</Z></AngularVelocity><Acceleration><X>0</X><Y>0</Y><Z>0</Z></Acceleration><Description>(No Description)</Description><Color><R>0</R><G>0</G><B>0</B><A>255</A></Color><Text /><SitName /><TouchName /><LinkNum>7</LinkNum><ClickAction>0</ClickAction><Shape><ProfileCurve>0</ProfileCurve><TextureEntry>R0TvbCNrQAWKBDSbgqQvQQAAAAAAAAAAgD8AAACAPwAAAAAAAAAAAADAAAAAAAAAAAAAAAAAAAAAAAAAAAAA</TextureEntry><ExtraParams>ATAAEQAAAFf2i/mkAEH8obaG6MXWP+aC</ExtraParams><PathBegin>0</PathBegin><PathCurve>32</PathCurve><PathEnd>0</PathEnd><PathRadiusOffset>0</PathRadiusOffset><PathRevolutions>0</PathRevolutions><PathScaleX>100</PathScaleX><PathScaleY>150</PathScaleY><PathShearX>0</PathShearX><PathShearY>0</PathShearY><PathSkew>0</PathSkew><PathTaperX>0</PathTaperX><PathTaperY>0</PathTaperY><PathTwist>0</PathTwist><PathTwistBegin>0</PathTwistBegin><PCode>9</PCode><ProfileBegin>0</ProfileBegin><ProfileEnd>0</ProfileEnd><ProfileHollow>0</ProfileHollow><State>0</State><LastAttachPoint>0</LastAttachPoint><ProfileShape>Circle</ProfileShape><HollowShape>Same</HollowShape><SculptTexture><UUID>57f68bf9-a400-41fc-a1b6-86e8c5d63fe6</UUID></SculptTexture><SculptType>130</SculptType><FlexiSoftness>0</FlexiSoftness><FlexiTension>0</FlexiTension><FlexiDrag>0</FlexiDrag><FlexiGravity>0</FlexiGravity><FlexiWind>0</FlexiWind><FlexiForceX>0</FlexiForceX><FlexiForceY>0</FlexiForceY><FlexiForceZ>0</FlexiForceZ><LightColorR>0</LightColorR><LightColorG>0</LightColorG><LightColorB>0</LightColorB><LightColorA>1</LightColorA><LightRadius>0</LightRadius><LightCutoff>0</LightCutoff><LightFalloff>0</LightFalloff><LightIntensity>1</LightIntensity><FlexiEntry>false</FlexiEntry><LightEntry>false</LightEntry><SculptEntry>true</SculptEntry></Shape><Scale><X>0.03331431</X><Y>0.03331431</Y><Z>0.01499665</Z></Scale><SitTargetOrientation><X>0</X><Y>0</Y><Z>0</Z><W>1</W></SitTargetOrientation><SitTargetPosition><X>0</X><Y>0</Y><Z>0</Z></SitTargetPosition><SitTargetPositionLL><X>0</X><Y>0</Y><Z>0</Z></SitTargetPositionLL><SitTargetOrientationLL><X>0</X><Y>0</Y><Z>0</Z><W>1</W></SitTargetOrientationLL><ParentID>1472706706</ParentID><CreationDate>1471709081</CreationDate><Category>0</Category><SalePrice>10</SalePrice><ObjectSaleType>0</ObjectSaleType><OwnershipCost>0</OwnershipCost><GroupID><UUID>00000000-0000-0000-0000-000000000000</UUID></GroupID><OwnerID><UUID>86f15958-8a66-407d-8d06-6f4a6ec94bab</UUID></OwnerID><LastOwnerID><UUID>86f15958-8a66-407d-8d06-6f4a6ec94bab</UUID></LastOwnerID><RezzerID><UUID>00000000-0000-0000-0000-000000000000</UUID></RezzerID><BaseMask>647168</BaseMask><OwnerMask>647168</OwnerMask><GroupMask>0</GroupMask><EveryoneMask>0</EveryoneMask><NextOwnerMask>532480</NextOwnerMask><Flags>None</Flags><CollisionSound><UUID>00000000-0000-0000-0000-000000000000</UUID></CollisionSound><CollisionSoundVolume>0</CollisionSoundVolume><AttachedPos><X>0</X><Y>0</Y><Z>0</Z></AttachedPos><TextureAnimation /><ParticleSystem /><PayPrice0>-2</PayPrice0><PayPrice1>-2</PayPrice1><PayPrice2>-2</PayPrice2><PayPrice3>-2</PayPrice3><PayPrice4>-2</PayPrice4><Buoyancy>0</Buoyancy><Force><X>0</X><Y>0</Y><Z>0</Z></Force><Torque><X>0</X><Y>0</Y><Z>0</Z></Torque><VolumeDetectActive>false</VolumeDetectActive><PhysicsShapeType>0</PhysicsShapeType><CameraEyeOffset><X>0</X><Y>0</Y><Z>0</Z></CameraEyeOffset><CameraAtOffset><X>0</X><Y>0</Y><Z>0</Z></CameraAtOffset><SoundID><UUID>00000000-0000-0000-0000-000000000000</UUID></SoundID><SoundGain>0</SoundGain><SoundFlags>0</SoundFlags><SoundRadius>0</SoundRadius><SoundQueueing>false</SoundQueueing><CreatorData>http://grid.vibel.eu:8002;Roland Francis</CreatorData></SceneObjectPart></Part><Part><SceneObjectPart xmlns:xsi="http://www.w3.org/2001/XMLSchema-instance" xmlns:xsd="http://www.w3.org/2001/XMLSchema"><AllowedDrop>false</AllowedDrop><CreatorID><UUID>86f15958-8a66-407d-8d06-6f4a6ec94bab</UUID></CreatorID><FolderID><UUID>b36b6020-b46c-4198-a4ed-51c02039c97d</UUID></FolderID><InventorySerial>0</InventorySerial><UUID><UUID>b36b6020-b46c-4198-a4ed-51c02039c97d</UUID></UUID><LocalId>1472706713</LocalId><Name>Object</Name><Material>3</Material><PassTouches>false</PassTouches><PassCollisions>false</PassCollisions><RegionHandle>10985220675669248</RegionHandle><ScriptAccessPin>0</ScriptAccessPin><GroupPosition><X>-0.146437</X><Y>0.003887</Y><Z>0.010049</Z></GroupPosition><OffsetPosition><X>0.07426982</X><Y>-0.06272699</Y><Z>0.08632093</Z></OffsetPosition><RotationOffset><X>0.7129827</X><Y>-0.3456773</Y><Z>0.2023373</Z><W>0.5755193</W></RotationOffset><Velocity><X>0</X><Y>0</Y><Z>0</Z></Velocity><AngularVelocity><X>0</X><Y>0</Y><Z>0</Z></AngularVelocity><Acceleration><X>0</X><Y>0</Y><Z>0</Z></Acceleration><Description>(No Description)</Description><Color><R>0</R><G>0</G><B>0</B><A>255</A></Color><Text /><SitName /><TouchName /><LinkNum>8</LinkNum><ClickAction>0</ClickAction><Shape><ProfileCurve>0</ProfileCurve><TextureEntry>R0TvbCNrQAWKBDSbgqQvQQAAAAAAAAAAgD8AAACAPwAAAAAAAAAAAADAAAAAAAAAAAAAAAAAAAAAAAAAAAAA</TextureEntry><ExtraParams>ATAAEQAAAFf2i/mkAEH8obaG6MXWP+aC</ExtraParams><PathBegin>0</PathBegin><PathCurve>32</PathCurve><PathEnd>0</PathEnd><PathRadiusOffset>0</PathRadiusOffset><PathRevolutions>0</PathRevolutions><PathScaleX>100</PathScaleX><PathScaleY>150</PathScaleY><PathShearX>0</PathShearX><PathShearY>0</PathShearY><PathSkew>0</PathSkew><PathTaperX>0</PathTaperX><PathTaperY>0</PathTaperY><PathTwist>0</PathTwist><PathTwistBegin>0</PathTwistBegin><PCode>9</PCode><ProfileBegin>0</ProfileBegin><ProfileEnd>0</ProfileEnd><ProfileHollow>0</ProfileHollow><State>0</State><LastAttachPoint>0</LastAttachPoint><ProfileShape>Circle</ProfileShape><HollowShape>Same</HollowShape><SculptTexture><UUID>57f68bf9-a400-41fc-a1b6-86e8c5d63fe6</UUID></SculptTexture><SculptType>130</SculptType><FlexiSoftness>0</FlexiSoftness><FlexiTension>0</FlexiTension><FlexiDrag>0</FlexiDrag><FlexiGravity>0</FlexiGravity><FlexiWind>0</FlexiWind><FlexiForceX>0</FlexiForceX><FlexiForceY>0</FlexiForceY><FlexiForceZ>0</FlexiForceZ><LightColorR>0</LightColorR><LightColorG>0</LightColorG><LightColorB>0</LightColorB><LightColorA>1</LightColorA><LightRadius>0</LightRadius><LightCutoff>0</LightCutoff><LightFalloff>0</LightFalloff><LightIntensity>1</LightIntensity><FlexiEntry>false</FlexiEntry><LightEntry>false</LightEntry><SculptEntry>true</SculptEntry></Shape><Scale><X>0.03331431</X><Y>0.03331431</Y><Z>0.01499665</Z></Scale><SitTargetOrientation><X>0</X><Y>0</Y><Z>0</Z><W>1</W></SitTargetOrientation><SitTargetPosition><X>0</X><Y>0</Y><Z>0</Z></SitTargetPosition><SitTargetPositionLL><X>0</X><Y>0</Y><Z>0</Z></SitTargetPositionLL><SitTargetOrientationLL><X>0</X><Y>0</Y><Z>0</Z><W>1</W></SitTargetOrientationLL><ParentID>1472706706</ParentID><CreationDate>1471709081</CreationDate><Category>0</Category><SalePrice>10</SalePrice><ObjectSaleType>0</ObjectSaleType><OwnershipCost>0</OwnershipCost><GroupID><UUID>00000000-0000-0000-0000-000000000000</UUID></GroupID><OwnerID><UUID>86f15958-8a66-407d-8d06-6f4a6ec94bab</UUID></OwnerID><LastOwnerID><UUID>86f15958-8a66-407d-8d06-6f4a6ec94bab</UUID></LastOwnerID><RezzerID><UUID>00000000-0000-0000-0000-000000000000</UUID></RezzerID><BaseMask>647168</BaseMask><OwnerMask>647168</OwnerMask><GroupMask>0</GroupMask><EveryoneMask>0</EveryoneMask><NextOwnerMask>532480</NextOwnerMask><Flags>None</Flags><CollisionSound><UUID>00000000-0000-0000-0000-000000000000</UUID></CollisionSound><CollisionSoundVolume>0</CollisionSoundVolume><AttachedPos><X>0</X><Y>0</Y><Z>0</Z></AttachedPos><TextureAnimation /><ParticleSystem /><PayPrice0>-2</PayPrice0><PayPrice1>-2</PayPrice1><PayPrice2>-2</PayPrice2><PayPrice3>-2</PayPrice3><PayPrice4>-2</PayPrice4><Buoyancy>0</Buoyancy><Force><X>0</X><Y>0</Y><Z>0</Z></Force><Torque><X>0</X><Y>0</Y><Z>0</Z></Torque><VolumeDetectActive>false</VolumeDetectActive><PhysicsShapeType>0</PhysicsShapeType><CameraEyeOffset><X>0</X><Y>0</Y><Z>0</Z></CameraEyeOffset><CameraAtOffset><X>0</X><Y>0</Y><Z>0</Z></CameraAtOffset><SoundID><UUID>00000000-0000-0000-0000-000000000000</UUID></SoundID><SoundGain>0</SoundGain><SoundFlags>0</SoundFlags><SoundRadius>0</SoundRadius><SoundQueueing>false</SoundQueueing><CreatorData>http://grid.vibel.eu:8002;Roland Francis</CreatorData></SceneObjectPart></Part><Part><SceneObjectPart xmlns:xsi="http://www.w3.org/2001/XMLSchema-instance" xmlns:xsd="http://www.w3.org/2001/XMLSchema"><AllowedDrop>false</AllowedDrop><CreatorID><UUID>86f15958-8a66-407d-8d06-6f4a6ec94bab</UUID></CreatorID><FolderID><UUID>79074d48-de7f-4e0f-a50a-a3f8c25e7061</UUID></FolderID><InventorySerial>0</InventorySerial><UUID><UUID>79074d48-de7f-4e0f-a50a-a3f8c25e7061</UUID></UUID><LocalId>1472706714</LocalId><Name>Object</Name><Material>3</Material><PassTouches>false</PassTouches><PassCollisions>false</PassCollisions><RegionHandle>10985220675669248</RegionHandle><ScriptAccessPin>0</ScriptAccessPin><GroupPosition><X>-0.146437</X><Y>0.003887</Y><Z>0.010049</Z></GroupPosition><OffsetPosition><X>0.05136654</X><Y>-0.06326751</Y><Z>0.1036012</Z></OffsetPosition><RotationOffset><X>0.01395289</X><Y>-0.7569847</Y><Z>-0.592073</Z><W>0.2760961</W></RotationOffset><Velocity><X>0</X><Y>0</Y><Z>0</Z></Velocity><AngularVelocity><X>0</X><Y>0</Y><Z>0</Z></AngularVelocity><Acceleration><X>0</X><Y>0</Y><Z>0</Z></Acceleration><Description>(No Description)</Description><Color><R>0</R><G>0</G><B>0</B><A>255</A></Color><Text /><SitName /><TouchName /><LinkNum>9</LinkNum><ClickAction>0</ClickAction><Shape><ProfileCurve>0</ProfileCurve><TextureEntry>R0TvbCNrQAWKBDSbgqQvQQAAAAAAAAAAgD8AAACAPwAAAAAAAAAAAADAAAAAAAAAAAAAAAAAAAAAAAAAAAAA</TextureEntry><ExtraParams>ATAAEQAAAFf2i/mkAEH8obaG6MXWP+aC</ExtraParams><PathBegin>0</PathBegin><PathCurve>32</PathCurve><PathEnd>0</PathEnd><PathRadiusOffset>0</PathRadiusOffset><PathRevolutions>0</PathRevolutions><PathScaleX>100</PathScaleX><PathScaleY>150</PathScaleY><PathShearX>0</PathShearX><PathShearY>0</PathShearY><PathSkew>0</PathSkew><PathTaperX>0</PathTaperX><PathTaperY>0</PathTaperY><PathTwist>0</PathTwist><PathTwistBegin>0</PathTwistBegin><PCode>9</PCode><ProfileBegin>0</ProfileBegin><ProfileEnd>0</ProfileEnd><ProfileHollow>0</ProfileHollow><State>0</State><LastAttachPoint>0</LastAttachPoint><ProfileShape>Circle</ProfileShape><HollowShape>Same</HollowShape><SculptTexture><UUID>57f68bf9-a400-41fc-a1b6-86e8c5d63fe6</UUID></SculptTexture><SculptType>130</SculptType><FlexiSoftness>0</FlexiSoftness><FlexiTension>0</FlexiTension><FlexiDrag>0</FlexiDrag><FlexiGravity>0</FlexiGravity><FlexiWind>0</FlexiWind><FlexiForceX>0</FlexiForceX><FlexiForceY>0</FlexiForceY><FlexiForceZ>0</FlexiForceZ><LightColorR>0</LightColorR><LightColorG>0</LightColorG><LightColorB>0</LightColorB><LightColorA>1</LightColorA><LightRadius>0</LightRadius><LightCutoff>0</LightCutoff><LightFalloff>0</LightFalloff><LightIntensity>1</LightIntensity><FlexiEntry>false</FlexiEntry><LightEntry>false</LightEntry><SculptEntry>true</SculptEntry></Shape><Scale><X>0.03331431</X><Y>0.03331431</Y><Z>0.01499665</Z></Scale><SitTargetOrientation><X>0</X><Y>0</Y><Z>0</Z><W>1</W></SitTargetOrientation><SitTargetPosition><X>0</X><Y>0</Y><Z>0</Z></SitTargetPosition><SitTargetPositionLL><X>0</X><Y>0</Y><Z>0</Z></SitTargetPositionLL><SitTargetOrientationLL><X>0</X><Y>0</Y><Z>0</Z><W>1</W></SitTargetOrientationLL><ParentID>1472706706</ParentID><CreationDate>1471709081</CreationDate><Category>0</Category><SalePrice>10</SalePrice><ObjectSaleType>0</ObjectSaleType><OwnershipCost>0</OwnershipCost><GroupID><UUID>00000000-0000-0000-0000-000000000000</UUID></GroupID><OwnerID><UUID>86f15958-8a66-407d-8d06-6f4a6ec94bab</UUID></OwnerID><LastOwnerID><UUID>86f15958-8a66-407d-8d06-6f4a6ec94bab</UUID></LastOwnerID><RezzerID><UUID>00000000-0000-0000-0000-000000000000</UUID></RezzerID><BaseMask>647168</BaseMask><OwnerMask>647168</OwnerMask><GroupMask>0</GroupMask><EveryoneMask>0</EveryoneMask><NextOwnerMask>532480</NextOwnerMask><Flags>None</Flags><CollisionSound><UUID>00000000-0000-0000-0000-000000000000</UUID></CollisionSound><CollisionSoundVolume>0</CollisionSoundVolume><AttachedPos><X>0</X><Y>0</Y><Z>0</Z></AttachedPos><TextureAnimation /><ParticleSystem /><PayPrice0>-2</PayPrice0><PayPrice1>-2</PayPrice1><PayPrice2>-2</PayPrice2><PayPrice3>-2</PayPrice3><PayPrice4>-2</PayPrice4><Buoyancy>0</Buoyancy><Force><X>0</X><Y>0</Y><Z>0</Z></Force><Torque><X>0</X><Y>0</Y><Z>0</Z></Torque><VolumeDetectActive>false</VolumeDetectActive><PhysicsShapeType>0</PhysicsShapeType><CameraEyeOffset><X>0</X><Y>0</Y><Z>0</Z></CameraEyeOffset><CameraAtOffset><X>0</X><Y>0</Y><Z>0</Z></CameraAtOffset><SoundID><UUID>00000000-0000-0000-0000-000000000000</UUID></SoundID><SoundGain>0</SoundGain><SoundFlags>0</SoundFlags><SoundRadius>0</SoundRadius><SoundQueueing>false</SoundQueueing><CreatorData>http://grid.vibel.eu:8002;Roland Francis</CreatorData></SceneObjectPart></Part><Part><SceneObjectPart xmlns:xsi="http://www.w3.org/2001/XMLSchema-instance" xmlns:xsd="http://www.w3.org/2001/XMLSchema"><AllowedDrop>false</AllowedDrop><CreatorID><UUID>86f15958-8a66-407d-8d06-6f4a6ec94bab</UUID></CreatorID><FolderID><UUID>ddc308fe-faeb-4671-8f4d-25d293aeda7c</UUID></FolderID><InventorySerial>0</InventorySerial><UUID><UUID>ddc308fe-faeb-4671-8f4d-25d293aeda7c</UUID></UUID><LocalId>1472706715</LocalId><Name>BootAnkleStrap</Name><Material>3</Material><PassTouches>false</PassTouches><PassCollisions>false</PassCollisions><RegionHandle>10985220675669248</RegionHandle><ScriptAccessPin>0</ScriptAccessPin><GroupPosition><X>-0.146437</X><Y>0.003887</Y><Z>0.010049</Z></GroupPosition><OffsetPosition><X>0.02069705</X><Y>-0.0004951223</Y><Z>0.1041001</Z></OffsetPosition><RotationOffset><X>-0.01302882</X><Y>-0.04336765</Y><Z>-0.008644016</Z><W>0.9989368</W></RotationOffset><Velocity><X>0</X><Y>0</Y><Z>0</Z></Velocity><AngularVelocity><X>0</X><Y>0</Y><Z>0</Z></AngularVelocity><Acceleration><X>0</X><Y>0</Y><Z>0</Z></Acceleration><Description>(No Description)</Description><Color><R>0</R><G>0</G><B>0</B><A>255</A></Color><Text /><SitName /><TouchName /><LinkNum>10</LinkNum><ClickAction>0</ClickAction><Shape><ProfileCurve>0</ProfileCurve><TextureEntry>YxLLqER/RhKD70PJzWqWAAAAAAAAAAAAgD8AAACAPwAAAAAAAAAAAABAAAAAAAAAAAAAAAAAAAAAAAAAAAAA</TextureEntry><ExtraParams>ATAAEQAAAAHX00iK70yXpFtjZ0D+EyYC</ExtraParams><PathBegin>0</PathBegin><PathCurve>32</PathCurve><PathEnd>0</PathEnd><PathRadiusOffset>0</PathRadiusOffset><PathRevolutions>0</PathRevolutions><PathScaleX>100</PathScaleX><PathScaleY>150</PathScaleY><PathShearX>0</PathShearX><PathShearY>0</PathShearY><PathSkew>0</PathSkew><PathTaperX>0</PathTaperX><PathTaperY>0</PathTaperY><PathTwist>0</PathTwist><PathTwistBegin>0</PathTwistBegin><PCode>9</PCode><ProfileBegin>0</ProfileBegin><ProfileEnd>0</ProfileEnd><ProfileHollow>0</ProfileHollow><State>0</State><LastAttachPoint>0</LastAttachPoint><ProfileShape>Circle</ProfileShape><HollowShape>Same</HollowShape><SculptTexture><UUID>01d7d348-8aef-4c97-a45b-636740fe1326</UUID></SculptTexture><SculptType>2</SculptType><FlexiSoftness>0</FlexiSoftness><FlexiTension>0</FlexiTension><FlexiDrag>0</FlexiDrag><FlexiGravity>0</FlexiGravity><FlexiWind>0</FlexiWind><FlexiForceX>0</FlexiForceX><FlexiForceY>0</FlexiForceY><FlexiForceZ>0</FlexiForceZ><LightColorR>0</LightColorR><LightColorG>0</LightColorG><LightColorB>0</LightColorB><LightColorA>1</LightColorA><LightRadius>0</LightRadius><LightCutoff>0</LightCutoff><LightFalloff>0</LightFalloff><LightIntensity>1</LightIntensity><FlexiEntry>false</FlexiEntry><LightEntry>false</LightEntry><SculptEntry>true</SculptEntry></Shape><Scale><X>0.1574442</X><Y>0.1292684</Y><Z>0.0335226</Z></Scale><SitTargetOrientation><X>0</X><Y>0</Y><Z>0</Z><W>1</W></SitTargetOrientation><SitTargetPosition><X>0</X><Y>0</Y><Z>0</Z></SitTargetPosition><SitTargetPositionLL><X>0</X><Y>0</Y><Z>0</Z></SitTargetPositionLL><SitTargetOrientationLL><X>0</X><Y>0</Y><Z>0</Z><W>1</W></SitTargetOrientationLL><ParentID>1472706706</ParentID><CreationDate>1471709081</CreationDate><Category>0</Category><SalePrice>10</SalePrice><ObjectSaleType>0</ObjectSaleType><OwnershipCost>0</OwnershipCost><GroupID><UUID>00000000-0000-0000-0000-000000000000</UUID></GroupID><OwnerID><UUID>86f15958-8a66-407d-8d06-6f4a6ec94bab</UUID></OwnerID><LastOwnerID><UUID>86f15958-8a66-407d-8d06-6f4a6ec94bab</UUID></LastOwnerID><RezzerID><UUID>00000000-0000-0000-0000-000000000000</UUID></RezzerID><BaseMask>647168</BaseMask><OwnerMask>647168</OwnerMask><GroupMask>0</GroupMask><EveryoneMask>0</EveryoneMask><NextOwnerMask>532480</NextOwnerMask><Flags>None</Flags><CollisionSound><UUID>00000000-0000-0000-0000-000000000000</UUID></CollisionSound><CollisionSoundVolume>0</CollisionSoundVolume><AttachedPos><X>0</X><Y>0</Y><Z>0</Z></AttachedPos><TextureAnimation /><ParticleSystem /><PayPrice0>-2</PayPrice0><PayPrice1>-2</PayPrice1><PayPrice2>-2</PayPrice2><PayPrice3>-2</PayPrice3><PayPrice4>-2</PayPrice4><Buoyancy>0</Buoyancy><Force><X>0</X><Y>0</Y><Z>0</Z></Force><Torque><X>0</X><Y>0</Y><Z>0</Z></Torque><VolumeDetectActive>false</VolumeDetectActive><PhysicsShapeType>0</PhysicsShapeType><CameraEyeOffset><X>0</X><Y>0</Y><Z>0</Z></CameraEyeOffset><CameraAtOffset><X>0</X><Y>0</Y><Z>0</Z></CameraAtOffset><SoundID><UUID>00000000-0000-0000-0000-000000000000</UUID></SoundID><SoundGain>0</SoundGain><SoundFlags>0</SoundFlags><SoundRadius>0</SoundRadius><SoundQueueing>false</SoundQueueing><CreatorData>http://grid.vibel.eu:8002;Roland Francis</CreatorData></SceneObjectPart></Part><Part><SceneObjectPart xmlns:xsi="http://www.w3.org/2001/XMLSchema-instance" xmlns:xsd="http://www.w3.org/2001/XMLSchema"><AllowedDrop>false</AllowedDrop><CreatorID><UUID>86f15958-8a66-407d-8d06-6f4a6ec94bab</UUID></CreatorID><FolderID><UUID>847c3602-24a8-4d69-8b3f-9c261e0e4df8</UUID></FolderID><InventorySerial>0</InventorySerial><UUID><UUID>847c3602-24a8-4d69-8b3f-9c261e0e4df8</UUID></UUID><LocalId>1472706716</LocalId><Name>Object</Name><Material>3</Material><PassTouches>false</PassTouches><PassCollisions>false</PassCollisions><RegionHandle>10985220675669248</RegionHandle><ScriptAccessPin>0</ScriptAccessPin><GroupPosition><X>-0.146437</X><Y>0.003887</Y><Z>0.010049</Z></GroupPosition><OffsetPosition><X>0.04021528</X><Y>-0.06510708</Y><Z>0.1032171</Z></OffsetPosition><RotationOffset><X>-0.1313292</X><Y>-0.7507629</Y><Z>-0.6255297</Z><W>0.1667936</W></RotationOffset><Velocity><X>0</X><Y>0</Y><Z>0</Z></Velocity><AngularVelocity><X>0</X><Y>0</Y><Z>0</Z></AngularVelocity><Acceleration><X>0</X><Y>0</Y><Z>0</Z></Acceleration><Description>(No Description)</Description><Color><R>0</R><G>0</G><B>0</B><A>255</A></Color><Text /><SitName /><TouchName /><LinkNum>11</LinkNum><ClickAction>0</ClickAction><Shape><ProfileCurve>0</ProfileCurve><TextureEntry>R0TvbCNrQAWKBDSbgqQvQQAAAAAAAAAAgD8AAACAPwAAAAAAAAAAAADAAAAAAAAAAAAAAAAAAAAAAAAAAAAA</TextureEntry><ExtraParams>ATAAEQAAAFf2i/mkAEH8obaG6MXWP+aC</ExtraParams><PathBegin>0</PathBegin><PathCurve>32</PathCurve><PathEnd>0</PathEnd><PathRadiusOffset>0</PathRadiusOffset><PathRevolutions>0</PathRevolutions><PathScaleX>100</PathScaleX><PathScaleY>150</PathScaleY><PathShearX>0</PathShearX><PathShearY>0</PathShearY><PathSkew>0</PathSkew><PathTaperX>0</PathTaperX><PathTaperY>0</PathTaperY><PathTwist>0</PathTwist><PathTwistBegin>0</PathTwistBegin><PCode>9</PCode><ProfileBegin>0</ProfileBegin><ProfileEnd>0</ProfileEnd><ProfileHollow>0</ProfileHollow><State>0</State><LastAttachPoint>0</LastAttachPoint><ProfileShape>Circle</ProfileShape><HollowShape>Same</HollowShape><SculptTexture><UUID>57f68bf9-a400-41fc-a1b6-86e8c5d63fe6</UUID></SculptTexture><SculptType>130</SculptType><FlexiSoftness>0</FlexiSoftness><FlexiTension>0</FlexiTension><FlexiDrag>0</FlexiDrag><FlexiGravity>0</FlexiGravity><FlexiWind>0</FlexiWind><FlexiForceX>0</FlexiForceX><FlexiForceY>0</FlexiForceY><FlexiForceZ>0</FlexiForceZ><LightColorR>0</LightColorR><LightColorG>0</LightColorG><LightColorB>0</LightColorB><LightColorA>1</LightColorA><LightRadius>0</LightRadius><LightCutoff>0</LightCutoff><LightFalloff>0</LightFalloff><LightIntensity>1</LightIntensity><FlexiEntry>false</FlexiEntry><LightEntry>false</LightEntry><SculptEntry>true</SculptEntry></Shape><Scale><X>0.03331431</X><Y>0.03331431</Y><Z>0.01499665</Z></Scale><SitTargetOrientation><X>0</X><Y>0</Y><Z>0</Z><W>1</W></SitTargetOrientation><SitTargetPosition><X>0</X><Y>0</Y><Z>0</Z></SitTargetPosition><SitTargetPositionLL><X>0</X><Y>0</Y><Z>0</Z></SitTargetPositionLL><SitTargetOrientationLL><X>0</X><Y>0</Y><Z>0</Z><W>1</W></SitTargetOrientationLL><ParentID>1472706706</ParentID><CreationDate>1471709081</CreationDate><Category>0</Category><SalePrice>10</SalePrice><ObjectSaleType>0</ObjectSaleType><OwnershipCost>0</OwnershipCost><GroupID><UUID>00000000-0000-0000-0000-000000000000</UUID></GroupID><OwnerID><UUID>86f15958-8a66-407d-8d06-6f4a6ec94bab</UUID></OwnerID><LastOwnerID><UUID>86f15958-8a66-407d-8d06-6f4a6ec94bab</UUID></LastOwnerID><RezzerID><UUID>00000000-0000-0000-0000-000000000000</UUID></RezzerID><BaseMask>647168</BaseMask><OwnerMask>647168</OwnerMask><GroupMask>0</GroupMask><EveryoneMask>0</EveryoneMask><NextOwnerMask>532480</NextOwnerMask><Flags>None</Flags><CollisionSound><UUID>00000000-0000-0000-0000-000000000000</UUID></CollisionSound><CollisionSoundVolume>0</CollisionSoundVolume><AttachedPos><X>0</X><Y>0</Y><Z>0</Z></AttachedPos><TextureAnimation /><ParticleSystem /><PayPrice0>-2</PayPrice0><PayPrice1>-2</PayPrice1><PayPrice2>-2</PayPrice2><PayPrice3>-2</PayPrice3><PayPrice4>-2</PayPrice4><Buoyancy>0</Buoyancy><Force><X>0</X><Y>0</Y><Z>0</Z></Force><Torque><X>0</X><Y>0</Y><Z>0</Z></Torque><VolumeDetectActive>false</VolumeDetectActive><PhysicsShapeType>0</PhysicsShapeType><CameraEyeOffset><X>0</X><Y>0</Y><Z>0</Z></CameraEyeOffset><CameraAtOffset><X>0</X><Y>0</Y><Z>0</Z></CameraAtOffset><SoundID><UUID>00000000-0000-0000-0000-000000000000</UUID></SoundID><SoundGain>0</SoundGain><SoundFlags>0</SoundFlags><SoundRadius>0</SoundRadius><SoundQueueing>false</SoundQueueing><CreatorData>http://grid.vibel.eu:8002;Roland Francis</CreatorData></SceneObjectPart></Part><Part><SceneObjectPart xmlns:xsi="http://www.w3.org/2001/XMLSchema-instance" xmlns:xsd="http://www.w3.org/2001/XMLSchema"><AllowedDrop>false</AllowedDrop><CreatorID><UUID>86f15958-8a66-407d-8d06-6f4a6ec94bab</UUID></CreatorID><FolderID><UUID>af0951eb-d9a5-4bdc-834e-e5f4b7612eeb</UUID></FolderID><InventorySerial>0</InventorySerial><UUID><UUID>af0951eb-d9a5-4bdc-834e-e5f4b7612eeb</UUID></UUID><LocalId>1472706717</LocalId><Name>Object</Name><Material>3</Material><PassTouches>false</PassTouches><PassCollisions>false</PassCollisions><RegionHandle>10985220675669248</RegionHandle><ScriptAccessPin>0</ScriptAccessPin><GroupPosition><X>-0.146437</X><Y>0.003887</Y><Z>0.010049</Z></GroupPosition><OffsetPosition><X>0.06155046</X><Y>-0.06269773</Y><Z>0.06022687</Z></OffsetPosition><RotationOffset><X>-0.04247966</X><Y>-0.7600129</Y><Z>-0.6234877</Z><W>0.1784347</W></RotationOffset><Velocity><X>0</X><Y>0</Y><Z>0</Z></Velocity><AngularVelocity><X>0</X><Y>0</Y><Z>0</Z></AngularVelocity><Acceleration><X>0</X><Y>0</Y><Z>0</Z></Acceleration><Description>(No Description)</Description><Color><R>0</R><G>0</G><B>0</B><A>255</A></Color><Text /><SitName /><TouchName /><LinkNum>12</LinkNum><ClickAction>0</ClickAction><Shape><ProfileCurve>0</ProfileCurve><TextureEntry>R0TvbCNrQAWKBDSbgqQvQQAAAAAAAAAAgD8AAACAPwAAAAAAAAAAAADAAAAAAAAAAAAAAAAAAAAAAAAAAAAA</TextureEntry><ExtraParams>ATAAEQAAAFf2i/mkAEH8obaG6MXWP+aC</ExtraParams><PathBegin>0</PathBegin><PathCurve>32</PathCurve><PathEnd>0</PathEnd><PathRadiusOffset>0</PathRadiusOffset><PathRevolutions>0</PathRevolutions><PathScaleX>100</PathScaleX><PathScaleY>150</PathScaleY><PathShearX>0</PathShearX><PathShearY>0</PathShearY><PathSkew>0</PathSkew><PathTaperX>0</PathTaperX><PathTaperY>0</PathTaperY><PathTwist>0</PathTwist><PathTwistBegin>0</PathTwistBegin><PCode>9</PCode><ProfileBegin>0</ProfileBegin><ProfileEnd>0</ProfileEnd><ProfileHollow>0</ProfileHollow><State>0</State><LastAttachPoint>0</LastAttachPoint><ProfileShape>Circle</ProfileShape><HollowShape>Same</HollowShape><SculptTexture><UUID>57f68bf9-a400-41fc-a1b6-86e8c5d63fe6</UUID></SculptTexture><SculptType>130</SculptType><FlexiSoftness>0</FlexiSoftness><FlexiTension>0</FlexiTension><FlexiDrag>0</FlexiDrag><FlexiGravity>0</FlexiGravity><FlexiWind>0</FlexiWind><FlexiForceX>0</FlexiForceX><FlexiForceY>0</FlexiForceY><FlexiForceZ>0</FlexiForceZ><LightColorR>0</LightColorR><LightColorG>0</LightColorG><LightColorB>0</LightColorB><LightColorA>1</LightColorA><LightRadius>0</LightRadius><LightCutoff>0</LightCutoff><LightFalloff>0</LightFalloff><LightIntensity>1</LightIntensity><FlexiEntry>false</FlexiEntry><LightEntry>false</LightEntry><SculptEntry>true</SculptEntry></Shape><Scale><X>0.03424565</X><Y>0.03424565</Y><Z>0.0154159</Z></Scale><SitTargetOrientation><X>0</X><Y>0</Y><Z>0</Z><W>1</W></SitTargetOrientation><SitTargetPosition><X>0</X><Y>0</Y><Z>0</Z></SitTargetPosition><SitTargetPositionLL><X>0</X><Y>0</Y><Z>0</Z></SitTargetPositionLL><SitTargetOrientationLL><X>0</X><Y>0</Y><Z>0</Z><W>1</W></SitTargetOrientationLL><ParentID>1472706706</ParentID><CreationDate>1471709081</CreationDate><Category>0</Category><SalePrice>10</SalePrice><ObjectSaleType>0</ObjectSaleType><OwnershipCost>0</OwnershipCost><GroupID><UUID>00000000-0000-0000-0000-000000000000</UUID></GroupID><OwnerID><UUID>86f15958-8a66-407d-8d06-6f4a6ec94bab</UUID></OwnerID><LastOwnerID><UUID>86f15958-8a66-407d-8d06-6f4a6ec94bab</UUID></LastOwnerID><RezzerID><UUID>00000000-0000-0000-0000-000000000000</UUID></RezzerID><BaseMask>647168</BaseMask><OwnerMask>647168</OwnerMask><GroupMask>0</GroupMask><EveryoneMask>0</EveryoneMask><NextOwnerMask>532480</NextOwnerMask><Flags>None</Flags><CollisionSound><UUID>00000000-0000-0000-0000-000000000000</UUID></CollisionSound><CollisionSoundVolume>0</CollisionSoundVolume><AttachedPos><X>0</X><Y>0</Y><Z>0</Z></AttachedPos><TextureAnimation /><ParticleSystem /><PayPrice0>-2</PayPrice0><PayPrice1>-2</PayPrice1><PayPrice2>-2</PayPrice2><PayPrice3>-2</PayPrice3><PayPrice4>-2</PayPrice4><Buoyancy>0</Buoyancy><Force><X>0</X><Y>0</Y><Z>0</Z></Force><Torque><X>0</X><Y>0</Y><Z>0</Z></Torque><VolumeDetectActive>false</VolumeDetectActive><PhysicsShapeType>0</PhysicsShapeType><CameraEyeOffset><X>0</X><Y>0</Y><Z>0</Z></CameraEyeOffset><CameraAtOffset><X>0</X><Y>0</Y><Z>0</Z></CameraAtOffset><SoundID><UUID>00000000-0000-0000-0000-000000000000</UUID></SoundID><SoundGain>0</SoundGain><SoundFlags>0</SoundFlags><SoundRadius>0</SoundRadius><SoundQueueing>false</SoundQueueing><CreatorData>http://grid.vibel.eu:8002;Roland Francis</CreatorData></SceneObjectPart></Part><Part><SceneObjectPart xmlns:xsi="http://www.w3.org/2001/XMLSchema-instance" xmlns:xsd="http://www.w3.org/2001/XMLSchema"><AllowedDrop>false</AllowedDrop><CreatorID><UUID>86f15958-8a66-407d-8d06-6f4a6ec94bab</UUID></CreatorID><FolderID><UUID>df0396b0-4d9b-4df9-9fb1-9689099c7146</UUID></FolderID><InventorySerial>0</InventorySerial><UUID><UUID>df0396b0-4d9b-4df9-9fb1-9689099c7146</UUID></UUID><LocalId>1472706718</LocalId><Name>BootStrap1</Name><Material>3</Material><PassTouches>false</PassTouches><PassCollisions>false</PassCollisions><RegionHandle>10985220675669248</RegionHandle><ScriptAccessPin>0</ScriptAccessPin><GroupPosition><X>-0.146437</X><Y>0.003887</Y><Z>0.010049</Z></GroupPosition><OffsetPosition><X>0.07291905</X><Y>-0.002944384</Y><Z>0.05556421</Z></OffsetPosition><RotationOffset><X>-0.003729737</X><Y>-0.0610429</Y><Z>-0.03155571</Z><W>0.9976292</W></RotationOffset><Velocity><X>0</X><Y>0</Y><Z>0</Z></Velocity><AngularVelocity><X>0</X><Y>0</Y><Z>0</Z></AngularVelocity><Acceleration><X>0</X><Y>0</Y><Z>0</Z></Acceleration><Description>(No Description)</Description><Color><R>0</R><G>0</G><B>0</B><A>255</A></Color><Text /><SitName /><TouchName /><LinkNum>13</LinkNum><ClickAction>0</ClickAction><Shape><ProfileCurve>0</ProfileCurve><TextureEntry>YxLLqER/RhKD70PJzWqWAAAAAAAAAAAAgD8AAACAPwAAAAAAAAAAAABAAAAAAAAAAAAAAAAAAAAAAAAAAAAA</TextureEntry><ExtraParams>ATAAEQAAAJI4wWHegUKElSwnM+vmBPgC</ExtraParams><PathBegin>0</PathBegin><PathCurve>32</PathCurve><PathEnd>0</PathEnd><PathRadiusOffset>0</PathRadiusOffset><PathRevolutions>0</PathRevolutions><PathScaleX>100</PathScaleX><PathScaleY>150</PathScaleY><PathShearX>0</PathShearX><PathShearY>0</PathShearY><PathSkew>0</PathSkew><PathTaperX>0</PathTaperX><PathTaperY>0</PathTaperY><PathTwist>0</PathTwist><PathTwistBegin>0</PathTwistBegin><PCode>9</PCode><ProfileBegin>0</ProfileBegin><ProfileEnd>0</ProfileEnd><ProfileHollow>0</ProfileHollow><State>0</State><LastAttachPoint>0</LastAttachPoint><ProfileShape>Circle</ProfileShape><HollowShape>Same</HollowShape><SculptTexture><UUID>9238c161-de81-4284-952c-2733ebe604f8</UUID></SculptTexture><SculptType>2</SculptType><FlexiSoftness>0</FlexiSoftness><FlexiTension>0</FlexiTension><FlexiDrag>0</FlexiDrag><FlexiGravity>0</FlexiGravity><FlexiWind>0</FlexiWind><FlexiForceX>0</FlexiForceX><FlexiForceY>0</FlexiForceY><FlexiForceZ>0</FlexiForceZ><LightColorR>0</LightColorR><LightColorG>0</LightColorG><LightColorB>0</LightColorB><LightColorA>1</LightColorA><LightRadius>0</LightRadius><LightCutoff>0</LightCutoff><LightFalloff>0</LightFalloff><LightIntensity>1</LightIntensity><FlexiEntry>false</FlexiEntry><LightEntry>false</LightEntry><SculptEntry>true</SculptEntry></Shape><Scale><X>0.0714732</X><Y>0.1242697</Y><Z>0.1282669</Z></Scale><SitTargetOrientation><X>0</X><Y>0</Y><Z>0</Z><W>1</W></SitTargetOrientation><SitTargetPosition><X>0</X><Y>0</Y><Z>0</Z></SitTargetPosition><SitTargetPositionLL><X>0</X><Y>0</Y><Z>0</Z></SitTargetPositionLL><SitTargetOrientationLL><X>0</X><Y>0</Y><Z>0</Z><W>1</W></SitTargetOrientationLL><ParentID>1472706706</ParentID><CreationDate>1471709082</CreationDate><Category>0</Category><SalePrice>10</SalePrice><ObjectSaleType>0</ObjectSaleType><OwnershipCost>0</OwnershipCost><GroupID><UUID>00000000-0000-0000-0000-000000000000</UUID></GroupID><OwnerID><UUID>86f15958-8a66-407d-8d06-6f4a6ec94bab</UUID></OwnerID><LastOwnerID><UUID>86f15958-8a66-407d-8d06-6f4a6ec94bab</UUID></LastOwnerID><RezzerID><UUID>00000000-0000-0000-0000-000000000000</UUID></RezzerID><BaseMask>647168</BaseMask><OwnerMask>647168</OwnerMask><GroupMask>0</GroupMask><EveryoneMask>0</EveryoneMask><NextOwnerMask>532480</NextOwnerMask><Flags>None</Flags><CollisionSound><UUID>00000000-0000-0000-0000-000000000000</UUID></CollisionSound><CollisionSoundVolume>0</CollisionSoundVolume><AttachedPos><X>0</X><Y>0</Y><Z>0</Z></AttachedPos><TextureAnimation /><ParticleSystem /><PayPrice0>-2</PayPrice0><PayPrice1>-2</PayPrice1><PayPrice2>-2</PayPrice2><PayPrice3>-2</PayPrice3><PayPrice4>-2</PayPrice4><Buoyancy>0</Buoyancy><Force><X>0</X><Y>0</Y><Z>0</Z></Force><Torque><X>0</X><Y>0</Y><Z>0</Z></Torque><VolumeDetectActive>false</VolumeDetectActive><PhysicsShapeType>0</PhysicsShapeType><CameraEyeOffset><X>0</X><Y>0</Y><Z>0</Z></CameraEyeOffset><CameraAtOffset><X>0</X><Y>0</Y><Z>0</Z></CameraAtOffset><SoundID><UUID>00000000-0000-0000-0000-000000000000</UUID></SoundID><SoundGain>0</SoundGain><SoundFlags>0</SoundFlags><SoundRadius>0</SoundRadius><SoundQueueing>false</SoundQueueing><CreatorData>http://grid.vibel.eu:8002;Roland Francis</CreatorData></SceneObjectPart></Part><Part><SceneObjectPart xmlns:xsi="http://www.w3.org/2001/XMLSchema-instance" xmlns:xsd="http://www.w3.org/2001/XMLSchema"><AllowedDrop>false</AllowedDrop><CreatorID><UUID>86f15958-8a66-407d-8d06-6f4a6ec94bab</UUID></CreatorID><FolderID><UUID>8cc16037-b9f4-4680-b9e1-95b2ca4f0408</UUID></FolderID><InventorySerial>0</InventorySerial><UUID><UUID>8cc16037-b9f4-4680-b9e1-95b2ca4f0408</UUID></UUID><LocalId>1472706719</LocalId><Name>Object</Name><Material>3</Material><PassTouches>false</PassTouches><PassCollisions>false</PassCollisions><RegionHandle>10985220675669248</RegionHandle><ScriptAccessPin>0</ScriptAccessPin><GroupPosition><X>-0.146437</X><Y>0.003887</Y><Z>0.010049</Z></GroupPosition><OffsetPosition><X>0.06770136</X><Y>-0.06160662</Y><Z>0.0728969</Z></OffsetPosition><RotationOffset><X>-0.04247966</X><Y>-0.7600129</Y><Z>-0.6234877</Z><W>0.1784347</W></RotationOffset><Velocity><X>0</X><Y>0</Y><Z>0</Z></Velocity><AngularVelocity><X>0</X><Y>0</Y><Z>0</Z></AngularVelocity><Acceleration><X>0</X><Y>0</Y><Z>0</Z></Acceleration><Description>(No Description)</Description><Color><R>0</R><G>0</G><B>0</B><A>255</A></Color><Text /><SitName /><TouchName /><LinkNum>14</LinkNum><ClickAction>0</ClickAction><Shape><ProfileCurve>0</ProfileCurve><TextureEntry>R0TvbCNrQAWKBDSbgqQvQQAAAAAAAAAAgD8AAACAPwAAAAAAAAAAAADAAAAAAAAAAAAAAAAAAAAAAAAAAAAA</TextureEntry><ExtraParams>ATAAEQAAAFf2i/mkAEH8obaG6MXWP+aC</ExtraParams><PathBegin>0</PathBegin><PathCurve>32</PathCurve><PathEnd>0</PathEnd><PathRadiusOffset>0</PathRadiusOffset><PathRevolutions>0</PathRevolutions><PathScaleX>100</PathScaleX><PathScaleY>150</PathScaleY><PathShearX>0</PathShearX><PathShearY>0</PathShearY><PathSkew>0</PathSkew><PathTaperX>0</PathTaperX><PathTaperY>0</PathTaperY><PathTwist>0</PathTwist><PathTwistBegin>0</PathTwistBegin><PCode>9</PCode><ProfileBegin>0</ProfileBegin><ProfileEnd>0</ProfileEnd><ProfileHollow>0</ProfileHollow><State>0</State><LastAttachPoint>0</LastAttachPoint><ProfileShape>Circle</ProfileShape><HollowShape>Same</HollowShape><SculptTexture><UUID>57f68bf9-a400-41fc-a1b6-86e8c5d63fe6</UUID></SculptTexture><SculptType>130</SculptType><FlexiSoftness>0</FlexiSoftness><FlexiTension>0</FlexiTension><FlexiDrag>0</FlexiDrag><FlexiGravity>0</FlexiGravity><FlexiWind>0</FlexiWind><FlexiForceX>0</FlexiForceX><FlexiForceY>0</FlexiForceY><FlexiForceZ>0</FlexiForceZ><LightColorR>0</LightColorR><LightColorG>0</LightColorG><LightColorB>0</LightColorB><LightColorA>1</LightColorA><LightRadius>0</LightRadius><LightCutoff>0</LightCutoff><LightFalloff>0</LightFalloff><LightIntensity>1</LightIntensity><FlexiEntry>false</FlexiEntry><LightEntry>false</LightEntry><SculptEntry>true</SculptEntry></Shape><Scale><X>0.03424565</X><Y>0.03424565</Y><Z>0.0154159</Z></Scale><SitTargetOrientation><X>0</X><Y>0</Y><Z>0</Z><W>1</W></SitTargetOrientation><SitTargetPosition><X>0</X><Y>0</Y><Z>0</Z></SitTargetPosition><SitTargetPositionLL><X>0</X><Y>0</Y><Z>0</Z></SitTargetPositionLL><SitTargetOrientationLL><X>0</X><Y>0</Y><Z>0</Z><W>1</W></SitTargetOrientationLL><ParentID>1472706706</ParentID><CreationDate>1471709082</CreationDate><Category>0</Category><SalePrice>10</SalePrice><ObjectSaleType>0</ObjectSaleType><OwnershipCost>0</OwnershipCost><GroupID><UUID>00000000-0000-0000-0000-000000000000</UUID></GroupID><OwnerID><UUID>86f15958-8a66-407d-8d06-6f4a6ec94bab</UUID></OwnerID><LastOwnerID><UUID>86f15958-8a66-407d-8d06-6f4a6ec94bab</UUID></LastOwnerID><RezzerID><UUID>00000000-0000-0000-0000-000000000000</UUID></RezzerID><BaseMask>647168</BaseMask><OwnerMask>647168</OwnerMask><GroupMask>0</GroupMask><EveryoneMask>0</EveryoneMask><NextOwnerMask>532480</NextOwnerMask><Flags>None</Flags><CollisionSound><UUID>00000000-0000-0000-0000-000000000000</UUID></CollisionSound><CollisionSoundVolume>0</CollisionSoundVolume><AttachedPos><X>0</X><Y>0</Y><Z>0</Z></AttachedPos><TextureAnimation /><ParticleSystem /><PayPrice0>-2</PayPrice0><PayPrice1>-2</PayPrice1><PayPrice2>-2</PayPrice2><PayPrice3>-2</PayPrice3><PayPrice4>-2</PayPrice4><Buoyancy>0</Buoyancy><Force><X>0</X><Y>0</Y><Z>0</Z></Force><Torque><X>0</X><Y>0</Y><Z>0</Z></Torque><VolumeDetectActive>false</VolumeDetectActive><PhysicsShapeType>0</PhysicsShapeType><CameraEyeOffset><X>0</X><Y>0</Y><Z>0</Z></CameraEyeOffset><CameraAtOffset><X>0</X><Y>0</Y><Z>0</Z></CameraAtOffset><SoundID><UUID>00000000-0000-0000-0000-000000000000</UUID></SoundID><SoundGain>0</SoundGain><SoundFlags>0</SoundFlags><SoundRadius>0</SoundRadius><SoundQueueing>false</SoundQueueing><CreatorData>http://grid.vibel.eu:8002;Roland Francis</CreatorData></SceneObjectPart></Part><Part><SceneObjectPart xmlns:xsi="http://www.w3.org/2001/XMLSchema-instance" xmlns:xsd="http://www.w3.org/2001/XMLSchema"><AllowedDrop>false</AllowedDrop><CreatorID><UUID>86f15958-8a66-407d-8d06-6f4a6ec94bab</UUID></CreatorID><FolderID><UUID>a7de6fed-569f-43a1-a65b-336168517e38</UUID></FolderID><InventorySerial>0</InventorySerial><UUID><UUID>a7de6fed-569f-43a1-a65b-336168517e38</UUID></UUID><LocalId>1472706720</LocalId><Name>Buckle</Name><Material>3</Material><PassTouches>false</PassTouches><PassCollisions>false</PassCollisions><RegionHandle>10985220675669248</RegionHandle><ScriptAccessPin>0</ScriptAccessPin><GroupPosition><X>-0.146437</X><Y>0.003887</Y><Z>0.010049</Z></GroupPosition><OffsetPosition><X>0.07663108</X><Y>-0.05853137</Y><Z>0.09152111</Z></OffsetPosition><RotationOffset><X>-0.7745723</X><Y>0.02400486</Y><Z>0.3440087</Z><W>0.530207</W></RotationOffset><Velocity><X>0</X><Y>0</Y><Z>0</Z></Velocity><AngularVelocity><X>0</X><Y>0</Y><Z>0</Z></AngularVelocity><Acceleration><X>0</X><Y>0</Y><Z>0</Z></Acceleration><Description>(No Description)</Description><Color><R>0</R><G>0</G><B>0</B><A>255</A></Color><Text /><SitName /><TouchName /><LinkNum>15</LinkNum><ClickAction>0</ClickAction><Shape><ProfileCurve>0</ProfileCurve><TextureEntry>R0TvbCNrQAWKBDSbgqQvQQAAAAAAAAAAgD8AAACAPwAAAAAAAAAAAADAAAAAAAAAAAAAAAAAAAAAAAAAAAAA</TextureEntry><ExtraParams>ATAAEQAAANFIj46/4Et+rqZUzufWbuGC</ExtraParams><PathBegin>0</PathBegin><PathCurve>32</PathCurve><PathEnd>0</PathEnd><PathRadiusOffset>0</PathRadiusOffset><PathRevolutions>0</PathRevolutions><PathScaleX>100</PathScaleX><PathScaleY>150</PathScaleY><PathShearX>0</PathShearX><PathShearY>0</PathShearY><PathSkew>0</PathSkew><PathTaperX>0</PathTaperX><PathTaperY>0</PathTaperY><PathTwist>0</PathTwist><PathTwistBegin>0</PathTwistBegin><PCode>9</PCode><ProfileBegin>0</ProfileBegin><ProfileEnd>0</ProfileEnd><ProfileHollow>0</ProfileHollow><State>0</State><LastAttachPoint>0</LastAttachPoint><ProfileShape>Circle</ProfileShape><HollowShape>Same</HollowShape><SculptTexture><UUID>d1488f8e-bfe0-4b7e-aea6-54cee7d66ee1</UUID></SculptTexture><SculptType>130</SculptType><FlexiSoftness>0</FlexiSoftness><FlexiTension>0</FlexiTension><FlexiDrag>0</FlexiDrag><FlexiGravity>0</FlexiGravity><FlexiWind>0</FlexiWind><FlexiForceX>0</FlexiForceX><FlexiForceY>0</FlexiForceY><FlexiForceZ>0</FlexiForceZ><LightColorR>0</LightColorR><LightColorG>0</LightColorG><LightColorB>0</LightColorB><LightColorA>1</LightColorA><LightRadius>0</LightRadius><LightCutoff>0</LightCutoff><LightFalloff>0</LightFalloff><LightIntensity>1</LightIntensity><FlexiEntry>false</FlexiEntry><LightEntry>false</LightEntry><SculptEntry>true</SculptEntry></Shape><Scale><X>0.03352187</X><Y>0.03747713</Y><Z>0.0351097</Z></Scale><SitTargetOrientation><X>0</X><Y>0</Y><Z>0</Z><W>1</W></SitTargetOrientation><SitTargetPosition><X>0</X><Y>0</Y><Z>0</Z></SitTargetPosition><SitTargetPositionLL><X>0</X><Y>0</Y><Z>0</Z></SitTargetPositionLL><SitTargetOrientationLL><X>0</X><Y>0</Y><Z>0</Z><W>1</W></SitTargetOrientationLL><ParentID>1472706706</ParentID><CreationDate>1471709082</CreationDate><Category>0</Category><SalePrice>10</SalePrice><ObjectSaleType>0</ObjectSaleType><OwnershipCost>0</OwnershipCost><GroupID><UUID>00000000-0000-0000-0000-000000000000</UUID></GroupID><OwnerID><UUID>86f15958-8a66-407d-8d06-6f4a6ec94bab</UUID></OwnerID><LastOwnerID><UUID>86f15958-8a66-407d-8d06-6f4a6ec94bab</UUID></LastOwnerID><RezzerID><UUID>00000000-0000-0000-0000-000000000000</UUID></RezzerID><BaseMask>647168</BaseMask><OwnerMask>647168</OwnerMask><GroupMask>0</GroupMask><EveryoneMask>0</EveryoneMask><NextOwnerMask>532480</NextOwnerMask><Flags>None</Flags><CollisionSound><UUID>00000000-0000-0000-0000-000000000000</UUID></CollisionSound><CollisionSoundVolume>0</CollisionSoundVolume><AttachedPos><X>0</X><Y>0</Y><Z>0</Z></AttachedPos><TextureAnimation /><ParticleSystem /><PayPrice0>-2</PayPrice0><PayPrice1>-2</PayPrice1><PayPrice2>-2</PayPrice2><PayPrice3>-2</PayPrice3><PayPrice4>-2</PayPrice4><Buoyancy>0</Buoyancy><Force><X>0</X><Y>0</Y><Z>0</Z></Force><Torque><X>0</X><Y>0</Y><Z>0</Z></Torque><VolumeDetectActive>false</VolumeDetectActive><PhysicsShapeType>0</PhysicsShapeType><CameraEyeOffset><X>0</X><Y>0</Y><Z>0</Z></CameraEyeOffset><CameraAtOffset><X>0</X><Y>0</Y><Z>0</Z></CameraAtOffset><SoundID><UUID>00000000-0000-0000-0000-000000000000</UUID></SoundID><SoundGain>0</SoundGain><SoundFlags>0</SoundFlags><SoundRadius>0</SoundRadius><SoundQueueing>false</SoundQueueing><CreatorData>http://grid.vibel.eu:8002;Roland Francis</CreatorData></SceneObjectPart></Part><Part><SceneObjectPart xmlns:xsi="http://www.w3.org/2001/XMLSchema-instance" xmlns:xsd="http://www.w3.org/2001/XMLSchema"><AllowedDrop>false</AllowedDrop><CreatorID><UUID>86f15958-8a66-407d-8d06-6f4a6ec94bab</UUID></CreatorID><FolderID><UUID>db7eeb48-7ef8-4e5e-98bf-731b405dea6c</UUID></FolderID><InventorySerial>0</InventorySerial><UUID><UUID>db7eeb48-7ef8-4e5e-98bf-731b405dea6c</UUID></UUID><LocalId>1472706721</LocalId><Name>BuckleLatch</Name><Material>3</Material><PassTouches>false</PassTouches><PassCollisions>false</PassCollisions><RegionHandle>10985220675669248</RegionHandle><ScriptAccessPin>0</ScriptAccessPin><GroupPosition><X>-0.146437</X><Y>0.003887</Y><Z>0.010049</Z></GroupPosition><OffsetPosition><X>0.07666761</X><Y>-0.05748779</Y><Z>0.09249693</Z></OffsetPosition><RotationOffset><X>-0.7818428</X><Y>-0.004046992</Y><Z>0.3742085</Z><W>0.4986718</W></RotationOffset><Velocity><X>0</X><Y>0</Y><Z>0</Z></Velocity><AngularVelocity><X>0</X><Y>0</Y><Z>0</Z></AngularVelocity><Acceleration><X>0</X><Y>0</Y><Z>0</Z></Acceleration><Description>(No Description)</Description><Color><R>0</R><G>0</G><B>0</B><A>255</A></Color><Text /><SitName /><TouchName /><LinkNum>16</LinkNum><ClickAction>0</ClickAction><Shape><ProfileCurve>0</ProfileCurve><TextureEntry>R0TvbCNrQAWKBDSbgqQvQQAAAAAAAAAAgD8AAACAPwAAAAAAAAAAAADAAAAAAAAAAAAAAAAAAAAAAAAAAAAA</TextureEntry><ExtraParams>ATAAEQAAAKl64WYsDEa2oOsa27quDjSB</ExtraParams><PathBegin>0</PathBegin><PathCurve>32</PathCurve><PathEnd>0</PathEnd><PathRadiusOffset>0</PathRadiusOffset><PathRevolutions>0</PathRevolutions><PathScaleX>100</PathScaleX><PathScaleY>150</PathScaleY><PathShearX>0</PathShearX><PathShearY>0</PathShearY><PathSkew>0</PathSkew><PathTaperX>0</PathTaperX><PathTaperY>0</PathTaperY><PathTwist>0</PathTwist><PathTwistBegin>0</PathTwistBegin><PCode>9</PCode><ProfileBegin>0</ProfileBegin><ProfileEnd>0</ProfileEnd><ProfileHollow>0</ProfileHollow><State>0</State><LastAttachPoint>0</LastAttachPoint><ProfileShape>Circle</ProfileShape><HollowShape>Same</HollowShape><SculptTexture><UUID>a97ae166-2c0c-46b6-a0eb-1adbbaae0e34</UUID></SculptTexture><SculptType>129</SculptType><FlexiSoftness>0</FlexiSoftness><FlexiTension>0</FlexiTension><FlexiDrag>0</FlexiDrag><FlexiGravity>0</FlexiGravity><FlexiWind>0</FlexiWind><FlexiForceX>0</FlexiForceX><FlexiForceY>0</FlexiForceY><FlexiForceZ>0</FlexiForceZ><LightColorR>0</LightColorR><LightColorG>0</LightColorG><LightColorB>0</LightColorB><LightColorA>1</LightColorA><LightRadius>0</LightRadius><LightCutoff>0</LightCutoff><LightFalloff>0</LightFalloff><LightIntensity>1</LightIntensity><FlexiEntry>false</FlexiEntry><LightEntry>false</LightEntry><SculptEntry>true</SculptEntry></Shape><Scale><X>0.01825087</X><Y>0.02974539</Y><Z>0.02591916</Z></Scale><SitTargetOrientation><X>0</X><Y>0</Y><Z>0</Z><W>1</W></SitTargetOrientation><SitTargetPosition><X>0</X><Y>0</Y><Z>0</Z></SitTargetPosition><SitTargetPositionLL><X>0</X><Y>0</Y><Z>0</Z></SitTargetPositionLL><SitTargetOrientationLL><X>0</X><Y>0</Y><Z>0</Z><W>1</W></SitTargetOrientationLL><ParentID>1472706706</ParentID><CreationDate>1471709082</CreationDate><Category>0</Category><SalePrice>10</SalePrice><ObjectSaleType>0</ObjectSaleType><OwnershipCost>0</OwnershipCost><GroupID><UUID>00000000-0000-0000-0000-000000000000</UUID></GroupID><OwnerID><UUID>86f15958-8a66-407d-8d06-6f4a6ec94bab</UUID></OwnerID><LastOwnerID><UUID>86f15958-8a66-407d-8d06-6f4a6ec94bab</UUID></LastOwnerID><RezzerID><UUID>00000000-0000-0000-0000-000000000000</UUID></RezzerID><BaseMask>647168</BaseMask><OwnerMask>647168</OwnerMask><GroupMask>0</GroupMask><EveryoneMask>0</EveryoneMask><NextOwnerMask>532480</NextOwnerMask><Flags>None</Flags><CollisionSound><UUID>00000000-0000-0000-0000-000000000000</UUID></CollisionSound><CollisionSoundVolume>0</CollisionSoundVolume><AttachedPos><X>0</X><Y>0</Y><Z>0</Z></AttachedPos><TextureAnimation /><ParticleSystem /><PayPrice0>-2</PayPrice0><PayPrice1>-2</PayPrice1><PayPrice2>-2</PayPrice2><PayPrice3>-2</PayPrice3><PayPrice4>-2</PayPrice4><Buoyancy>0</Buoyancy><Force><X>0</X><Y>0</Y><Z>0</Z></Force><Torque><X>0</X><Y>0</Y><Z>0</Z></Torque><VolumeDetectActive>false</VolumeDetectActive><PhysicsShapeType>0</PhysicsShapeType><CameraEyeOffset><X>0</X><Y>0</Y><Z>0</Z></CameraEyeOffset><CameraAtOffset><X>0</X><Y>0</Y><Z>0</Z></CameraAtOffset><SoundID><UUID>00000000-0000-0000-0000-000000000000</UUID></SoundID><SoundGain>0</SoundGain><SoundFlags>0</SoundFlags><SoundRadius>0</SoundRadius><SoundQueueing>false</SoundQueueing><CreatorData>http://grid.vibel.eu:8002;Roland Francis</CreatorData></SceneObjectPart></Part><Part><SceneObjectPart xmlns:xsi="http://www.w3.org/2001/XMLSchema-instance" xmlns:xsd="http://www.w3.org/2001/XMLSchema"><AllowedDrop>false</AllowedDrop><CreatorID><UUID>86f15958-8a66-407d-8d06-6f4a6ec94bab</UUID></CreatorID><FolderID><UUID>565d9242-88ad-426c-bd69-da52cd7ad691</UUID></FolderID><InventorySerial>0</InventorySerial><UUID><UUID>565d9242-88ad-426c-bd69-da52cd7ad691</UUID></UUID><LocalId>1472706722</LocalId><Name>Object</Name><Material>3</Material><PassTouches>false</PassTouches><PassCollisions>false</PassCollisions><RegionHandle>10985220675669248</RegionHandle><ScriptAccessPin>0</ScriptAccessPin><GroupPosition><X>-0.146437</X><Y>0.003887</Y><Z>0.010049</Z></GroupPosition><OffsetPosition><X>0.02692395</X><Y>-0.06590883</Y><Z>0.1022674</Z></OffsetPosition><RotationOffset><X>0.6474649</X><Y>-0.2452895</Y><Z>0.3229851</Z><W>0.6452153</W></RotationOffset><Velocity><X>0</X><Y>0</Y><Z>0</Z></Velocity><AngularVelocity><X>0</X><Y>0</Y><Z>0</Z></AngularVelocity><Acceleration><X>0</X><Y>0</Y><Z>0</Z></Acceleration><Description>(No Description)</Description><Color><R>0</R><G>0</G><B>0</B><A>255</A></Color><Text /><SitName /><TouchName /><LinkNum>17</LinkNum><ClickAction>0</ClickAction><Shape><ProfileCurve>0</ProfileCurve><TextureEntry>R0TvbCNrQAWKBDSbgqQvQQAAAAAAAAAAgD8AAACAPwAAAAAAAAAAAADAAAAAAAAAAAAAAAAAAAAAAAAAAAAA</TextureEntry><ExtraParams>ATAAEQAAAFf2i/mkAEH8obaG6MXWP+aC</ExtraParams><PathBegin>0</PathBegin><PathCurve>32</PathCurve><PathEnd>0</PathEnd><PathRadiusOffset>0</PathRadiusOffset><PathRevolutions>0</PathRevolutions><PathScaleX>100</PathScaleX><PathScaleY>150</PathScaleY><PathShearX>0</PathShearX><PathShearY>0</PathShearY><PathSkew>0</PathSkew><PathTaperX>0</PathTaperX><PathTaperY>0</PathTaperY><PathTwist>0</PathTwist><PathTwistBegin>0</PathTwistBegin><PCode>9</PCode><ProfileBegin>0</ProfileBegin><ProfileEnd>0</ProfileEnd><ProfileHollow>0</ProfileHollow><State>0</State><LastAttachPoint>0</LastAttachPoint><ProfileShape>Circle</ProfileShape><HollowShape>Same</HollowShape><SculptTexture><UUID>57f68bf9-a400-41fc-a1b6-86e8c5d63fe6</UUID></SculptTexture><SculptType>130</SculptType><FlexiSoftness>0</FlexiSoftness><FlexiTension>0</FlexiTension><FlexiDrag>0</FlexiDrag><FlexiGravity>0</FlexiGravity><FlexiWind>0</FlexiWind><FlexiForceX>0</FlexiForceX><FlexiForceY>0</FlexiForceY><FlexiForceZ>0</FlexiForceZ><LightColorR>0</LightColorR><LightColorG>0</LightColorG><LightColorB>0</LightColorB><LightColorA>1</LightColorA><LightRadius>0</LightRadius><LightCutoff>0</LightCutoff><LightFalloff>0</LightFalloff><LightIntensity>1</LightIntensity><FlexiEntry>false</FlexiEntry><LightEntry>false</LightEntry><SculptEntry>true</SculptEntry></Shape><Scale><X>0.03424565</X><Y>0.03424565</Y><Z>0.0154159</Z></Scale><SitTargetOrientation><X>0</X><Y>0</Y><Z>0</Z><W>1</W></SitTargetOrientation><SitTargetPosition><X>0</X><Y>0</Y><Z>0</Z></SitTargetPosition><SitTargetPositionLL><X>0</X><Y>0</Y><Z>0</Z></SitTargetPositionLL><SitTargetOrientationLL><X>0</X><Y>0</Y><Z>0</Z><W>1</W></SitTargetOrientationLL><ParentID>1472706706</ParentID><CreationDate>1471709082</CreationDate><Category>0</Category><SalePrice>10</SalePrice><ObjectSaleType>0</ObjectSaleType><OwnershipCost>0</OwnershipCost><GroupID><UUID>00000000-0000-0000-0000-000000000000</UUID></GroupID><OwnerID><UUID>86f15958-8a66-407d-8d06-6f4a6ec94bab</UUID></OwnerID><LastOwnerID><UUID>86f15958-8a66-407d-8d06-6f4a6ec94bab</UUID></LastOwnerID><RezzerID><UUID>00000000-0000-0000-0000-000000000000</UUID></RezzerID><BaseMask>647168</BaseMask><OwnerMask>647168</OwnerMask><GroupMask>0</GroupMask><EveryoneMask>0</EveryoneMask><NextOwnerMask>532480</NextOwnerMask><Flags>None</Flags><CollisionSound><UUID>00000000-0000-0000-0000-000000000000</UUID></CollisionSound><CollisionSoundVolume>0</CollisionSoundVolume><AttachedPos><X>0</X><Y>0</Y><Z>0</Z></AttachedPos><TextureAnimation /><ParticleSystem /><PayPrice0>-2</PayPrice0><PayPrice1>-2</PayPrice1><PayPrice2>-2</PayPrice2><PayPrice3>-2</PayPrice3><PayPrice4>-2</PayPrice4><Buoyancy>0</Buoyancy><Force><X>0</X><Y>0</Y><Z>0</Z></Force><Torque><X>0</X><Y>0</Y><Z>0</Z></Torque><VolumeDetectActive>false</VolumeDetectActive><PhysicsShapeType>0</PhysicsShapeType><CameraEyeOffset><X>0</X><Y>0</Y><Z>0</Z></CameraEyeOffset><CameraAtOffset><X>0</X><Y>0</Y><Z>0</Z></CameraAtOffset><SoundID><UUID>00000000-0000-0000-0000-000000000000</UUID></SoundID><SoundGain>0</SoundGain><SoundFlags>0</SoundFlags><SoundRadius>0</SoundRadius><SoundQueueing>false</SoundQueueing><CreatorData>http://grid.vibel.eu:8002;Roland Francis</CreatorData></SceneObjectPart></Part></OtherParts></SceneObjectGroup> 