<SceneObjectGroup><RootPart><SceneObjectPart xmlns:xsi="http://www.w3.org/2001/XMLSchema-instance" xmlns:xsd="http://www.w3.org/2001/XMLSchema"><AllowedDrop>false</AllowedDrop><CreatorID><UUID>9d7419d1-276d-4cae-a281-ca399be0db02</UUID></CreatorID><CreatorData>http://hypergrid.org:8002;Dorothea Lundquist</CreatorData><FolderID><UUID>627c6ec6-3f58-4e62-ac37-0c86e1d88efb</UUID></FolderID><InventorySerial>6</InventorySerial><UUID><UUID>627c6ec6-3f58-4e62-ac37-0c86e1d88efb</UUID></UUID><LocalId>2472056875</LocalId><Name>D&amp;J earring Gold L2</Name><Material>3</Material><PassTouches>false</PassTouches><PassCollisions>false</PassCollisions><RegionHandle>7689984326456320</RegionHandle><ScriptAccessPin>0</ScriptAccessPin><GroupPosition><X>0.009746789</X><Y>0.003503702</Y><Z>-0.01127572</Z></GroupPosition><OffsetPosition><X>0</X><Y>0</Y><Z>0</Z></OffsetPosition><RotationOffset><X>0.5000002</X><Y>-0.5000002</Y><Z>-0.5</Z><W>0.4999995</W></RotationOffset><Velocity><X>0</X><Y>0</Y><Z>0</Z></Velocity><AngularVelocity><X>0</X><Y>0</Y><Z>0</Z></AngularVelocity><Acceleration><X>0</X><Y>0</Y><Z>0</Z></Acceleration><Description /><Color><R>0</R><G>0</G><B>0</B><A>255</A></Color><Text /><SitName /><TouchName /><LinkNum>1</LinkNum><ClickAction>0</ClickAction><Shape><ProfileCurve>0</ProfileCurve><TextureEntry>yVH5tnixSJmzikpqcVQ5nQGnw5inNBRNoJVDdoyOrUijAo2W+NpTakO4mLt/IfwTOR0AAAAAAAAAAIA/AZqZGT8AAACAPwGamRk/ApqZnUEAAAAAAAAAAAAAIAAAAAgAAAAAAAAAAAAAAAAAAAAAAA==</TextureEntry><ExtraParams>AA==</ExtraParams><PathBegin>0</PathBegin><PathCurve>32</PathCurve><PathEnd>0</PathEnd><PathRadiusOffset>-94</PathRadiusOffset><PathRevolutions>200</PathRevolutions><PathScaleX>100</PathScaleX><PathScaleY>194</PathScaleY><PathShearX>0</PathShearX><PathShearY>0</PathShearY><PathSkew>80</PathSkew><PathTaperX>0</PathTaperX><PathTaperY>0</PathTaperY><PathTwist>0</PathTwist><PathTwistBegin>0</PathTwistBegin><PCode>9</PCode><ProfileBegin>0</ProfileBegin><ProfileEnd>0</ProfileEnd><ProfileHollow>0</ProfileHollow><State>13</State><LastAttachPoint>14</LastAttachPoint><ProfileShape>Circle</ProfileShape><HollowShape>Same</HollowShape><SculptTexture><UUID>00000000-0000-0000-0000-000000000000</UUID></SculptTexture><SculptType>0</SculptType><FlexiSoftness>0</FlexiSoftness><FlexiTension>0</FlexiTension><FlexiDrag>0</FlexiDrag><FlexiGravity>0</FlexiGravity><FlexiWind>0</FlexiWind><FlexiForceX>0</FlexiForceX><FlexiForceY>0</FlexiForceY><FlexiForceZ>0</FlexiForceZ><LightColorR>0</LightColorR><LightColorG>0</LightColorG><LightColorB>0</LightColorB><LightColorA>1</LightColorA><LightRadius>0</LightRadius><LightCutoff>0</LightCutoff><LightFalloff>0</LightFalloff><LightIntensity>1</LightIntensity><FlexiEntry>false</FlexiEntry><LightEntry>false</LightEntry><SculptEntry>false</SculptEntry></Shape><Scale><X>0.01012806</X><Y>0.04234013</Y><Z>0.04109872</Z></Scale><SitTargetOrientation><X>0</X><Y>0</Y><Z>0</Z><W>1</W></SitTargetOrientation><SitTargetPosition><X>0</X><Y>0</Y><Z>0</Z></SitTargetPosition><SitTargetPositionLL><X>0</X><Y>0</Y><Z>0</Z></SitTargetPositionLL><SitTargetOrientationLL><X>0</X><Y>0</Y><Z>0</Z><W>1</W></SitTargetOrientationLL><ParentID>0</ParentID><CreationDate>1347365987</CreationDate><Category>0</Category><SalePrice>0</SalePrice><ObjectSaleType>0</ObjectSaleType><OwnershipCost>0</OwnershipCost><GroupID><UUID>00000000-0000-0000-0000-000000000000</UUID></GroupID><OwnerID><UUID>b3560a21-af33-4a85-9723-5ee97fe8cdab</UUID></OwnerID><LastOwnerID><UUID>b3560a21-af33-4a85-9723-5ee97fe8cdab</UUID></LastOwnerID><BaseMask>647168</BaseMask><OwnerMask>647168</OwnerMask><GroupMask>0</GroupMask><EveryoneMask>557056</EveryoneMask><NextOwnerMask>581632</NextOwnerMask><Flags>Phantom</Flags><CollisionSound><UUID>00000000-0000-0000-0000-000000000000</UUID></CollisionSound><CollisionSoundVolume>0</CollisionSoundVolume><AttachedPos><X>0.009746789</X><Y>0.003503702</Y><Z>-0.01127572</Z></AttachedPos><TextureAnimation></TextureAnimation><ParticleSystem></ParticleSystem><PayPrice0>-2</PayPrice0><PayPrice1>-2</PayPrice1><PayPrice2>-2</PayPrice2><PayPrice3>-2</PayPrice3><PayPrice4>-2</PayPrice4></SceneObjectPart></RootPart><OtherParts><Part><SceneObjectPart xmlns:xsi="http://www.w3.org/2001/XMLSchema-instance" xmlns:xsd="http://www.w3.org/2001/XMLSchema"><AllowedDrop>false</AllowedDrop><CreatorID><UUID>9d7419d1-276d-4cae-a281-ca399be0db02</UUID></CreatorID><CreatorData>http://hypergrid.org:8002;Dorothea Lundquist</CreatorData><FolderID><UUID>eb01d008-2673-43fc-90fe-03d80e315d9a</UUID></FolderID><InventorySerial>5</InventorySerial><UUID><UUID>eb01d008-2673-43fc-90fe-03d80e315d9a</UUID></UUID><LocalId>2472056876</LocalId><Name>Primitive</Name><Material>3</Material><PassTouches>false</PassTouches><PassCollisions>false</PassCollisions><RegionHandle>7689984326456320</RegionHandle><ScriptAccessPin>0</ScriptAccessPin><GroupPosition><X>0.009746789</X><Y>0.003503702</Y><Z>-0.01127572</Z></GroupPosition><OffsetPosition><X>0.002975468</X><Y>-0.02807617</Y><Z>0.001754763</Z></OffsetPosition><RotationOffset><X>0.000311354</X><Y>0.7070403</Y><Z>-0.0003113192</Z><W>-0.7071731</W></RotationOffset><Velocity><X>0</X><Y>0</Y><Z>0</Z></Velocity><AngularVelocity><X>0</X><Y>0</Y><Z>0</Z></AngularVelocity><Acceleration><X>0</X><Y>0</Y><Z>0</Z></Acceleration><Description /><Color><R>0</R><G>0</G><B>0</B><A>255</A></Color><Text /><SitName /><TouchName /><LinkNum>2</LinkNum><ClickAction>0</ClickAction><Shape><ProfileCurve>0</ProfileCurve><TextureEntry>yVH5tnixSJmzikpqcVQ5nQGnw5inNBRNoJVDdoyOrUijAo2W+NpTakO4mLt/IfwTOR0AAAAAAAAAAIA/AZqZGT8AAACAPwGamRk/ApqZnUEAAAAAAAAAAAAAIAAAAAgAAAAAAAAAAAAAAAAAAAAAAA==</TextureEntry><ExtraParams>AA==</ExtraParams><PathBegin>0</PathBegin><PathCurve>32</PathCurve><PathEnd>0</PathEnd><PathRadiusOffset>94</PathRadiusOffset><PathRevolutions>200</PathRevolutions><PathScaleX>100</PathScaleX><PathScaleY>194</PathScaleY><PathShearX>0</PathShearX><PathShearY>0</PathShearY><PathSkew>80</PathSkew><PathTaperX>0</PathTaperX><PathTaperY>0</PathTaperY><PathTwist>0</PathTwist><PathTwistBegin>0</PathTwistBegin><PCode>9</PCode><ProfileBegin>0</ProfileBegin><ProfileEnd>0</ProfileEnd><ProfileHollow>0</ProfileHollow><State>0</State><LastAttachPoint>0</LastAttachPoint><ProfileShape>Circle</ProfileShape><HollowShape>Same</HollowShape><SculptTexture><UUID>00000000-0000-0000-0000-000000000000</UUID></SculptTexture><SculptType>0</SculptType><FlexiSoftness>0</FlexiSoftness><FlexiTension>0</FlexiTension><FlexiDrag>0</FlexiDrag><FlexiGravity>0</FlexiGravity><FlexiWind>0</FlexiWind><FlexiForceX>0</FlexiForceX><FlexiForceY>0</FlexiForceY><FlexiForceZ>0</FlexiForceZ><LightColorR>0</LightColorR><LightColorG>0</LightColorG><LightColorB>0</LightColorB><LightColorA>1</LightColorA><LightRadius>0</LightRadius><LightCutoff>0</LightCutoff><LightFalloff>0</LightFalloff><LightIntensity>1</LightIntensity><FlexiEntry>false</FlexiEntry><LightEntry>false</LightEntry><SculptEntry>false</SculptEntry></Shape><Scale><X>0.006861412</X><Y>0.02709861</Y><Z>0.02709861</Z></Scale><SitTargetOrientation><X>0</X><Y>0</Y><Z>0</Z><W>1</W></SitTargetOrientation><SitTargetPosition><X>0</X><Y>0</Y><Z>0</Z></SitTargetPosition><SitTargetPositionLL><X>0</X><Y>0</Y><Z>0</Z></SitTargetPositionLL><SitTargetOrientationLL><X>0</X><Y>0</Y><Z>0</Z><W>1</W></SitTargetOrientationLL><ParentID>2472056875</ParentID><CreationDate>1347365987</CreationDate><Category>0</Category><SalePrice>10</SalePrice><ObjectSaleType>0</ObjectSaleType><OwnershipCost>0</OwnershipCost><GroupID><UUID>00000000-0000-0000-0000-000000000000</UUID></GroupID><OwnerID><UUID>b3560a21-af33-4a85-9723-5ee97fe8cdab</UUID></OwnerID><LastOwnerID><UUID>b3560a21-af33-4a85-9723-5ee97fe8cdab</UUID></LastOwnerID><BaseMask>647168</BaseMask><OwnerMask>647168</OwnerMask><GroupMask>0</GroupMask><EveryoneMask>557056</EveryoneMask><NextOwnerMask>581632</NextOwnerMask><Flags>Phantom</Flags><CollisionSound><UUID>00000000-0000-0000-0000-000000000000</UUID></CollisionSound><CollisionSoundVolume>0</CollisionSoundVolume><AttachedPos><X>0</X><Y>0</Y><Z>0</Z></AttachedPos><TextureAnimation></TextureAnimation><ParticleSystem></ParticleSystem><PayPrice0>-2</PayPrice0><PayPrice1>-2</PayPrice1><PayPrice2>-2</PayPrice2><PayPrice3>-2</PayPrice3><PayPrice4>-2</PayPrice4></SceneObjectPart></Part><Part><SceneObjectPart xmlns:xsi="http://www.w3.org/2001/XMLSchema-instance" xmlns:xsd="http://www.w3.org/2001/XMLSchema"><AllowedDrop>false</AllowedDrop><CreatorID><UUID>39508062-8358-4da5-88e9-5ce43992c071</UUID></CreatorID><CreatorData>http://users.osgrid.org/39508062-8358-4da5-88e9-5ce43992c071/;Dorothea Lundquist</CreatorData><FolderID><UUID>c6e4391a-ec63-4733-b9b3-aeb4cd82a697</UUID></FolderID><InventorySerial>5</InventorySerial><UUID><UUID>c6e4391a-ec63-4733-b9b3-aeb4cd82a697</UUID></UUID><LocalId>2472056877</LocalId><Name>D&amp;J Brocat Dress flex</Name><Material>3</Material><PassTouches>false</PassTouches><PassCollisions>false</PassCollisions><RegionHandle>7689984326456320</RegionHandle><ScriptAccessPin>0</ScriptAccessPin><GroupPosition><X>0.009746789</X><Y>0.003503702</Y><Z>-0.01127572</Z></GroupPosition><OffsetPosition><X>0.01271058</X><Y>-0.05114746</Y><Z>-0.000549313</Z></OffsetPosition><RotationOffset><X>-0.5239314</X><Y>-0.474864</Y><Z>0.474864</Z><W>-0.5239316</W></RotationOffset><Velocity><X>0</X><Y>0</Y><Z>0</Z></Velocity><AngularVelocity><X>0</X><Y>0</Y><Z>0</Z></AngularVelocity><Acceleration><X>0</X><Y>0</Y><Z>0</Z></Acceleration><Description /><Color><R>0</R><G>0</G><B>0</B><A>255</A></Color><Text /><SitName /><TouchName /><LinkNum>3</LinkNum><ClickAction>0</ClickAction><Shape><ProfileCurve>0</ProfileCurve><TextureEntry>ddYCyNJCQQCQCsFGDPT8jAAAAAAAAQAAAP8AAACAPwAAAEBAAAAAAAAAAA3AACAAAAAIAAAAAAAAAAAAAAAAAAAAAAA=</TextureEntry><ExtraParams>ARAAEAAAAIqUZwAAAAAAAAAAAAAAAAA=</ExtraParams><PathBegin>0</PathBegin><PathCurve>128</PathCurve><PathEnd>0</PathEnd><PathRadiusOffset>0</PathRadiusOffset><PathRevolutions>0</PathRevolutions><PathScaleX>15</PathScaleX><PathScaleY>30</PathScaleY><PathShearX>0</PathShearX><PathShearY>0</PathShearY><PathSkew>0</PathSkew><PathTaperX>0</PathTaperX><PathTaperY>0</PathTaperY><PathTwist>0</PathTwist><PathTwistBegin>0</PathTwistBegin><PCode>9</PCode><ProfileBegin>0</ProfileBegin><ProfileEnd>0</ProfileEnd><ProfileHollow>47450</ProfileHollow><State>0</State><LastAttachPoint>0</LastAttachPoint><ProfileShape>Circle</ProfileShape><HollowShape>Same</HollowShape><SculptTexture><UUID>00000000-0000-0000-0000-000000000000</UUID></SculptTexture><SculptType>0</SculptType><FlexiSoftness>3</FlexiSoftness><FlexiTension>1</FlexiTension><FlexiDrag>2</FlexiDrag><FlexiGravity>0.3000002</FlexiGravity><FlexiWind>0</FlexiWind><FlexiForceX>0</FlexiForceX><FlexiForceY>0</FlexiForceY><FlexiForceZ>0</FlexiForceZ><LightColorR>0</LightColorR><LightColorG>0</LightColorG><LightColorB>0</LightColorB><LightColorA>1</LightColorA><LightRadius>0</LightRadius><LightCutoff>0</LightCutoff><LightFalloff>0</LightFalloff><LightIntensity>1</LightIntensity><FlexiEntry>true</FlexiEntry><LightEntry>false</LightEntry><SculptEntry>false</SculptEntry></Shape><Scale><X>0.003885937</X><Y>0.003518508</Y><Z>0.03758142</Z></Scale><SitTargetOrientation><X>0</X><Y>0</Y><Z>0</Z><W>1</W></SitTargetOrientation><SitTargetPosition><X>0</X><Y>0</Y><Z>0</Z></SitTargetPosition><SitTargetPositionLL><X>0</X><Y>0</Y><Z>0</Z></SitTargetPositionLL><SitTargetOrientationLL><X>0</X><Y>0</Y><Z>0</Z><W>1</W></SitTargetOrientationLL><ParentID>2472056875</ParentID><CreationDate>1267166485</CreationDate><Category>0</Category><SalePrice>10</SalePrice><ObjectSaleType>0</ObjectSaleType><OwnershipCost>0</OwnershipCost><GroupID><UUID>00000000-0000-0000-0000-000000000000</UUID></GroupID><OwnerID><UUID>b3560a21-af33-4a85-9723-5ee97fe8cdab</UUID></OwnerID><LastOwnerID><UUID>b3560a21-af33-4a85-9723-5ee97fe8cdab</UUID></LastOwnerID><BaseMask>647168</BaseMask><OwnerMask>647168</OwnerMask><GroupMask>0</GroupMask><EveryoneMask>557056</EveryoneMask><NextOwnerMask>581632</NextOwnerMask><Flags>Phantom</Flags><CollisionSound><UUID>00000000-0000-0000-0000-000000000000</UUID></CollisionSound><CollisionSoundVolume>0</CollisionSoundVolume><AttachedPos><X>0</X><Y>0</Y><Z>0</Z></AttachedPos><TextureAnimation></TextureAnimation><ParticleSystem></ParticleSystem><PayPrice0>-2</PayPrice0><PayPrice1>-2</PayPrice1><PayPrice2>-2</PayPrice2><PayPrice3>-2</PayPrice3><PayPrice4>-2</PayPrice4></SceneObjectPart></Part><Part><SceneObjectPart xmlns:xsi="http://www.w3.org/2001/XMLSchema-instance" xmlns:xsd="http://www.w3.org/2001/XMLSchema"><AllowedDrop>false</AllowedDrop><CreatorID><UUID>39508062-8358-4da5-88e9-5ce43992c071</UUID></CreatorID><CreatorData>http://users.osgrid.org/39508062-8358-4da5-88e9-5ce43992c071/;Dorothea Lundquist</CreatorData><FolderID><UUID>63f05255-dc1b-4b3c-959f-84a64acc8f0f</UUID></FolderID><InventorySerial>5</InventorySerial><UUID><UUID>63f05255-dc1b-4b3c-959f-84a64acc8f0f</UUID></UUID><LocalId>2472056878</LocalId><Name>D&amp;J Brocat Dress flex</Name><Material>3</Material><PassTouches>false</PassTouches><PassCollisions>false</PassCollisions><RegionHandle>7689984326456320</RegionHandle><ScriptAccessPin>0</ScriptAccessPin><GroupPosition><X>0.009746789</X><Y>0.003503702</Y><Z>-0.01127572</Z></GroupPosition><OffsetPosition><X>0.009635933</X><Y>-0.05535889</Y><Z>-0.0005493115</Z></OffsetPosition><RotationOffset><X>-0.5239314</X><Y>-0.474864</Y><Z>0.474864</Z><W>-0.5239316</W></RotationOffset><Velocity><X>0</X><Y>0</Y><Z>0</Z></Velocity><AngularVelocity><X>0</X><Y>0</Y><Z>0</Z></AngularVelocity><Acceleration><X>0</X><Y>0</Y><Z>0</Z></Acceleration><Description /><Color><R>0</R><G>0</G><B>0</B><A>255</A></Color><Text /><SitName /><TouchName /><LinkNum>4</LinkNum><ClickAction>0</ClickAction><Shape><ProfileCurve>0</ProfileCurve><TextureEntry>ddYCyNJCQQCQCsFGDPT8jAAAAAAAAQAAAP8AAACAPwAAAEBAAAAAAAAAAA3AACAAAAAIAAAAAAAAAAAAAAAAAAAAAAA=</TextureEntry><ExtraParams>ARAAEAAAAIqUZwAAAAAAAAAAAAAAAAA=</ExtraParams><PathBegin>0</PathBegin><PathCurve>128</PathCurve><PathEnd>0</PathEnd><PathRadiusOffset>0</PathRadiusOffset><PathRevolutions>0</PathRevolutions><PathScaleX>15</PathScaleX><PathScaleY>30</PathScaleY><PathShearX>0</PathShearX><PathShearY>0</PathShearY><PathSkew>0</PathSkew><PathTaperX>0</PathTaperX><PathTaperY>0</PathTaperY><PathTwist>0</PathTwist><PathTwistBegin>0</PathTwistBegin><PCode>9</PCode><ProfileBegin>0</ProfileBegin><ProfileEnd>0</ProfileEnd><ProfileHollow>47450</ProfileHollow><State>0</State><LastAttachPoint>0</LastAttachPoint><ProfileShape>Circle</ProfileShape><HollowShape>Same</HollowShape><SculptTexture><UUID>00000000-0000-0000-0000-000000000000</UUID></SculptTexture><SculptType>0</SculptType><FlexiSoftness>3</FlexiSoftness><FlexiTension>1</FlexiTension><FlexiDrag>2</FlexiDrag><FlexiGravity>0.3000002</FlexiGravity><FlexiWind>0</FlexiWind><FlexiForceX>0</FlexiForceX><FlexiForceY>0</FlexiForceY><FlexiForceZ>0</FlexiForceZ><LightColorR>0</LightColorR><LightColorG>0</LightColorG><LightColorB>0</LightColorB><LightColorA>1</LightColorA><LightRadius>0</LightRadius><LightCutoff>0</LightCutoff><LightFalloff>0</LightFalloff><LightIntensity>1</LightIntensity><FlexiEntry>true</FlexiEntry><LightEntry>false</LightEntry><SculptEntry>false</SculptEntry></Shape><Scale><X>0.003885937</X><Y>0.003518508</Y><Z>0.03758142</Z></Scale><SitTargetOrientation><X>0</X><Y>0</Y><Z>0</Z><W>1</W></SitTargetOrientation><SitTargetPosition><X>0</X><Y>0</Y><Z>0</Z></SitTargetPosition><SitTargetPositionLL><X>0</X><Y>0</Y><Z>0</Z></SitTargetPositionLL><SitTargetOrientationLL><X>0</X><Y>0</Y><Z>0</Z><W>1</W></SitTargetOrientationLL><ParentID>2472056875</ParentID><CreationDate>1267166485</CreationDate><Category>0</Category><SalePrice>10</SalePrice><ObjectSaleType>0</ObjectSaleType><OwnershipCost>0</OwnershipCost><GroupID><UUID>00000000-0000-0000-0000-000000000000</UUID></GroupID><OwnerID><UUID>b3560a21-af33-4a85-9723-5ee97fe8cdab</UUID></OwnerID><LastOwnerID><UUID>b3560a21-af33-4a85-9723-5ee97fe8cdab</UUID></LastOwnerID><BaseMask>647168</BaseMask><OwnerMask>647168</OwnerMask><GroupMask>0</GroupMask><EveryoneMask>557056</EveryoneMask><NextOwnerMask>581632</NextOwnerMask><Flags>Phantom</Flags><CollisionSound><UUID>00000000-0000-0000-0000-000000000000</UUID></CollisionSound><CollisionSoundVolume>0</CollisionSoundVolume><AttachedPos><X>0</X><Y>0</Y><Z>0</Z></AttachedPos><TextureAnimation></TextureAnimation><ParticleSystem></ParticleSystem><PayPrice0>-2</PayPrice0><PayPrice1>-2</PayPrice1><PayPrice2>-2</PayPrice2><PayPrice3>-2</PayPrice3><PayPrice4>-2</PayPrice4></SceneObjectPart></Part><Part><SceneObjectPart xmlns:xsi="http://www.w3.org/2001/XMLSchema-instance" xmlns:xsd="http://www.w3.org/2001/XMLSchema"><AllowedDrop>false</AllowedDrop><CreatorID><UUID>39508062-8358-4da5-88e9-5ce43992c071</UUID></CreatorID><CreatorData>http://users.osgrid.org/39508062-8358-4da5-88e9-5ce43992c071/;Dorothea Lundquist</CreatorData><FolderID><UUID>13088ab2-7cb5-4111-9150-cd32774c655c</UUID></FolderID><InventorySerial>5</InventorySerial><UUID><UUID>13088ab2-7cb5-4111-9150-cd32774c655c</UUID></UUID><LocalId>2472056879</LocalId><Name>D&amp;J Brocat Dress flex</Name><Material>3</Material><PassTouches>false</PassTouches><PassCollisions>false</PassCollisions><RegionHandle>7689984326456320</RegionHandle><ScriptAccessPin>0</ScriptAccessPin><GroupPosition><X>0.009746789</X><Y>0.003503702</Y><Z>-0.01127572</Z></GroupPosition><OffsetPosition><X>0.006179817</X><Y>-0.05923462</Y><Z>-0.0005493099</Z></OffsetPosition><RotationOffset><X>-0.5239314</X><Y>-0.474864</Y><Z>0.474864</Z><W>-0.5239316</W></RotationOffset><Velocity><X>0</X><Y>0</Y><Z>0</Z></Velocity><AngularVelocity><X>0</X><Y>0</Y><Z>0</Z></AngularVelocity><Acceleration><X>0</X><Y>0</Y><Z>0</Z></Acceleration><Description /><Color><R>0</R><G>0</G><B>0</B><A>255</A></Color><Text /><SitName /><TouchName /><LinkNum>5</LinkNum><ClickAction>0</ClickAction><Shape><ProfileCurve>0</ProfileCurve><TextureEntry>ddYCyNJCQQCQCsFGDPT8jAAAAAAAAQAAAP8AAACAPwAAAEBAAAAAAAAAAA3AACAAAAAIAAAAAAAAAAAAAAAAAAAAAAA=</TextureEntry><ExtraParams>ARAAEAAAAIqUZwAAAAAAAAAAAAAAAAA=</ExtraParams><PathBegin>0</PathBegin><PathCurve>128</PathCurve><PathEnd>0</PathEnd><PathRadiusOffset>0</PathRadiusOffset><PathRevolutions>0</PathRevolutions><PathScaleX>15</PathScaleX><PathScaleY>30</PathScaleY><PathShearX>0</PathShearX><PathShearY>0</PathShearY><PathSkew>0</PathSkew><PathTaperX>0</PathTaperX><PathTaperY>0</PathTaperY><PathTwist>0</PathTwist><PathTwistBegin>0</PathTwistBegin><PCode>9</PCode><ProfileBegin>0</ProfileBegin><ProfileEnd>0</ProfileEnd><ProfileHollow>47450</ProfileHollow><State>0</State><LastAttachPoint>0</LastAttachPoint><ProfileShape>Circle</ProfileShape><HollowShape>Same</HollowShape><SculptTexture><UUID>00000000-0000-0000-0000-000000000000</UUID></SculptTexture><SculptType>0</SculptType><FlexiSoftness>3</FlexiSoftness><FlexiTension>1</FlexiTension><FlexiDrag>2</FlexiDrag><FlexiGravity>0.3000002</FlexiGravity><FlexiWind>0</FlexiWind><FlexiForceX>0</FlexiForceX><FlexiForceY>0</FlexiForceY><FlexiForceZ>0</FlexiForceZ><LightColorR>0</LightColorR><LightColorG>0</LightColorG><LightColorB>0</LightColorB><LightColorA>1</LightColorA><LightRadius>0</LightRadius><LightCutoff>0</LightCutoff><LightFalloff>0</LightFalloff><LightIntensity>1</LightIntensity><FlexiEntry>true</FlexiEntry><LightEntry>false</LightEntry><SculptEntry>false</SculptEntry></Shape><Scale><X>0.003885937</X><Y>0.003518508</Y><Z>0.0418844</Z></Scale><SitTargetOrientation><X>0</X><Y>0</Y><Z>0</Z><W>1</W></SitTargetOrientation><SitTargetPosition><X>0</X><Y>0</Y><Z>0</Z></SitTargetPosition><SitTargetPositionLL><X>0</X><Y>0</Y><Z>0</Z></SitTargetPositionLL><SitTargetOrientationLL><X>0</X><Y>0</Y><Z>0</Z><W>1</W></SitTargetOrientationLL><ParentID>2472056875</ParentID><CreationDate>1267166485</CreationDate><Category>0</Category><SalePrice>10</SalePrice><ObjectSaleType>0</ObjectSaleType><OwnershipCost>0</OwnershipCost><GroupID><UUID>00000000-0000-0000-0000-000000000000</UUID></GroupID><OwnerID><UUID>b3560a21-af33-4a85-9723-5ee97fe8cdab</UUID></OwnerID><LastOwnerID><UUID>b3560a21-af33-4a85-9723-5ee97fe8cdab</UUID></LastOwnerID><BaseMask>647168</BaseMask><OwnerMask>647168</OwnerMask><GroupMask>0</GroupMask><EveryoneMask>557056</EveryoneMask><NextOwnerMask>581632</NextOwnerMask><Flags>Phantom</Flags><CollisionSound><UUID>00000000-0000-0000-0000-000000000000</UUID></CollisionSound><CollisionSoundVolume>0</CollisionSoundVolume><AttachedPos><X>0</X><Y>0</Y><Z>0</Z></AttachedPos><TextureAnimation></TextureAnimation><ParticleSystem></ParticleSystem><PayPrice0>-2</PayPrice0><PayPrice1>-2</PayPrice1><PayPrice2>-2</PayPrice2><PayPrice3>-2</PayPrice3><PayPrice4>-2</PayPrice4></SceneObjectPart></Part><Part><SceneObjectPart xmlns:xsi="http://www.w3.org/2001/XMLSchema-instance" xmlns:xsd="http://www.w3.org/2001/XMLSchema"><AllowedDrop>false</AllowedDrop><CreatorID><UUID>39508062-8358-4da5-88e9-5ce43992c071</UUID></CreatorID><CreatorData>http://users.osgrid.org/39508062-8358-4da5-88e9-5ce43992c071/;Dorothea Lundquist</CreatorData><FolderID><UUID>1dabcfde-1e37-4959-9b84-65327c1585a5</UUID></FolderID><InventorySerial>5</InventorySerial><UUID><UUID>1dabcfde-1e37-4959-9b84-65327c1585a5</UUID></UUID><LocalId>2472056880</LocalId><Name>D&amp;J Brocat Dress flex</Name><Material>3</Material><PassTouches>false</PassTouches><PassCollisions>false</PassCollisions><RegionHandle>7689984326456320</RegionHandle><ScriptAccessPin>0</ScriptAccessPin><GroupPosition><X>0.009746789</X><Y>0.003503702</Y><Z>-0.01127572</Z></GroupPosition><OffsetPosition><X>0.001998909</X><Y>-0.06195068</Y><Z>-0.0005493092</Z></OffsetPosition><RotationOffset><X>-0.5239314</X><Y>-0.474864</Y><Z>0.474864</Z><W>-0.5239316</W></RotationOffset><Velocity><X>0</X><Y>0</Y><Z>0</Z></Velocity><AngularVelocity><X>0</X><Y>0</Y><Z>0</Z></AngularVelocity><Acceleration><X>0</X><Y>0</Y><Z>0</Z></Acceleration><Description /><Color><R>0</R><G>0</G><B>0</B><A>255</A></Color><Text /><SitName /><TouchName /><LinkNum>6</LinkNum><ClickAction>0</ClickAction><Shape><ProfileCurve>0</ProfileCurve><TextureEntry>ddYCyNJCQQCQCsFGDPT8jAAAAAAAAQAAAP8AAACAPwAAAEBAAAAAAAAAAA3AACAAAAAIAAAAAAAAAAAAAAAAAAAAAAA=</TextureEntry><ExtraParams>ARAAEAAAAIqUZwAAAAAAAAAAAAAAAAA=</ExtraParams><PathBegin>0</PathBegin><PathCurve>128</PathCurve><PathEnd>0</PathEnd><PathRadiusOffset>0</PathRadiusOffset><PathRevolutions>0</PathRevolutions><PathScaleX>15</PathScaleX><PathScaleY>30</PathScaleY><PathShearX>0</PathShearX><PathShearY>0</PathShearY><PathSkew>0</PathSkew><PathTaperX>0</PathTaperX><PathTaperY>0</PathTaperY><PathTwist>0</PathTwist><PathTwistBegin>0</PathTwistBegin><PCode>9</PCode><ProfileBegin>0</ProfileBegin><ProfileEnd>0</ProfileEnd><ProfileHollow>47450</ProfileHollow><State>0</State><LastAttachPoint>0</LastAttachPoint><ProfileShape>Circle</ProfileShape><HollowShape>Same</HollowShape><SculptTexture><UUID>00000000-0000-0000-0000-000000000000</UUID></SculptTexture><SculptType>0</SculptType><FlexiSoftness>3</FlexiSoftness><FlexiTension>1</FlexiTension><FlexiDrag>2</FlexiDrag><FlexiGravity>0.3000002</FlexiGravity><FlexiWind>0</FlexiWind><FlexiForceX>0</FlexiForceX><FlexiForceY>0</FlexiForceY><FlexiForceZ>0</FlexiForceZ><LightColorR>0</LightColorR><LightColorG>0</LightColorG><LightColorB>0</LightColorB><LightColorA>1</LightColorA><LightRadius>0</LightRadius><LightCutoff>0</LightCutoff><LightFalloff>0</LightFalloff><LightIntensity>1</LightIntensity><FlexiEntry>true</FlexiEntry><LightEntry>false</LightEntry><SculptEntry>false</SculptEntry></Shape><Scale><X>0.003885937</X><Y>0.003518508</Y><Z>0.04643152</Z></Scale><SitTargetOrientation><X>0</X><Y>0</Y><Z>0</Z><W>1</W></SitTargetOrientation><SitTargetPosition><X>0</X><Y>0</Y><Z>0</Z></SitTargetPosition><SitTargetPositionLL><X>0</X><Y>0</Y><Z>0</Z></SitTargetPositionLL><SitTargetOrientationLL><X>0</X><Y>0</Y><Z>0</Z><W>1</W></SitTargetOrientationLL><ParentID>2472056875</ParentID><CreationDate>1267166485</CreationDate><Category>0</Category><SalePrice>10</SalePrice><ObjectSaleType>0</ObjectSaleType><OwnershipCost>0</OwnershipCost><GroupID><UUID>00000000-0000-0000-0000-000000000000</UUID></GroupID><OwnerID><UUID>b3560a21-af33-4a85-9723-5ee97fe8cdab</UUID></OwnerID><LastOwnerID><UUID>b3560a21-af33-4a85-9723-5ee97fe8cdab</UUID></LastOwnerID><BaseMask>647168</BaseMask><OwnerMask>647168</OwnerMask><GroupMask>0</GroupMask><EveryoneMask>557056</EveryoneMask><NextOwnerMask>581632</NextOwnerMask><Flags>Phantom</Flags><CollisionSound><UUID>00000000-0000-0000-0000-000000000000</UUID></CollisionSound><CollisionSoundVolume>0</CollisionSoundVolume><AttachedPos><X>0</X><Y>0</Y><Z>0</Z></AttachedPos><TextureAnimation></TextureAnimation><ParticleSystem></ParticleSystem><PayPrice0>-2</PayPrice0><PayPrice1>-2</PayPrice1><PayPrice2>-2</PayPrice2><PayPrice3>-2</PayPrice3><PayPrice4>-2</PayPrice4></SceneObjectPart></Part><Part><SceneObjectPart xmlns:xsi="http://www.w3.org/2001/XMLSchema-instance" xmlns:xsd="http://www.w3.org/2001/XMLSchema"><AllowedDrop>false</AllowedDrop><CreatorID><UUID>39508062-8358-4da5-88e9-5ce43992c071</UUID></CreatorID><CreatorData>http://users.osgrid.org/39508062-8358-4da5-88e9-5ce43992c071/;Dorothea Lundquist</CreatorData><FolderID><UUID>fa6c022e-3e3a-4906-b1c7-d81d8689019f</UUID></FolderID><InventorySerial>4</InventorySerial><UUID><UUID>fa6c022e-3e3a-4906-b1c7-d81d8689019f</UUID></UUID><LocalId>2472056881</LocalId><Name>D&amp;J Brocat Dress flex</Name><Material>3</Material><PassTouches>false</PassTouches><PassCollisions>false</PassCollisions><RegionHandle>7689984326456320</RegionHandle><ScriptAccessPin>0</ScriptAccessPin><GroupPosition><X>0.009746789</X><Y>0.003503702</Y><Z>-0.01127572</Z></GroupPosition><OffsetPosition><X>-0.001892083</X><Y>-0.05926514</Y><Z>-0.0005493089</Z></OffsetPosition><RotationOffset><X>-0.5239314</X><Y>-0.474864</Y><Z>0.474864</Z><W>-0.5239316</W></RotationOffset><Velocity><X>0</X><Y>0</Y><Z>0</Z></Velocity><AngularVelocity><X>0</X><Y>0</Y><Z>0</Z></AngularVelocity><Acceleration><X>0</X><Y>0</Y><Z>0</Z></Acceleration><Description /><Color><R>0</R><G>0</G><B>0</B><A>255</A></Color><Text /><SitName /><TouchName /><LinkNum>7</LinkNum><ClickAction>0</ClickAction><Shape><ProfileCurve>0</ProfileCurve><TextureEntry>ddYCyNJCQQCQCsFGDPT8jAAAAAAAAQAAAP8AAACAPwAAAEBAAAAAAAAAAA3AACAAAAAIAAAAAAAAAAAAAAAAAAAAAAA=</TextureEntry><ExtraParams>ARAAEAAAAIqUZwAAAAAAAAAAAAAAAAA=</ExtraParams><PathBegin>0</PathBegin><PathCurve>128</PathCurve><PathEnd>0</PathEnd><PathRadiusOffset>0</PathRadiusOffset><PathRevolutions>0</PathRevolutions><PathScaleX>15</PathScaleX><PathScaleY>30</PathScaleY><PathShearX>0</PathShearX><PathShearY>0</PathShearY><PathSkew>0</PathSkew><PathTaperX>0</PathTaperX><PathTaperY>0</PathTaperY><PathTwist>0</PathTwist><PathTwistBegin>0</PathTwistBegin><PCode>9</PCode><ProfileBegin>0</ProfileBegin><ProfileEnd>0</ProfileEnd><ProfileHollow>47450</ProfileHollow><State>0</State><LastAttachPoint>0</LastAttachPoint><ProfileShape>Circle</ProfileShape><HollowShape>Same</HollowShape><SculptTexture><UUID>00000000-0000-0000-0000-000000000000</UUID></SculptTexture><SculptType>0</SculptType><FlexiSoftness>3</FlexiSoftness><FlexiTension>1</FlexiTension><FlexiDrag>2</FlexiDrag><FlexiGravity>0.3000002</FlexiGravity><FlexiWind>0</FlexiWind><FlexiForceX>0</FlexiForceX><FlexiForceY>0</FlexiForceY><FlexiForceZ>0</FlexiForceZ><LightColorR>0</LightColorR><LightColorG>0</LightColorG><LightColorB>0</LightColorB><LightColorA>1</LightColorA><LightRadius>0</LightRadius><LightCutoff>0</LightCutoff><LightFalloff>0</LightFalloff><LightIntensity>1</LightIntensity><FlexiEntry>true</FlexiEntry><LightEntry>false</LightEntry><SculptEntry>false</SculptEntry></Shape><Scale><X>0.003885937</X><Y>0.003518508</Y><Z>0.04191492</Z></Scale><SitTargetOrientation><X>0</X><Y>0</Y><Z>0</Z><W>1</W></SitTargetOrientation><SitTargetPosition><X>0</X><Y>0</Y><Z>0</Z></SitTargetPosition><SitTargetPositionLL><X>0</X><Y>0</Y><Z>0</Z></SitTargetPositionLL><SitTargetOrientationLL><X>0</X><Y>0</Y><Z>0</Z><W>1</W></SitTargetOrientationLL><ParentID>2472056875</ParentID><CreationDate>1267166485</CreationDate><Category>0</Category><SalePrice>10</SalePrice><ObjectSaleType>0</ObjectSaleType><OwnershipCost>0</OwnershipCost><GroupID><UUID>00000000-0000-0000-0000-000000000000</UUID></GroupID><OwnerID><UUID>b3560a21-af33-4a85-9723-5ee97fe8cdab</UUID></OwnerID><LastOwnerID><UUID>b3560a21-af33-4a85-9723-5ee97fe8cdab</UUID></LastOwnerID><BaseMask>647168</BaseMask><OwnerMask>647168</OwnerMask><GroupMask>0</GroupMask><EveryoneMask>557056</EveryoneMask><NextOwnerMask>581632</NextOwnerMask><Flags>Phantom</Flags><CollisionSound><UUID>00000000-0000-0000-0000-000000000000</UUID></CollisionSound><CollisionSoundVolume>0</CollisionSoundVolume><AttachedPos><X>0</X><Y>0</Y><Z>0</Z></AttachedPos><TextureAnimation></TextureAnimation><ParticleSystem></ParticleSystem><PayPrice0>-2</PayPrice0><PayPrice1>-2</PayPrice1><PayPrice2>-2</PayPrice2><PayPrice3>-2</PayPrice3><PayPrice4>-2</PayPrice4></SceneObjectPart></Part><Part><SceneObjectPart xmlns:xsi="http://www.w3.org/2001/XMLSchema-instance" xmlns:xsd="http://www.w3.org/2001/XMLSchema"><AllowedDrop>false</AllowedDrop><CreatorID><UUID>39508062-8358-4da5-88e9-5ce43992c071</UUID></CreatorID><CreatorData>http://users.osgrid.org/39508062-8358-4da5-88e9-5ce43992c071/;Dorothea Lundquist</CreatorData><FolderID><UUID>34b3556f-5d36-4709-b27b-4e764479021c</UUID></FolderID><InventorySerial>5</InventorySerial><UUID><UUID>34b3556f-5d36-4709-b27b-4e764479021c</UUID></UUID><LocalId>2472056882</LocalId><Name>D&amp;J Brocat Dress flex</Name><Material>3</Material><PassTouches>false</PassTouches><PassCollisions>false</PassCollisions><RegionHandle>7689984326456320</RegionHandle><ScriptAccessPin>0</ScriptAccessPin><GroupPosition><X>0.009746789</X><Y>0.003503702</Y><Z>-0.01127572</Z></GroupPosition><OffsetPosition><X>-0.00457763</X><Y>-0.05535889</Y><Z>-0.0005493088</Z></OffsetPosition><RotationOffset><X>-0.5239314</X><Y>-0.474864</Y><Z>0.474864</Z><W>-0.5239316</W></RotationOffset><Velocity><X>0</X><Y>0</Y><Z>0</Z></Velocity><AngularVelocity><X>0</X><Y>0</Y><Z>0</Z></AngularVelocity><Acceleration><X>0</X><Y>0</Y><Z>0</Z></Acceleration><Description /><Color><R>0</R><G>0</G><B>0</B><A>255</A></Color><Text /><SitName /><TouchName /><LinkNum>8</LinkNum><ClickAction>0</ClickAction><Shape><ProfileCurve>0</ProfileCurve><TextureEntry>ddYCyNJCQQCQCsFGDPT8jAAAAAAAAQAAAP8AAACAPwAAAEBAAAAAAAAAAA3AACAAAAAIAAAAAAAAAAAAAAAAAAAAAAA=</TextureEntry><ExtraParams>ARAAEAAAAIqUZwAAAAAAAAAAAAAAAAA=</ExtraParams><PathBegin>0</PathBegin><PathCurve>128</PathCurve><PathEnd>0</PathEnd><PathRadiusOffset>0</PathRadiusOffset><PathRevolutions>0</PathRevolutions><PathScaleX>15</PathScaleX><PathScaleY>30</PathScaleY><PathShearX>0</PathShearX><PathShearY>0</PathShearY><PathSkew>0</PathSkew><PathTaperX>0</PathTaperX><PathTaperY>0</PathTaperY><PathTwist>0</PathTwist><PathTwistBegin>0</PathTwistBegin><PCode>9</PCode><ProfileBegin>0</ProfileBegin><ProfileEnd>0</ProfileEnd><ProfileHollow>47450</ProfileHollow><State>0</State><LastAttachPoint>0</LastAttachPoint><ProfileShape>Circle</ProfileShape><HollowShape>Same</HollowShape><SculptTexture><UUID>00000000-0000-0000-0000-000000000000</UUID></SculptTexture><SculptType>0</SculptType><FlexiSoftness>3</FlexiSoftness><FlexiTension>1</FlexiTension><FlexiDrag>2</FlexiDrag><FlexiGravity>0.3000002</FlexiGravity><FlexiWind>0</FlexiWind><FlexiForceX>0</FlexiForceX><FlexiForceY>0</FlexiForceY><FlexiForceZ>0</FlexiForceZ><LightColorR>0</LightColorR><LightColorG>0</LightColorG><LightColorB>0</LightColorB><LightColorA>1</LightColorA><LightRadius>0</LightRadius><LightCutoff>0</LightCutoff><LightFalloff>0</LightFalloff><LightIntensity>1</LightIntensity><FlexiEntry>true</FlexiEntry><LightEntry>false</LightEntry><SculptEntry>false</SculptEntry></Shape><Scale><X>0.003885937</X><Y>0.003518508</Y><Z>0.03758142</Z></Scale><SitTargetOrientation><X>0</X><Y>0</Y><Z>0</Z><W>1</W></SitTargetOrientation><SitTargetPosition><X>0</X><Y>0</Y><Z>0</Z></SitTargetPosition><SitTargetPositionLL><X>0</X><Y>0</Y><Z>0</Z></SitTargetPositionLL><SitTargetOrientationLL><X>0</X><Y>0</Y><Z>0</Z><W>1</W></SitTargetOrientationLL><ParentID>2472056875</ParentID><CreationDate>1267166485</CreationDate><Category>0</Category><SalePrice>10</SalePrice><ObjectSaleType>0</ObjectSaleType><OwnershipCost>0</OwnershipCost><GroupID><UUID>00000000-0000-0000-0000-000000000000</UUID></GroupID><OwnerID><UUID>b3560a21-af33-4a85-9723-5ee97fe8cdab</UUID></OwnerID><LastOwnerID><UUID>b3560a21-af33-4a85-9723-5ee97fe8cdab</UUID></LastOwnerID><BaseMask>647168</BaseMask><OwnerMask>647168</OwnerMask><GroupMask>0</GroupMask><EveryoneMask>557056</EveryoneMask><NextOwnerMask>581632</NextOwnerMask><Flags>Phantom</Flags><CollisionSound><UUID>00000000-0000-0000-0000-000000000000</UUID></CollisionSound><CollisionSoundVolume>0</CollisionSoundVolume><AttachedPos><X>0</X><Y>0</Y><Z>0</Z></AttachedPos><TextureAnimation></TextureAnimation><ParticleSystem></ParticleSystem><PayPrice0>-2</PayPrice0><PayPrice1>-2</PayPrice1><PayPrice2>-2</PayPrice2><PayPrice3>-2</PayPrice3><PayPrice4>-2</PayPrice4></SceneObjectPart></Part><Part><SceneObjectPart xmlns:xsi="http://www.w3.org/2001/XMLSchema-instance" xmlns:xsd="http://www.w3.org/2001/XMLSchema"><AllowedDrop>false</AllowedDrop><CreatorID><UUID>39508062-8358-4da5-88e9-5ce43992c071</UUID></CreatorID><CreatorData>http://users.osgrid.org/39508062-8358-4da5-88e9-5ce43992c071/;Dorothea Lundquist</CreatorData><FolderID><UUID>50cc7872-5f88-4f12-83d9-e2ac94987e29</UUID></FolderID><InventorySerial>5</InventorySerial><UUID><UUID>50cc7872-5f88-4f12-83d9-e2ac94987e29</UUID></UUID><LocalId>2472056883</LocalId><Name>D&amp;J Brocat Dress flex</Name><Material>3</Material><PassTouches>false</PassTouches><PassCollisions>false</PassCollisions><RegionHandle>7689984326456320</RegionHandle><ScriptAccessPin>0</ScriptAccessPin><GroupPosition><X>0.009746789</X><Y>0.003503702</Y><Z>-0.01127572</Z></GroupPosition><OffsetPosition><X>-0.007850642</X><Y>-0.05114746</Y><Z>-0.0005493087</Z></OffsetPosition><RotationOffset><X>-0.5239314</X><Y>-0.474864</Y><Z>0.474864</Z><W>-0.5239316</W></RotationOffset><Velocity><X>0</X><Y>0</Y><Z>0</Z></Velocity><AngularVelocity><X>0</X><Y>0</Y><Z>0</Z></AngularVelocity><Acceleration><X>0</X><Y>0</Y><Z>0</Z></Acceleration><Description /><Color><R>0</R><G>0</G><B>0</B><A>255</A></Color><Text /><SitName /><TouchName /><LinkNum>9</LinkNum><ClickAction>0</ClickAction><Shape><ProfileCurve>0</ProfileCurve><TextureEntry>ddYCyNJCQQCQCsFGDPT8jAAAAAAAAQAAAP8AAACAPwAAAEBAAAAAAAAAAA3AACAAAAAIAAAAAAAAAAAAAAAAAAAAAAA=</TextureEntry><ExtraParams>ARAAEAAAAIqUZwAAAAAAAAAAAAAAAAA=</ExtraParams><PathBegin>0</PathBegin><PathCurve>128</PathCurve><PathEnd>0</PathEnd><PathRadiusOffset>0</PathRadiusOffset><PathRevolutions>0</PathRevolutions><PathScaleX>15</PathScaleX><PathScaleY>30</PathScaleY><PathShearX>0</PathShearX><PathShearY>0</PathShearY><PathSkew>0</PathSkew><PathTaperX>0</PathTaperX><PathTaperY>0</PathTaperY><PathTwist>0</PathTwist><PathTwistBegin>0</PathTwistBegin><PCode>9</PCode><ProfileBegin>0</ProfileBegin><ProfileEnd>0</ProfileEnd><ProfileHollow>47450</ProfileHollow><State>0</State><LastAttachPoint>0</LastAttachPoint><ProfileShape>Circle</ProfileShape><HollowShape>Same</HollowShape><SculptTexture><UUID>00000000-0000-0000-0000-000000000000</UUID></SculptTexture><SculptType>0</SculptType><FlexiSoftness>3</FlexiSoftness><FlexiTension>1</FlexiTension><FlexiDrag>2</FlexiDrag><FlexiGravity>0.3000002</FlexiGravity><FlexiWind>0</FlexiWind><FlexiForceX>0</FlexiForceX><FlexiForceY>0</FlexiForceY><FlexiForceZ>0</FlexiForceZ><LightColorR>0</LightColorR><LightColorG>0</LightColorG><LightColorB>0</LightColorB><LightColorA>1</LightColorA><LightRadius>0</LightRadius><LightCutoff>0</LightCutoff><LightFalloff>0</LightFalloff><LightIntensity>1</LightIntensity><FlexiEntry>true</FlexiEntry><LightEntry>false</LightEntry><SculptEntry>false</SculptEntry></Shape><Scale><X>0.003885937</X><Y>0.003518508</Y><Z>0.03758142</Z></Scale><SitTargetOrientation><X>0</X><Y>0</Y><Z>0</Z><W>1</W></SitTargetOrientation><SitTargetPosition><X>0</X><Y>0</Y><Z>0</Z></SitTargetPosition><SitTargetPositionLL><X>0</X><Y>0</Y><Z>0</Z></SitTargetPositionLL><SitTargetOrientationLL><X>0</X><Y>0</Y><Z>0</Z><W>1</W></SitTargetOrientationLL><ParentID>2472056875</ParentID><CreationDate>1267166485</CreationDate><Category>0</Category><SalePrice>10</SalePrice><ObjectSaleType>0</ObjectSaleType><OwnershipCost>0</OwnershipCost><GroupID><UUID>00000000-0000-0000-0000-000000000000</UUID></GroupID><OwnerID><UUID>b3560a21-af33-4a85-9723-5ee97fe8cdab</UUID></OwnerID><LastOwnerID><UUID>b3560a21-af33-4a85-9723-5ee97fe8cdab</UUID></LastOwnerID><BaseMask>647168</BaseMask><OwnerMask>647168</OwnerMask><GroupMask>0</GroupMask><EveryoneMask>557056</EveryoneMask><NextOwnerMask>581632</NextOwnerMask><Flags>Phantom</Flags><CollisionSound><UUID>00000000-0000-0000-0000-000000000000</UUID></CollisionSound><CollisionSoundVolume>0</CollisionSoundVolume><AttachedPos><X>0</X><Y>0</Y><Z>0</Z></AttachedPos><TextureAnimation></TextureAnimation><ParticleSystem></ParticleSystem><PayPrice0>-2</PayPrice0><PayPrice1>-2</PayPrice1><PayPrice2>-2</PayPrice2><PayPrice3>-2</PayPrice3><PayPrice4>-2</PayPrice4></SceneObjectPart></Part></OtherParts></SceneObjectGroup> 